Workbook

Sheet Final
A1: Product Name | B1: Product Name | C1: Category | D1: 3 month revenue | E1: MRP Including GST | F1: MRP without GST | G1: Returns | H1: Discounts | I1: Net Revenue | J1: Cost of Material | K1: Gross margin | L1: Packaging Secondary | M1: Razorpay Deduction | N1: Shipping to Customer | O1: COD Costs | P1: CM 1 | Q1: Marketing Cost | R1: Units sold | S1: CM 2 | T1: CM 2 % | U1: Overheads | V1: EBIDTA | W1: EBIDTA %
A2: magic paint dust | B2: Magic Paint Dust – Baby’s First Painting Kit | C2: Magic paint dust | D2: {=XLOOKUP(B2,'Calculations As per GA Data'!B20:B141,'Calculations As per GA Data'!G20:G141)} -> 192044 | E2: 899 | F2: =E2/1.18 -> 761.86441 | G2: 4.75 | H2: {=XLOOKUP(B2,'Discount calculation'!A:A,'Discount calculation'!D:D)} -> 11.111156 | I2: =F2-SUM(G2:H2) -> 746.00325 | J2: 126.3 | K2: =I2-J2 -> 619.70325 | L2: 12.5 | M2: 7.52 | N2: 150.51244 | O2: 4.55 | P2: =K2-SUM(L2:O2) -> 444.62081 | Q2: {=XLOOKUP(B2,'Calculations As per GA Data'!B20:B141,'Calculations As per GA Data'!J20:J141)} -> 1098.7847 | R2: {=XLOOKUP(B2,'Calculations As per GA Data'!B20:B141,'Calculations As per GA Data'!F20:F141)} -> 221 | S2: =P2-Q2 -> -654.16393 | T2: =S2/I2 -> -0.87689153 | U2: 229 | V2: =S2-U2 -> -883.16393 | W2: =V2/I2 -> -1.1838607
A3: Playdough | B3: dabble Sensory Playdough | C3: Playdough | D3: {=XLOOKUP(B3,'Calculations As per GA Data'!B21:B142,'Calculations As per GA Data'!G21:G142)} -> 190336 | E3: 899 | F3: =E3/1.18 -> 761.86441 | G3: 4.75 | H3: {=XLOOKUP(B3,'Discount calculation'!A:A,'Discount calculation'!D:D)} -> 11.273119 | I3: =F3-SUM(G3:H3) -> 745.84129 | J3: 124.49 | K3: =I3-J3 -> 621.35129 | L3: 12.5 | M3: 7.52 | N3: 167.52374 | O3: 4.55 | P3: =K3-SUM(L3:O3) -> 429.25755 | Q3: {=XLOOKUP(B3,'Calculations As per GA Data'!B21:B142,'Calculations As per GA Data'!J21:J142)} -> 1038.5119 | R3: {=XLOOKUP(B3,'Calculations As per GA Data'!B21:B142,'Calculations As per GA Data'!F21:F142)} -> 214 | S3: =P3-Q3 -> -609.25437 | T3: =S3/I3 -> -0.81686866 | U3: 229 | V3: =S3-U3 -> -838.25437 | W3: =V3/I3 -> -1.1239045
A4: FP8+CB | B4: Dabble Finger Painting Fun Pack | C4: Combo | D4: {=XLOOKUP(B4,'Calculations As per GA Data'!B22:B143,'Calculations As per GA Data'!G22:G143)} -> 157681 | E4: 1348 | F4: =E4/1.18 -> 1142.3729 | G4: 4.75 | H4: {=XLOOKUP(B4,'Discount calculation'!A:A,'Discount calculation'!D:D)} -> 17.370523 | I4: =F4-SUM(G4:H4) -> 1120.2524 | J4: 238.12 | K4: =I4-J4 -> 882.13236 | L4: 14.5 | M4: 7.52 | N4: 189.105 | O4: 4.55 | P4: =K4-SUM(L4:O4) -> 666.45736 | Q4: {=XLOOKUP(B4,'Calculations As per GA Data'!B22:B143,'Calculations As per GA Data'!J22:J143)} -> 651.96262 | R4: {=XLOOKUP(B4,'Calculations As per GA Data'!B22:B143,'Calculations As per GA Data'!F22:F143)} -> 122 | S4: =P4-Q4 -> 14.494743 | T4: =S4/I4 -> 0.012938819 | U4: 229 | V4: =S4-U4 -> -214.50526 | W4: =V4/I4 -> -0.19147941
A5: Canvas Kit | B5: Babyâ€™s first handprint and footprint kit | C5: Canvas Kit | D5: {=XLOOKUP(B5,'Calculations As per GA Data'!B23:B144,'Calculations As per GA Data'!G23:G144)} -> 113540 | E5: 649 | F5: =E5/1.18 -> 550 | G5: 4.75 | H5: {=XLOOKUP(B5,'Discount calculation'!A:A,'Discount calculation'!D:D)} -> 8.1738809 | I5: =F5-SUM(G5:H5) -> 537.07612 | J5: 70.1 | K5: =I5-J5 -> 466.97612 | L5: 12.5 | M5: 7.52 | N5: 171.34694 | O5: 4.55 | P5: =K5-SUM(L5:O5) -> 271.05918 | Q5: {=XLOOKUP(B5,'Calculations As per GA Data'!B23:B144,'Calculations As per GA Data'!J23:J144)} -> 1115.285 | R5: {=XLOOKUP(B5,'Calculations As per GA Data'!B23:B144,'Calculations As per GA Data'!F23:F144)} -> 160 | S5: =P5-Q5 -> -844.22578 | T5: =S5/I5 -> -1.5718922 | U5: 229 | V5: =S5-U5 -> -1073.2258 | W5: =V5/I5 -> -1.998275
A6: SFP | B6: Mini Starter Finger Painting Fun Pack | C6: SFP | D6: {=XLOOKUP(B6,'Calculations As per GA Data'!B24:B145,'Calculations As per GA Data'!G24:G145)} -> 101319 | E6: 599 | F6: =E6/1.18 -> 507.62712 | G6: 4.75 | H6: {=XLOOKUP(B6,'Discount calculation'!A:A,'Discount calculation'!D:D)} -> 6.5260964 | I6: =F6-SUM(G6:H6) -> 496.35102 | J6: 89.33 | K6: =I6-J6 -> 407.02102 | L6: 6.5 | M6: 7.52 | N6: 176.04228 | O6: 4.55 | P6: =K6-SUM(L6:O6) -> 212.40874 | Q6: {=XLOOKUP(B6,'Calculations As per GA Data'!B24:B145,'Calculations As per GA Data'!J24:J145)} -> 460.17557 | R6: {=XLOOKUP(B6,'Calculations As per GA Data'!B24:B145,'Calculations As per GA Data'!F24:F145)} -> 171 | S6: =P6-Q6 -> -247.76682 | T6: =S6/I6 -> -0.49917662 | U6: 229 | V6: =S6-U6 -> -476.76682 | W6: =V6/I6 -> -0.96054365
A7: SFP+JB | B7: Babyâ€™s Starter Painting + Jumbo Brush Combo Kit | C7: Combo | D7: {=XLOOKUP(B7,'Calculations As per GA Data'!B25:B146,'Calculations As per GA Data'!G25:G146)} -> 79281 | E7: 1098 | F7: =E7/1.18 -> 930.50847 | G7: 4.75 | H7: {=XLOOKUP(B7,'Discount calculation'!A:A,'Discount calculation'!D:D)} -> 12.236439 | I7: =F7-SUM(G7:H7) -> 913.52204 | J7: 117.5 | K7: =I7-J7 -> 796.02204 | L7: 11.5 | M7: 7.52 | N7: 153.54427 | O7: 4.55 | P7: =K7-SUM(L7:O7) -> 618.90777 | Q7: {=XLOOKUP(B7,'Calculations As per GA Data'!B25:B146,'Calculations As per GA Data'!J25:J146)} -> 477.93882 | R7: {=XLOOKUP(B7,'Calculations As per GA Data'!B25:B146,'Calculations As per GA Data'!F25:F146)} -> 75 | S7: =P7-Q7 -> 140.96895 | T7: =S7/I7 -> 0.15431368 | U7: 229 | V7: =S7-U7 -> -88.03105 | W7: =V7/I7 -> -0.096364452
A8: B3 | B8: Dabble Playart Chunkies | C8: Caryons | D8: {=XLOOKUP(B8,'Calculations As per GA Data'!B26:B147,'Calculations As per GA Data'!G26:G147)} -> 70820.999 | E8: 549 | F8: =E8/1.18 -> 465.25424 | G8: 4.75 | H8: {=XLOOKUP(B8,'Discount calculation'!A:A,'Discount calculation'!D:D)} -> 6.0704762 | I8: =F8-SUM(G8:H8) -> 454.43376 | J8: 65.5 | K8: =I8-J8 -> 388.93376 | L8: 5 | M8: 7.52 | N8: 96.507674 | O8: 4.55 | P8: =K8-SUM(L8:O8) -> 275.35609 | Q8: {=XLOOKUP(B8,'Calculations As per GA Data'!B26:B147,'Calculations As per GA Data'!J26:J147)} -> 914.47348 | R8: {=XLOOKUP(B8,'Calculations As per GA Data'!B26:B147,'Calculations As per GA Data'!F26:F147)} -> 129 | S8: =P8-Q8 -> -639.1174 | T8: =S8/I8 -> -1.4064039 | U8: 229 | V8: =S8-U8 -> -868.1174 | W8: =V8/I8 -> -1.9103277
A9: FP8, B8, CB | B9: Little Artist Combo Kit | C9: Combo | D9: {=XLOOKUP(B9,'Calculations As per GA Data'!B27:B148,'Calculations As per GA Data'!G27:G148)} -> 81477 | E9: 1797 | F9: =E9/1.18 -> 1522.8814 | G9: 4.75 | H9: {=XLOOKUP(B9,'Discount calculation'!A:A,'Discount calculation'!D:D)} -> 30.1056 | I9: =F9-SUM(G9:H9) -> 1488.0258 | J9: 254.99 | K9: =I9-J9 -> 1233.0358 | L9: 19.5 | M9: 7.52 | N9: 170.99915 | O9: 4.55 | P9: =K9-SUM(L9:O9) -> 1030.4666 | Q9: {=XLOOKUP(B9,'Calculations As per GA Data'!B27:B148,'Calculations As per GA Data'!J27:J148)} -> 804.59701 | R9: {=XLOOKUP(B9,'Calculations As per GA Data'!B27:B148,'Calculations As per GA Data'!F27:F148)} -> 47 | S9: =P9-Q9 -> 225.86959 | T9: =S9/I9 -> 0.15179145 | U9: 229 | V9: =S9-U9 -> -3.1304073 | W9: =V9/I9 -> -0.002103732
A10: SFP+CB | B10: Dabble Starter Painting + Chubby Brush Combo Kit | C10: Combo | D10: {=XLOOKUP(B10,'Calculations As per GA Data'!B28:B149,'Calculations As per GA Data'!G28:G149)} -> 90842 | E10: 1048 | F10: =E10/1.18 -> 888.13559 | G10: 4.75 | H10: {=XLOOKUP(B10,'Discount calculation'!A:A,'Discount calculation'!D:D)} -> 11.805471 | I10: =F10-SUM(G10:H10) -> 871.58012 | J10: 165.73 | K10: =I10-J10 -> 705.85012 | L10: 11.5 | M10: 7.52 | N10: 142.47578 | O10: 4.55 | P10: =K10-SUM(L10:O10) -> 539.80434 | Q10: {=XLOOKUP(B10,'Calculations As per GA Data'!B28:B149,'Calculations As per GA Data'!J28:J149)} -> 503.23258 | R10: {=XLOOKUP(B10,'Calculations As per GA Data'!B28:B149,'Calculations As per GA Data'!F28:F149)} -> 90 | S10: =P10-Q10 -> 36.571765 | T10: =S10/I10 -> 0.041960301 | U10: 229 | V10: =S10-U10 -> -192.42824 | W10: =V10/I10 -> -0.22078089
A11: FP3 | B11: Dabble Finger Paints For Toddlers | C11: FP3 | D11: {=XLOOKUP(B11,'Calculations As per GA Data'!B29:B150,'Calculations As per GA Data'!G29:G150)} -> 63589 | E11: 649 | F11: =E11/1.18 -> 550 | G11: 4.75 | H11: {=XLOOKUP(B11,'Discount calculation'!A:A,'Discount calculation'!D:D)} -> 9.4861538 | I11: =F11-SUM(G11:H11) -> 535.76385 | J11: 62.96 | K11: =I11-J11 -> 472.80385 | L11: 6.5 | M11: 7.52 | N11: 139.41584 | O11: 4.55 | P11: =K11-SUM(L11:O11) -> 314.818 | Q11: {=XLOOKUP(B11,'Calculations As per GA Data'!B29:B150,'Calculations As per GA Data'!J29:J150)} -> 478.36493 | R11: {=XLOOKUP(B11,'Calculations As per GA Data'!B29:B150,'Calculations As per GA Data'!F29:F150)} -> 101 | S11: =P11-Q11 -> -163.54693 | T11: =S11/I11 -> -0.30525935 | U11: 229 | V11: =S11-U11 -> -392.54693 | W11: =V11/I11 -> -0.73268648
A12: AR | B12: Dabble Art Roll | C12: AR | D12: {=XLOOKUP(B12,'Calculations As per GA Data'!B30:B151,'Calculations As per GA Data'!G30:G151)} -> 50328 | E12: 699 | F12: =E12/1.18 -> 592.37288 | G12: 4.75 | H12: {=XLOOKUP(B12,'Discount calculation'!A:A,'Discount calculation'!D:D)} -> 9.6347942 | I12: =F12-SUM(G12:H12) -> 577.98809 | J12: 131 | K12: =I12-J12 -> 446.98809 | L12: 8.5 | M12: 7.52 | N12: 145.18389 | O12: 4.55 | P12: =K12-SUM(L12:O12) -> 281.2342 | Q12: {=XLOOKUP(B12,'Calculations As per GA Data'!B30:B151,'Calculations As per GA Data'!J30:J151)} -> 338.82314 | R12: {=XLOOKUP(B12,'Calculations As per GA Data'!B30:B151,'Calculations As per GA Data'!F30:F151)} -> 72 | S12: =P12-Q12 -> -57.588938 | T12: =S12/I12 -> -0.099636894 | U12: 229 | V12: =S12-U12 -> -286.58894 | W12: =V12/I12 -> -0.49583883
A13: magic paint dust+jb | B13: Magic Paint Dust + Jumbo Brush Combo Kit â€“ Babyâ€™s First Painting Kit | C13: Combo | D13: {=XLOOKUP(B13,'Calculations As per GA Data'!B31:B152,'Calculations As per GA Data'!G31:G152)} -> 45782 | E13: 1398 | F13: =E13/1.18 -> 1184.7458 | G13: 4.75 | H13: {=XLOOKUP(B13,'Discount calculation'!A:A,'Discount calculation'!D:D)} -> 22.653765 | I13: =F13-SUM(G13:H13) -> 1157.342 | J13: 182 | K13: =I13-J13 -> 975.342 | L13: 17.5 | M13: 7.52 | N13: 145.05882 | O13: 4.55 | P13: =K13-SUM(L13:O13) -> 800.71317 | Q13: {=XLOOKUP(B13,'Calculations As per GA Data'!B31:B152,'Calculations As per GA Data'!J31:J152)} -> 966.33713 | R13: {=XLOOKUP(B13,'Calculations As per GA Data'!B31:B152,'Calculations As per GA Data'!F31:F152)} -> 34 | S13: =P13-Q13 -> -165.62396 | T13: =S13/I13 -> -0.14310719 | U13: 229 | V13: =S13-U13 -> -394.62396 | W13: =V13/I13 -> -0.34097437
... A19: Apron | B19: Dabble Painting Art Apron | C19: Apron | D19: {=XLOOKUP(B19,'Calculations As per GA Data'!B37:B158,'Calculations As per GA Data'!G37:G158)} -> 38751.5 | E19: 799 | F19: =E19/1.18 -> 677.11864 | G19: 4.75 | H19: {=XLOOKUP(B19,'Discount calculation'!A:A,'Discount calculation'!D:D)} -> 12.823761 | I19: =F19-SUM(G19:H19) -> 659.54488 | J19: 215.5 | K19: =I19-J19 -> 444.04488 | L19: 5 | M19: 7.52 | N19: 109.919 | O19: 4.55 | P19: =K19-SUM(L19:O19) -> 317.05588 | Q19: {=XLOOKUP(B19,'Calculations As per GA Data'!B37:B158,'Calculations As per GA Data'!J37:J158)} -> 322.77859 | R19: {=XLOOKUP(B19,'Calculations As per GA Data'!B37:B158,'Calculations As per GA Data'!F37:F158)} -> 50 | S19: =P19-Q19 -> -5.722704 | T19: =S19/I19 -> -0.0086767469 | U19: 229 | V19: =S19-U19 -> -234.7227 | W19: =V19/I19 -> -0.35588587
A20: ABC Kit | B20: My Dabble ABC Trace & Colour Kit | Multi-Sensory Alphabet Learning for Kids | C20: ABC Kit | D20: {=XLOOKUP(B20,'Calculations As per GA Data'!B38:B159,'Calculations As per GA Data'!G38:G159)} -> 58561.999 | E20: 699 | F20: =E20/1.18 -> 592.37288 | G20: 4.75 | H20: {=XLOOKUP(B20,'Discount calculation'!A:A,'Discount calculation'!D:D)} -> 7.1620459 | I20: =F20-SUM(G20:H20) -> 580.46084 | J20: 105 | K20: =I20-J20 -> 475.46084 | L20: 8.5 | M20: 7.52 | N20: NA | O20: 4.55 | P20: =K20-SUM(L20:O20) -> 454.89084 | Q20: {=XLOOKUP(B20,'Calculations As per GA Data'!B38:B159,'Calculations As per GA Data'!J38:J159)} -> 857.39146 | R20: {=XLOOKUP(B20,'Calculations As per GA Data'!B38:B159,'Calculations As per GA Data'!F38:F159)} -> 98 | S20: =P20-Q20 -> -402.50062 | T20: =S20/I20 -> -0.69341564 | U20: 229 | V20: =S20-U20 -> -631.50062 | W20: =V20/I20 -> -1.0879298
A21: FP8 | B21: Dabble Playart Finger Paints | C21: FP8 | D21: {=XLOOKUP(B21,'Calculations As per GA Data'!B39:B160,'Calculations As per GA Data'!G39:G160)} -> 53295 | E21: 899 | F21: =E21/1.18 -> 761.86441 | G21: 4.75 | H21: {=XLOOKUP(B21,'Discount calculation'!A:A,'Discount calculation'!D:D)} -> 11.633624 | I21: =F21-SUM(G21:H21) -> 745.48078 | J21: 117.7 | K21: =I21-J21 -> 627.78078 | L21: 9.5 | M21: 7.52 | N21: 198.64467 | O21: 4.55 | P21: =K21-SUM(L21:O21) -> 407.56612 | Q21: {=XLOOKUP(B21,'Calculations As per GA Data'!B39:B160,'Calculations As per GA Data'!J39:J160)} -> 460.95047 | R21: {=XLOOKUP(B21,'Calculations As per GA Data'!B39:B160,'Calculations As per GA Data'!F39:F160)} -> 60 | S21: =P21-Q21 -> -53.384357 | T21: =S21/I21 -> -0.071610642 | U21: 229 | V21: =S21-U21 -> -282.38436 | W21: =V21/I21 -> -0.37879495
A22: Playdough+MPD | B22: Imagination Spark Kit | Dabble Sensory Play Dough + Magic Paint Dust | C22: Combo | D22: {=XLOOKUP(B22,'Calculations As per GA Data'!B40:B161,'Calculations As per GA Data'!G40:G161)} -> 19004 | E22: 1798 | F22: =E22/1.18 -> 1523.7288 | G22: 4.75 | H22: {=XLOOKUP(B22,'Discount calculation'!A:A,'Discount calculation'!D:D)} -> 36.494687 | I22: =F22-SUM(G22:H22) -> 1482.4841 | J22: 256.82 | K22: =I22-J22 -> 1225.6641 | L22: 25 | M22: 7.52 | N22: 157.91 | O22: 4.55 | P22: =K22-SUM(L22:O22) -> 1030.6841 | Q22: {=XLOOKUP(B22,'Calculations As per GA Data'!B40:B161,'Calculations As per GA Data'!J40:J161)} -> 1065.6327 | R22: {=XLOOKUP(B22,'Calculations As per GA Data'!B40:B161,'Calculations As per GA Data'!F40:F161)} -> 11 | S22: =P22-Q22 -> -34.948528 | T22: =S22/I22 -> -0.023574302 | U22: 229 | V22: =S22-U22 -> -263.94853 | W22: =V22/I22 -> -0.17804476
A23: Bubbles | B23: Dabble Magic Bubbles POP n PLAY | C23: Bubbles | D23: {=XLOOKUP(B23,'Calculations As per GA Data'!B41:B162,'Calculations As per GA Data'!G41:G162)} -> 20025.399 | E23: 449 | F23: =E23/1.18 -> 380.50847 | G23: 4.75 | H23: {=XLOOKUP(B23,'Discount calculation'!A:A,'Discount calculation'!D:D)} -> 7.3279583 | I23: =F23-SUM(G23:H23) -> 368.43052 | J23: 64.7 | K23: =I23-J23 -> 303.73052 | L23: 5.5 | M23: 7.52 | N23: 100.73208 | O23: 4.55 | P23: =K23-SUM(L23:O23) -> 185.42843 | Q23: {=XLOOKUP(B23,'Calculations As per GA Data'!B41:B162,'Calculations As per GA Data'!J41:J162)} -> 816.85634 | R23: {=XLOOKUP(B23,'Calculations As per GA Data'!B41:B162,'Calculations As per GA Data'!F41:F162)} -> 48 | S23: =P23-Q23 -> -631.4279 | T23: =S23/I23 -> -1.7138317 | U23: 229 | V23: =S23-U23 -> -860.4279 | W23: =V23/I23 -> -2.3353872
A24: FP3+B3+AR | B24: Dabble Starter Pack | Chunkies + Finger Paints + Art Roll | C24: Combo | D24: {=XLOOKUP(B24,'Calculations As per GA Data'!B42:B163,'Calculations As per GA Data'!G42:G163)} -> 12785 | E24: 1897 | F24: =E24/1.18 -> 1607.6271 | G24: 4.75 | H24: {=XLOOKUP(B24,'Discount calculation'!A:A,'Discount calculation'!D:D)} -> 32.313 | I24: =F24-SUM(G24:H24) -> 1570.5641 | J24: 259.46 | K24: =I24-J24 -> 1311.1041 | L24: 20 | M24: 7.52 | N24: 162.85143 | O24: 4.55 | P24: =K24-SUM(L24:O24) -> 1116.1827 | Q24: {=XLOOKUP(B24,'Calculations As per GA Data'!B42:B163,'Calculations As per GA Data'!J42:J163)} -> 844.56352 | R24: {=XLOOKUP(B24,'Calculations As per GA Data'!B42:B163,'Calculations As per GA Data'!F42:F163)} -> 7 | S24: =P24-Q24 -> 271.61917 | T24: =S24/I24 -> 0.1729437 | U24: 229 | V24: =S24-U24 -> 42.61917 | W24: =V24/I24 -> 0.027136218
A25: Preschool kit | B25: Preschool Art and Craft Kit | C25: Preschool kit | D25: {=XLOOKUP(B25,'Calculations As per GA Data'!B43:B164,'Calculations As per GA Data'!G43:G164)} -> 35911.001 | E25: 599 | F25: =E25/1.18 -> 507.62712 | G25: 4.75 | H25: {=XLOOKUP(B25,'Discount calculation'!A:A,'Discount calculation'!D:D)} -> 10.207814 | I25: =F25-SUM(G25:H25) -> 492.6693 | J25: 151.28 | K25: =I25-J25 -> 341.3893 | L25: 12.5 | M25: 7.52 | N25: 121.94607 | O25: 4.55 | P25: =K25-SUM(L25:O25) -> 194.87324 | Q25: {=XLOOKUP(B25,'Calculations As per GA Data'!B43:B164,'Calculations As per GA Data'!J43:J164)} -> 537.50015 | R25: {=XLOOKUP(B25,'Calculations As per GA Data'!B43:B164,'Calculations As per GA Data'!F43:F164)} -> 61 | S25: =P25-Q25 -> -342.62691 | T25: =S25/I25 -> -0.69545008 | U25: 229 | V25: =S25-U25 -> -571.62691 | W25: =V25/I25 -> -1.1602649
A26: SJ+SFP+CB | B26: My First Dabble Swinginâ€™ Jungle Adventure + Mini Starter Fun Pack + Chubby Brushes Combo | C26: Combo | D26: {=XLOOKUP(B26,'Calculations As per GA Data'!B44:B165,'Calculations As per GA Data'!G44:G165)} -> 31366 | E26: 1547 | F26: =E26/1.18 -> 1311.0169 | G26: 4.75 | H26: {=XLOOKUP(B26,'Discount calculation'!A:A,'Discount calculation'!D:D)} -> 28.966465 | I26: =F26-SUM(G26:H26) -> 1277.3005 | J26: 210.73 | K26: =I26-J26 -> 1066.5705 | L26: 20 | M26: 7.52 | N26: 133.70952 | O26: 4.55 | P26: =K26-SUM(L26:O26) -> 900.79096 | Q26: {=XLOOKUP(B26,'Calculations As per GA Data'!B44:B165,'Calculations As per GA Data'!J44:J165)} -> 677.91593 | R26: {=XLOOKUP(B26,'Calculations As per GA Data'!B44:B165,'Calculations As per GA Data'!F44:F165)} -> 21 | S26: =P26-Q26 -> 222.87503 | T26: =S26/I26 -> 0.17448912 | U26: 229 | V26: =S26-U26 -> -6.1249681 | W26: =V26/I26 -> -0.0047952445
A27: B8 | B27: Dabble Playart Crayons | C27: B8 | D27: {=XLOOKUP(B27,'Calculations As per GA Data'!B45:B166,'Calculations As per GA Data'!G45:G166)} -> 23018 | E27: 449 | F27: =E27/1.18 -> 380.50847 | G27: 4.75 | H27: {=XLOOKUP(B27,'Discount calculation'!A:A,'Discount calculation'!D:D)} -> 4.967751 | I27: =F27-SUM(G27:H27) -> 370.79072 | J27: 60.89 | K27: =I27-J27 -> 309.90072 | L27: 5 | M27: 7.52 | N27: 101.03519 | O27: 4.55 | P27: =K27-SUM(L27:O27) -> 191.79553 | Q27: {=XLOOKUP(B27,'Calculations As per GA Data'!B45:B166,'Calculations As per GA Data'!J45:J166)} -> 446.9242 | R27: {=XLOOKUP(B27,'Calculations As per GA Data'!B45:B166,'Calculations As per GA Data'!F45:F166)} -> 52 | S27: =P27-Q27 -> -255.12867 | T27: =S27/I27 -> -0.68806647 | U27: 229 | V27: =S27-U27 -> -484.12867 | W27: =V27/I27 -> -1.3056655
A28: SR | B28: Dabble Sensory Rice Play Kit | C28: SR | D28: {=XLOOKUP(B28,'Calculations As per GA Data'!B46:B167,'Calculations As per GA Data'!G46:G167)} -> 19372 | E28: 699 | F28: =E28/1.18 -> 592.37288 | G28: 4.75 | H28: {=XLOOKUP(B28,'Discount calculation'!A:A,'Discount calculation'!D:D)} -> 8.6020134 | I28: =F28-SUM(G28:H28) -> 579.02087 | J28: 84.27 | K28: =I28-J28 -> 494.75087 | L28: 12.5 | M28: 7.52 | N28: 122.50536 | O28: 4.55 | P28: =K28-SUM(L28:O28) -> 347.67551 | Q28: {=XLOOKUP(B28,'Calculations As per GA Data'!B46:B167,'Calculations As per GA Data'!J46:J167)} -> 1292.3278 | R28: {=XLOOKUP(B28,'Calculations As per GA Data'!B46:B167,'Calculations As per GA Data'!F46:F167)} -> 28 | S28: =P28-Q28 -> -944.65229 | T28: =S28/I28 -> -1.631465 | U28: 229 | V28: =S28-U28 -> -1173.6523 | W28: =V28/I28 -> -2.0269603
A29: Stamp kit | B29: My First Shape Explorer Stamp Kit | C29: Stamp kit | D29: {=XLOOKUP(B29,'Calculations As per GA Data'!B47:B168,'Calculations As per GA Data'!G47:G168)} -> 36963 | E29: 999 | F29: =E29/1.18 -> 846.61017 | G29: 4.75 | H29: {=XLOOKUP(B29,'Discount calculation'!A:A,'Discount calculation'!D:D)} -> 15.105808 | I29: =F29-SUM(G29:H29) -> 826.75436 | J29: 276.02 | K29: =I29-J29 -> 550.73436 | L29: 12.5 | M29: 7.52 | N29: 138.26514 | O29: 4.55 | P29: =K29-SUM(L29:O29) -> 387.89923 | Q29: {=XLOOKUP(B29,'Calculations As per GA Data'!B47:B168,'Calculations As per GA Data'!J47:J168)} -> 366.39731 | R29: {=XLOOKUP(B29,'Calculations As per GA Data'!B47:B168,'Calculations As per GA Data'!F47:F168)} -> 37 | S29: =P29-Q29 -> 21.501912 | T29: =S29/I29 -> 0.026007618 | U29: 229 | V29: =S29-U29 -> -207.49809 | W29: =V29/I29 -> -0.25097913
A30: SR+Playdough | B30: Sensory Discovery Kit | Dabble Sensory Rice + Sensory Play Dough | C30: Combo | D30: {=XLOOKUP(B30,'Calculations As per GA Data'!B48:B169,'Calculations As per GA Data'!G48:G169)} -> 30792 | E30: 1598 | F30: =E30/1.18 -> 1354.2373 | G30: 4.75 | H30: {=XLOOKUP(B30,'Discount calculation'!A:A,'Discount calculation'!D:D)} -> 25.319091 | I30: =F30-SUM(G30:H30) -> 1324.1682 | J30: 208.76 | K30: =I30-J30 -> 1115.4082 | L30: 25 | M30: 7.52 | N30: 157.418 | O30: 4.55 | P30: =K30-SUM(L30:O30) -> 920.9202 | Q30: {=XLOOKUP(B30,'Calculations As per GA Data'!B48:B169,'Calculations As per GA Data'!J48:J169)} -> 823.93481 | R30: {=XLOOKUP(B30,'Calculations As per GA Data'!B48:B169,'Calculations As per GA Data'!F48:F169)} -> 20 | S30: =P30-Q30 -> 96.985384 | T30: =S30/I30 -> 0.073242496 | U30: 229 | V30: =S30-U30 -> -132.01462 | W30: =V30/I30 -> -0.099696259
A31: FP3+JB | B31: Toddler's First Painting Set | Finger Paints + Jumbo Brushes | C31: Combo | D31: {=XLOOKUP(B31,'Calculations As per GA Data'!B49:B170,'Calculations As per GA Data'!G49:G170)} -> 13325 | E31: 1148 | F31: =E31/1.18 -> 972.88136 | G31: 4.75 | H31: {=XLOOKUP(B31,'Discount calculation'!A:A,'Discount calculation'!D:D)} -> 16.005472 | I31: =F31-SUM(G31:H31) -> 952.12588 | J31: 137.96 | K31: =I31-J31 -> 814.16588 | L31: 11.5 | M31: 7.52 | N31: 112.79417 | O31: 4.55 | P31: =K31-SUM(L31:O31) -> 677.80172 | Q31: {=XLOOKUP(B31,'Calculations As per GA Data'!B49:B170,'Calculations As per GA Data'!J49:J170)} -> 863.57429 | R31: {=XLOOKUP(B31,'Calculations As per GA Data'!B49:B170,'Calculations As per GA Data'!F49:F170)} -> 12 | S31: =P31-Q31 -> -185.77257 | T31: =S31/I31 -> -0.19511346 | U31: 229 | V31: =S31-U31 -> -414.77257 | W31: =V31/I31 -> -0.43562787
A32: Mini SPD | B32: Dabble DIY Sensory Playdough Kit | C32: Mini SPD | D32: {=XLOOKUP(B32,'Calculations As per GA Data'!B50:B171,'Calculations As per GA Data'!G50:G171)} -> 18643 | E32: 599 | F32: =E32/1.18 -> 507.62712 | G32: 4.75 | H32: {=XLOOKUP(B32,'Discount calculation'!A:A,'Discount calculation'!D:D)} -> 6.1700658 | I32: =F32-SUM(G32:H32) -> 496.70705 | J32: 56.8 | K32: =I32-J32 -> 439.90705 | L32: 8.5 | M32: 7.52 | N32: 135.315 | O32: 4.55 | P32: =K32-SUM(L32:O32) -> 284.02205 | Q32: {=XLOOKUP(B32,'Calculations As per GA Data'!B50:B171,'Calculations As per GA Data'!J50:J171)} -> 1014.3042 | R32: {=XLOOKUP(B32,'Calculations As per GA Data'!B50:B171,'Calculations As per GA Data'!F50:F171)} -> 34 | S32: =P32-Q32 -> -730.28217 | T32: =S32/I32 -> -1.4702472 | U32: 229 | V32: =S32-U32 -> -959.28217 | W32: =V32/I32 -> -1.9312836
... A40: Canvas | B40: Dabble Canvas Art Board | C40: Canvas | D40: {=XLOOKUP(B40,'Calculations As per GA Data'!B58:B179,'Calculations As per GA Data'!G58:G179)} -> 6080.0002 | E40: 190 | F40: =E40/1.18 -> 161.01695 | G40: 4.75 | H40: {=XLOOKUP(B40,'Discount calculation'!A:A,'Discount calculation'!D:D)} -> 2.1130556 | I40: =F40-SUM(G40:H40) -> 154.15389 | J40: 38.6 | K40: =I40-J40 -> 115.55389 | L40: 8.5 | M40: 7.52 | N40: 109.51286 | O40: 4.55 | P40: =K40-SUM(L40:O40) -> -14.528964 | Q40: {=XLOOKUP(B40,'Calculations As per GA Data'!B58:B179,'Calculations As per GA Data'!J58:J179)} -> 193.18177 | R40: {=XLOOKUP(B40,'Calculations As per GA Data'!B58:B179,'Calculations As per GA Data'!F58:F179)} -> 35 | S40: =P40-Q40 -> -207.71073 | T40: =S40/I40 -> -1.3474245 | U40: 229 | V40: =S40-U40 -> -436.71073 | W40: =V40/I40 -> -2.832953
A41: MPD+AR+JB | B41: Magic Paint Dust + Jumbo Brush Combo Kit + PlayArt Roll â€“ Babyâ€™s First Painting Kit | C41: Combo | D41: {=XLOOKUP(B41,'Calculations As per GA Data'!B59:B180,'Calculations As per GA Data'!G59:G180)} -> 1992 | E41: 2097 | F41: =E41/1.18 -> 1777.1186 | G41: 4.75 | H41: {=XLOOKUP(B41,'Discount calculation'!A:A,'Discount calculation'!D:D)} -> 40.518 | I41: =F41-SUM(G41:H41) -> 1731.8506 | J41: 338.44 | K41: =I41-J41 -> 1393.4106 | L41: 26 | M41: 7.52 | N41: NA | O41: 4.55 | P41: =K41-SUM(L41:O41) -> 1355.3406 | Q41: {=XLOOKUP(B41,'Calculations As per GA Data'!B59:B180,'Calculations As per GA Data'!J59:J180)} -> 10838.565 | R41: {=XLOOKUP(B41,'Calculations As per GA Data'!B59:B180,'Calculations As per GA Data'!F59:F180)} -> 1 | S41: =P41-Q41 -> -9483.2245 | T41: =S41/I41 -> -5.475775 | U41: 229 | V41: =S41-U41 -> -9712.2245 | W41: =V41/I41 -> -5.6080035
A42: DP | B42: Dabble Baby's First Big Colouring Pages | C42: DP | D42: {=XLOOKUP(B42,'Calculations As per GA Data'!B60:B181,'Calculations As per GA Data'!G60:G181)} -> 32903 | E42: 399 | F42: =E42/1.18 -> 338.13559 | G42: 4.75 | H42: {=XLOOKUP(B42,'Discount calculation'!A:A,'Discount calculation'!D:D)} -> 13.496923 | I42: =F42-SUM(G42:H42) -> 319.88867 | J42: 54 | K42: =I42-J42 -> 265.88867 | L42: 8.5 | M42: 7.52 | N42: 145.63595 | O42: 4.55 | P42: =K42-SUM(L42:O42) -> 99.682724 | Q42: {=XLOOKUP(B42,'Calculations As per GA Data'!B60:B181,'Calculations As per GA Data'!J60:J181)} -> 543.62709 | R42: {=XLOOKUP(B42,'Calculations As per GA Data'!B60:B181,'Calculations As per GA Data'!F60:F181)} -> 37 | S42: =P42-Q42 -> -443.94437 | T42: =S42/I42 -> -1.387809 | U42: 229 | V42: =S42-U42 -> -672.94437 | W42: =V42/I42 -> -2.103683
A43: SJ | B43: My First Dabble Swinginâ€™ Jungle Adventure | Reusable Story Card Set | C43: SJ | D43: {=XLOOKUP(B43,'Calculations As per GA Data'!B61:B182,'Calculations As per GA Data'!G61:G182)} -> 10479 | E43: 499 | F43: =E43/1.18 -> 422.88136 | G43: 4.75 | H43: {=XLOOKUP(B43,'Discount calculation'!A:A,'Discount calculation'!D:D)} -> 8.1027273 | I43: =F43-SUM(G43:H43) -> 410.02863 | J43: 45 | K43: =I43-J43 -> 365.02863 | L43: 8.5 | M43: 7.52 | N43: 104.07571 | O43: 4.55 | P43: =K43-SUM(L43:O43) -> 240.38291 | Q43: {=XLOOKUP(B43,'Calculations As per GA Data'!B61:B182,'Calculations As per GA Data'!J61:J182)} -> 959.4371 | R43: {=XLOOKUP(B43,'Calculations As per GA Data'!B61:B182,'Calculations As per GA Data'!F61:F182)} -> 21 | S43: =P43-Q43 -> -719.05419 | T43: =S43/I43 -> -1.7536683 | U43: 229 | V43: =S43-U43 -> -948.05419 | W43: =V43/I43 -> -2.3121658
A44: DP+B8 | B44: Dabble Reusable Colouring Pages + Crayons Combo Kit | C44: Combo | D44: {=XLOOKUP(B44,'Calculations As per GA Data'!B62:B183,'Calculations As per GA Data'!G62:G183)} -> 7341 | E44: 848 | F44: =E44/1.18 -> 718.64407 | G44: 4.75 | H44: {=XLOOKUP(B44,'Discount calculation'!A:A,'Discount calculation'!D:D)} -> 11.2465 | I44: =F44-SUM(G44:H44) -> 702.64757 | J44: 114.89 | K44: =I44-J44 -> 587.75757 | L44: 13.5 | M44: 7.52 | N44: 157.08889 | O44: 4.55 | P44: =K44-SUM(L44:O44) -> 405.09868 | Q44: {=XLOOKUP(B44,'Calculations As per GA Data'!B62:B183,'Calculations As per GA Data'!J62:J183)} -> 755.03763 | R44: {=XLOOKUP(B44,'Calculations As per GA Data'!B62:B183,'Calculations As per GA Data'!F62:F183)} -> 9 | S44: =P44-Q44 -> -349.93895 | T44: =S44/I44 -> -0.49802912 | U44: 229 | V44: =S44-U44 -> -578.93895 | W44: =V44/I44 -> -0.82393931
A45: FP3+AR | B45: Multi Sensory Painting Set | C45: Combo | D45: {=XLOOKUP(B45,'Calculations As per GA Data'!B63:B184,'Calculations As per GA Data'!G63:G184)} -> 2605 | E45: 1348 | F45: =E45/1.18 -> 1142.3729 | G45: 4.75 | H45: {=XLOOKUP(B45,'Discount calculation'!A:A,'Discount calculation'!D:D)} -> 9.0481818 | I45: =F45-SUM(G45:H45) -> 1128.5747 | J45: 193.96 | K45: =I45-J45 -> 934.6147 | L45: 15 | M45: 7.52 | N45: 433.3 | O45: 4.55 | P45: =K45-SUM(L45:O45) -> 474.2447 | Q45: {=XLOOKUP(B45,'Calculations As per GA Data'!B63:B184,'Calculations As per GA Data'!J63:J184)} -> 1494.9745 | R45: {=XLOOKUP(B45,'Calculations As per GA Data'!B63:B184,'Calculations As per GA Data'!F63:F184)} -> 2 | S45: =P45-Q45 -> -1020.7298 | T45: =S45/I45 -> -0.90444151 | U45: 229 | V45: =S45-U45 -> -1249.7298 | W45: =V45/I45 -> -1.1073523
A46: CB | B46: Dabble Chubby Brushes | C46: CB | D46: {=XLOOKUP(B46,'Calculations As per GA Data'!B64:B185,'Calculations As per GA Data'!G64:G185)} -> 7984 | E46: 449 | F46: =E46/1.18 -> 380.50847 | G46: 4.75 | H46: {=XLOOKUP(B46,'Discount calculation'!A:A,'Discount calculation'!D:D)} -> 7.5284694 | I46: =F46-SUM(G46:H46) -> 368.23001 | J46: 76.4 | K46: =I46-J46 -> 291.83001 | L46: 5 | M46: 7.52 | N46: 96.685 | O46: 4.55 | P46: =K46-SUM(L46:O46) -> 178.07501 | Q46: {=XLOOKUP(B46,'Calculations As per GA Data'!B64:B185,'Calculations As per GA Data'!J64:J185)} -> 641.31009 | R46: {=XLOOKUP(B46,'Calculations As per GA Data'!B64:B185,'Calculations As per GA Data'!F64:F185)} -> 16 | S46: =P46-Q46 -> -463.23508 | T46: =S46/I46 -> -1.2580047 | U46: 229 | V46: =S46-U46 -> -692.23508 | W46: =V46/I46 -> -1.8798986
A47: DP+SFP | B47: Dabble Reusable Colouring Pages + Mini Finger Paints Combo Kit | C47: Combo | D47: {=XLOOKUP(B47,'Calculations As per GA Data'!B65:B186,'Calculations As per GA Data'!G65:G186)} -> 3823 | E47: 998 | F47: =E47/1.18 -> 845.76271 | G47: 4.75 | H47: {=XLOOKUP(B47,'Discount calculation'!A:A,'Discount calculation'!D:D)} -> 12.627778 | I47: =F47-SUM(G47:H47) -> 828.38493 | J47: 143.33 | K47: =I47-J47 -> 685.05493 | L47: 15 | M47: 7.52 | N47: 210.6925 | O47: 4.55 | P47: =K47-SUM(L47:O47) -> 447.29243 | Q47: {=XLOOKUP(B47,'Calculations As per GA Data'!B65:B186,'Calculations As per GA Data'!J65:J186)} -> 934.35907 | R47: {=XLOOKUP(B47,'Calculations As per GA Data'!B65:B186,'Calculations As per GA Data'!F65:F186)} -> 4 | S47: =P47-Q47 -> -487.06663 | T47: =S47/I47 -> -0.58797138 | U47: 229 | V47: =S47-U47 -> -716.06663 | W47: =V47/I47 -> -0.86441291
A48: Magic Dough | B48: Dabble Magic Dough Lab â€” Colour Mixing STEAM Kit | C48: Magic Dough | D48: {=XLOOKUP(B48,'Calculations As per GA Data'!B66:B187,'Calculations As per GA Data'!G66:G187)} -> 5519.9999 | E48: 599 | F48: =E48/1.18 -> 507.62712 | G48: 4.75 | H48: {=XLOOKUP(B48,'Discount calculation'!A:A,'Discount calculation'!D:D)} -> 6.2028947 | I48: =F48-SUM(G48:H48) -> 496.67422 | J48: 38.5 | K48: =I48-J48 -> 458.17422 | L48: 8.5 | M48: 7.52 | N48: 133.052 | O48: 4.55 | P48: =K48-SUM(L48:O48) -> 304.55222 | Q48: {=XLOOKUP(B48,'Calculations As per GA Data'!B66:B187,'Calculations As per GA Data'!J66:J187)} -> 1902.6948 | R48: {=XLOOKUP(B48,'Calculations As per GA Data'!B66:B187,'Calculations As per GA Data'!F66:F187)} -> 10 | S48: =P48-Q48 -> -1598.1426 | T48: =S48/I48 -> -3.2176878 | U48: 229 | V48: =S48-U48 -> -1827.1426 | W48: =V48/I48 -> -3.6787546
A49: Puzzle Kit | B49: My First Dabble Puzzle Colouring Set - Emotions, Shapes & Colours | C49: Puzzle Kit | D49: {=XLOOKUP(B49,'Calculations As per GA Data'!B67:B188,'Calculations As per GA Data'!G67:G188)} -> 6433.0001 | E49: 999 | F49: =E49/1.18 -> 846.61017 | G49: 4.75 | H49: {=XLOOKUP(B49,'Discount calculation'!A:A,'Discount calculation'!D:D)} -> 13.530714 | I49: =F49-SUM(G49:H49) -> 828.32946 | J49: 217.35 | K49: =I49-J49 -> 610.97946 | L49: 12.5 | M49: 7.52 | N49: 128.31714 | O49: 4.55 | P49: =K49-SUM(L49:O49) -> 458.09231 | Q49: {=XLOOKUP(B49,'Calculations As per GA Data'!B67:B188,'Calculations As per GA Data'!J67:J188)} -> 1703.6885 | R49: {=XLOOKUP(B49,'Calculations As per GA Data'!B67:B188,'Calculations As per GA Data'!F67:F188)} -> 7 | S49: =P49-Q49 -> -1245.5962 | T49: =S49/I49 -> -1.5037449 | U49: 229 | V49: =S49-U49 -> -1474.5962 | W49: =V49/I49 -> -1.7802049
A50: Dino Kit | B50: Dabble DINOSAUR STENCIL ART & CRAFT Kit | C50: Dino Kit | D50: {=XLOOKUP(B50,'Calculations As per GA Data'!B68:B189,'Calculations As per GA Data'!G68:G189)} -> 10552 | E50: 399 | F50: =E50/1.18 -> 338.13559 | G50: 4.75 | H50: {=XLOOKUP(B50,'Discount calculation'!A:A,'Discount calculation'!D:D)} -> 16.094881 | I50: =F50-SUM(G50:H50) -> 317.29071 | J50: 80.85 | K50: =I50-J50 -> 236.44071 | L50: 8.5 | M50: 7.52 | N50: NA | O50: 4.55 | P50: =K50-SUM(L50:O50) -> 215.87071 | Q50: {=XLOOKUP(B50,'Calculations As per GA Data'!B68:B189,'Calculations As per GA Data'!J68:J189)} -> 1790.147 | R50: {=XLOOKUP(B50,'Calculations As per GA Data'!B68:B189,'Calculations As per GA Data'!F68:F189)} -> 16 | S50: =P50-Q50 -> -1574.2763 | T50: =S50/I50 -> -4.9616212 | U50: 229 | V50: =S50-U50 -> -1803.2763 | W50: =V50/I50 -> -5.6833568
A51: A1 Kit | B51: All In One Paint Kit | C51: A1 Kit | D51: {=XLOOKUP(B51,'Calculations As per GA Data'!B69:B190,'Calculations As per GA Data'!G69:G190)} -> 8620.0002 | E51: 499 | F51: =E51/1.18 -> 422.88136 | G51: 4.75 | H51: {=XLOOKUP(B51,'Discount calculation'!A:A,'Discount calculation'!D:D)} -> 5.7874194 | I51: =F51-SUM(G51:H51) -> 412.34394 | J51: 96.95 | K51: =I51-J51 -> 315.39394 | L51: 12.5 | M51: 7.52 | N51: 119.85056 | O51: 4.55 | P51: =K51-SUM(L51:O51) -> 170.97338 | Q51: {=XLOOKUP(B51,'Calculations As per GA Data'!B69:B190,'Calculations As per GA Data'!J69:J190)} -> 590.81695 | R51: {=XLOOKUP(B51,'Calculations As per GA Data'!B69:B190,'Calculations As per GA Data'!F69:F190)} -> 18 | S51: =P51-Q51 -> -419.84356 | T51: =S51/I51 -> -1.0181878 | U51: 229 | V51: =S51-U51 -> -648.84356 | W51: =V51/I51 -> -1.5735494
A52: FP8+CB+Apron | B52: Dabble Finger Painting Super Pack | C52: Combo | D52: {=XLOOKUP(B52,'Calculations As per GA Data'!B70:B191,'Calculations As per GA Data'!G70:G191)} -> 2104 | E52: 2147 | F52: =E52/1.18 -> 1819.4915 | G52: 4.75 | H52: {=XLOOKUP(B52,'Discount calculation'!A:A,'Discount calculation'!D:D)} -> 33.415714 | I52: =F52-SUM(G52:H52) -> 1781.3258 | J52: 409.6 | K52: =I52-J52 -> 1371.7258 | L52: 19.5 | M52: 7.52 | N52: 270.01 | O52: 4.55 | P52: =K52-SUM(L52:O52) -> 1070.1458 | Q52: {=XLOOKUP(B52,'Calculations As per GA Data'!B70:B191,'Calculations As per GA Data'!J70:J191)} -> 3397.6693 | R52: {=XLOOKUP(B52,'Calculations As per GA Data'!B70:B191,'Calculations As per GA Data'!F70:F191)} -> 1 | S52: =P52-Q52 -> -2327.5235 | T52: =S52/I52 -> -1.3066243 | U52: 229 | V52: =S52-U52 -> -2556.5235 | W52: =V52/I52 -> -1.4351802
A53: Unicorn Kit | B53: Dabble UNICORN STENCIL ART & CRAFT Kit | C53: Unicorn Kit | D53: {=XLOOKUP(B53,'Calculations As per GA Data'!B71:B192,'Calculations As per GA Data'!G71:G192)} -> 6462.0001 | E53: 399 | F53: =E53/1.18 -> 338.13559 | G53: 4.75 | H53: {=XLOOKUP(B53,'Discount calculation'!A:A,'Discount calculation'!D:D)} -> 14.039153 | I53: =F53-SUM(G53:H53) -> 319.34644 | J53: 80.85 | K53: =I53-J53 -> 238.49644 | L53: 8.5 | M53: 7.52 | N53: NA | O53: 4.55 | P53: =K53-SUM(L53:O53) -> 217.92644 | Q53: {=XLOOKUP(B53,'Calculations As per GA Data'!B71:B192,'Calculations As per GA Data'!J71:J192)} -> 1287.3392 | R53: {=XLOOKUP(B53,'Calculations As per GA Data'!B71:B192,'Calculations As per GA Data'!F71:F192)} -> 9 | S53: =P53-Q53 -> -1069.4127 | T53: =S53/I53 -> -3.3487541 | U53: 229 | V53: =S53-U53 -> -1298.4127 | W53: =V53/I53 -> -4.0658437
A54: A1 Kit+B8 | B54: All In One Paint Kit + Playart Crayons Combo | C54: Combo | D54: {=XLOOKUP(B54,'Calculations As per GA Data'!B72:B193,'Calculations As per GA Data'!G72:G193)} -> 1994 | E54: 948 | F54: =E54/1.18 -> 803.38983 | G54: 4.75 | H54: {=XLOOKUP(B54,'Discount calculation'!A:A,'Discount calculation'!D:D)} -> 20.721429 | I54: =F54-SUM(G54:H54) -> 777.9184 | J54: 157.84 | K54: =I54-J54 -> 620.0784 | L54: 17.5 | M54: 7.52 | N54: 74.18 | O54: 4.55 | P54: =K54-SUM(L54:O54) -> 516.3284 | Q54: {=XLOOKUP(B54,'Calculations As per GA Data'!B72:B193,'Calculations As per GA Data'!J72:J193)} -> 3023.9257 | R54: {=XLOOKUP(B54,'Calculations As per GA Data'!B72:B193,'Calculations As per GA Data'!F72:F193)} -> 2 | S54: =P54-Q54 -> -2507.5973 | T54: =S54/I54 -> -3.2234709 | U54: 229 | V54: =S54-U54 -> -2736.5973 | W54: =V54/I54 -> -3.5178462
A55: India Map Kit | B55: My dabble India Map Art | India maps for kids learning | C55: India Map Kit | D55: {=XLOOKUP(B55,'Calculations As per GA Data'!B73:B194,'Calculations As per GA Data'!G73:G194)} -> 4280 | E55: 1099 | F55: =E55/1.18 -> 931.35593 | G55: 4.75 | H55: {=XLOOKUP(B55,'Discount calculation'!A:A,'Discount calculation'!D:D)} -> 14.893077 | I55: =F55-SUM(G55:H55) -> 911.71286 | J55: 173.95 | K55: =I55-J55 -> 737.76286 | L55: 12.5 | M55: 7.52 | N55: 92.6075 | O55: 4.55 | P55: =K55-SUM(L55:O55) -> 620.58536 | Q55: {=XLOOKUP(B55,'Calculations As per GA Data'!B73:B194,'Calculations As per GA Data'!J73:J194)} -> 1112.7367 | R55: {=XLOOKUP(B55,'Calculations As per GA Data'!B73:B194,'Calculations As per GA Data'!F73:F194)} -> 4 | S55: =P55-Q55 -> -492.15135 | T55: =S55/I55 -> -0.5398096 | U55: 229 | V55: =S55-U55 -> -721.15135 | W55: =V55/I55 -> -0.79098517
A56: SFP+Apron | B56: Dabble Starter Finger Painting Fun Pack + Apron ComboKit | C56: Combo | D56: {=XLOOKUP(B56,'Calculations As per GA Data'!B74:B195,'Calculations As per GA Data'!G74:G195)} -> 18726 | E56: 1398 | F56: =E56/1.18 -> 1184.7458 | G56: 4.75 | H56: {=XLOOKUP(B56,'Discount calculation'!A:A,'Discount calculation'!D:D)} -> 26.877714 | I56: =F56-SUM(G56:H56) -> 1153.118 | J56: 304.83 | K56: =I56-J56 -> 848.28805 | L56: 11.5 | M56: 7.52 | N56: 111.65571 | O56: 4.55 | P56: =K56-SUM(L56:O56) -> 713.06233 | Q56: {=XLOOKUP(B56,'Calculations As per GA Data'!B74:B195,'Calculations As per GA Data'!J74:J195)} -> 434.41629 | R56: {=XLOOKUP(B56,'Calculations As per GA Data'!B74:B195,'Calculations As per GA Data'!F74:F195)} -> 14 | S56: =P56-Q56 -> 278.64604 | T56: =S56/I56 -> 0.24164572 | U56: 229 | V56: =S56-U56 -> 49.646041 | W56: =V56/I56 -> 0.043053737
A57: FP8+Canvs | B57: Dabble Finger Paints + Canvas Art Board | C57: Combo | D57: {=XLOOKUP(B57,'Calculations As per GA Data'!B75:B196,'Calculations As per GA Data'!G75:G196)} -> 4202 | E57: 1089 | F57: =E57/1.18 -> 922.88136 | G57: 4.75 | H57: {=XLOOKUP(B57,'Discount calculation'!A:A,'Discount calculation'!D:D)} -> 13.601667 | I57: =F57-SUM(G57:H57) -> 904.52969 | J57: 219.36 | K57: =I57-J57 -> 685.16969 | L57: 18 | M57: 7.52 | N57: 183.16 | O57: 4.55 | P57: =K57-SUM(L57:O57) -> 471.93969 | Q57: {=XLOOKUP(B57,'Calculations As per GA Data'!B75:B196,'Calculations As per GA Data'!J75:J196)} -> 1036.2891 | R57: {=XLOOKUP(B57,'Calculations As per GA Data'!B75:B196,'Calculations As per GA Data'!F75:F196)} -> 4 | S57: =P57-Q57 -> -564.34946 | T57: =S57/I57 -> -0.6239148 | U57: 229 | V57: =S57-U57 -> -793.34946 | W57: =V57/I57 -> -0.87708504
A58: SFP+CB+Canvas | B58: Dabble Playtime Prep Kit | C58: Combo | D58: {=XLOOKUP(B58,'Calculations As per GA Data'!B76:B197,'Calculations As per GA Data'!G76:G197)} -> 4778 | E58: 1238 | F58: =E58/1.18 -> 1049.1525 | G58: 4.75 | H58: {=XLOOKUP(B58,'Discount calculation'!A:A,'Discount calculation'!D:D)} -> 20.768667 | I58: =F58-SUM(G58:H58) -> 1023.6339 | J58: 204.33 | K58: =I58-J58 -> 819.30388 | L58: 20 | M58: 7.52 | N58: 297.0075 | O58: 4.55 | P58: =K58-SUM(L58:O58) -> 490.22638 | Q58: {=XLOOKUP(B58,'Calculations As per GA Data'!B76:B197,'Calculations As per GA Data'!J76:J197)} -> 874.89985 | R58: {=XLOOKUP(B58,'Calculations As per GA Data'!B76:B197,'Calculations As per GA Data'!F76:F197)} -> 4 | S58: =P58-Q58 -> -384.67348 | T58: =S58/I58 -> -0.37579205 | U58: 229 | V58: =S58-U58 -> -613.67348 | W58: =V58/I58 -> -0.59950485
A59: Activity Pack | B59: A-Z Alphabet Printable Activity Pack | C59: Activity Pack | D59: {=XLOOKUP(B59,'Calculations As per GA Data'!B77:B198,'Calculations As per GA Data'!G77:G198)} -> 3960.0001 | E59: 99 | F59: =E59/1.18 -> 83.898305 | G59: 4.75 | H59: {=XLOOKUP(B59,'Discount calculation'!A:A,'Discount calculation'!D:D)} -> 0.85947368 | I59: =F59-SUM(G59:H59) -> 78.288831 | K59: =I59-J59 -> 78.288831 | M59: 7.52 | N59: 1.58625 | O59: 4.55 | P59: =K59-SUM(L59:O59) -> 64.632581 | Q59: {=XLOOKUP(B59,'Calculations As per GA Data'!B77:B198,'Calculations As per GA Data'!J77:J198)} -> 1229.9563 | R59: {=XLOOKUP(B59,'Calculations As per GA Data'!B77:B198,'Calculations As per GA Data'!F77:F198)} -> 40 | S59: =P59-Q59 -> -1165.3237 | T59: =S59/I59 -> -14.884929 | U59: 229 | V59: =S59-U59 -> -1394.3237 | W59: =V59/I59 -> -17.809995
A60: Glue | B60: Dabble Chunky Glue | C60: Glue | D60: {=XLOOKUP(B60,'Calculations As per GA Data'!B78:B199,'Calculations As per GA Data'!G78:G199)} -> 8725.0001 | E60: 349 | F60: =E60/1.18 -> 295.76271 | G60: 4.75 | H60: {=XLOOKUP(B60,'Discount calculation'!A:A,'Discount calculation'!D:D)} -> 4.6983237 | I60: =F60-SUM(G60:H60) -> 286.31439 | J60: 50.42 | K60: =I60-J60 -> 235.89439 | L60: 5 | M60: 7.52 | N60: 94.7388 | O60: 4.55 | P60: =K60-SUM(L60:O60) -> 124.08559 | Q60: {=XLOOKUP(B60,'Calculations As per GA Data'!B78:B199,'Calculations As per GA Data'!J78:J199)} -> 292.19956 | R60: {=XLOOKUP(B60,'Calculations As per GA Data'!B78:B199,'Calculations As per GA Data'!F78:F199)} -> 25 | S60: =P60-Q60 -> -168.11397 | T60: =S60/I60 -> -0.58716565 | U60: 229 | V60: =S60-U60 -> -397.11397 | W60: =V60/I60 -> -1.3869857
A61: SFP+CB+Apron | B61: Dabble Essentials Pack | C61: Combo | D61: {=XLOOKUP(B61,'Calculations As per GA Data'!B79:B200,'Calculations As per GA Data'!G79:G200)} -> 1810 | E61: 1847 | F61: =E61/1.18 -> 1565.2542 | G61: 4.75 | H61: {=XLOOKUP(B61,'Discount calculation'!A:A,'Discount calculation'!D:D)} -> 60.33 | I61: =F61-SUM(G61:H61) -> 1500.1742 | J61: 381.3 | K61: =I61-J61 -> 1118.8742 | L61: 16.5 | M61: 7.52 | N61: 174.01 | O61: 4.55 | P61: =K61-SUM(L61:O61) -> 916.29424 | Q61: {=XLOOKUP(B61,'Calculations As per GA Data'!B79:B200,'Calculations As per GA Data'!J79:J200)} -> 2310.4151 | R61: {=XLOOKUP(B61,'Calculations As per GA Data'!B79:B200,'Calculations As per GA Data'!F79:F200)} -> 1 | S61: =P61-Q61 -> -1394.1209 | T61: =S61/I61 -> -0.92930599 | U61: 229 | V61: =S61-U61 -> -1623.1209 | W61: =V61/I61 -> -1.0819549
A62: Dino+B8 | B62: Flip Flap Crayon Play Pack Dinosaur Themed | Activity Book with Crayons | | C62: Combo | D62: {=XLOOKUP(B62,'Calculations As per GA Data'!B80:B201,'Calculations As per GA Data'!G80:G201)} -> 0 | E62: 998 | F62: =E62/1.18 -> 845.76271 | G62: 4.75 | H62: {=XLOOKUP(B62,'Discount calculation'!A:A,'Discount calculation'!D:D)} -> #N/A | I62: =F62-SUM(G62:H62) -> #N/A | J62: 141.74 | K62: =I62-J62 -> #N/A | L62: 10.5 | M62: 7.52 | N62: NA | O62: 4.55 | P62: =K62-SUM(L62:O62) -> #N/A | Q62: {=XLOOKUP(B62,'Calculations As per GA Data'!B80:B201,'Calculations As per GA Data'!J80:J201)} -> #DIV/0! | R62: {=XLOOKUP(B62,'Calculations As per GA Data'!B80:B201,'Calculations As per GA Data'!F80:F201)} -> 0 | S62: =P62-Q62 -> #N/A | T62: =S62/I62 -> #N/A | U62: 229 | V62: =S62-U62 -> #N/A | W62: =V62/I62 -> #N/A
A63: SJ+SFP | B63: My First Dabble Swinginâ€™ Jungle Adventure + Mini Starter Fun Pack Combo | C63: Combo | D63: {=XLOOKUP(B63,'Calculations As per GA Data'!B81:B202,'Calculations As per GA Data'!G81:G202)} -> 8358.9999 | E63: 1098 | F63: =E63/1.18 -> 930.50847 | G63: 4.75 | H63: {=XLOOKUP(B63,'Discount calculation'!A:A,'Discount calculation'!D:D)} -> #N/A | I63: =F63-SUM(G63:H63) -> #N/A | J63: 134.33 | K63: =I63-J63 -> #N/A | L63: 15 | M63: 7.52 | N63: 141.00625 | O63: 4.55 | P63: =K63-SUM(L63:O63) -> #N/A | Q63: {=XLOOKUP(B63,'Calculations As per GA Data'!B81:B202,'Calculations As per GA Data'!J81:J202)} -> 1282.6202 | R63: {=XLOOKUP(B63,'Calculations As per GA Data'!B81:B202,'Calculations As per GA Data'!F81:F202)} -> 8 | S63: =P63-Q63 -> #N/A | T63: =S63/I63 -> #N/A | U63: 229 | V63: =S63-U63 -> #N/A | W63: =V63/I63 -> #N/A
A64: FP3+CB | B64: Dabble Painting set | Finger Paints + Chubby Brushes | C64: Combo | D64: {=XLOOKUP(B64,'Calculations As per GA Data'!B82:B203,'Calculations As per GA Data'!G82:G203)} -> 5237 | E64: 1098 | F64: =E64/1.18 -> 930.50847 | G64: 4.75 | H64: {=XLOOKUP(B64,'Discount calculation'!A:A,'Discount calculation'!D:D)} -> 19.025 | I64: =F64-SUM(G64:H64) -> 906.73347 | J64: 139.36 | K64: =I64-J64 -> 767.37347 | L64: 11.5 | M64: 7.52 | N64: 144.898 | O64: 4.55 | P64: =K64-SUM(L64:O64) -> 598.90547 | Q64: {=XLOOKUP(B64,'Calculations As per GA Data'!B82:B203,'Calculations As per GA Data'!J82:J203)} -> 530.03642 | R64: {=XLOOKUP(B64,'Calculations As per GA Data'!B82:B203,'Calculations As per GA Data'!F82:F203)} -> 5 | S64: =P64-Q64 -> 68.869059 | T64: =S64/I64 -> 0.075952924 | U64: 229 | V64: =S64-U64 -> -160.13094 | W64: =V64/I64 -> -0.176602
A65: FP3+Glue+AR+B3 | B65: My First Dabble Art Set For Toddlers | C65: Combo | D65: {=XLOOKUP(B65,'Calculations As per GA Data'!B83:B204,'Calculations As per GA Data'!G83:G204)} -> 0 | E65: 2246 | F65: =E65/1.18 -> 1903.3898 | G65: 4.75 | H65: {=XLOOKUP(B65,'Discount calculation'!A:A,'Discount calculation'!D:D)} -> 27.643333 | I65: =F65-SUM(G65:H65) -> 1870.9965 | J65: 309.88 | K65: =I65-J65 -> 1561.1165 | L65: 25 | M65: 7.52 | N65: NA | O65: 4.55 | P65: =K65-SUM(L65:O65) -> 1524.0465 | Q65: {=XLOOKUP(B65,'Calculations As per GA Data'!B83:B204,'Calculations As per GA Data'!J83:J204)} -> #DIV/0! | R65: {=XLOOKUP(B65,'Calculations As per GA Data'!B83:B204,'Calculations As per GA Data'!F83:F204)} -> 0 | S65: =P65-Q65 -> #DIV/0! | T65: =S65/I65 -> #DIV/0! | U65: 229 | V65: =S65-U65 -> #DIV/0! | W65: =V65/I65 -> #DIV/0!
A66: CC8+DP | B66: Dabble Christmas Crayons + Dabble Pages | C66: Combo | D66: {=XLOOKUP(B66,'Calculations As per GA Data'!B84:B205,'Calculations As per GA Data'!G84:G205)} -> #N/A | E66: NA | F66: 1048 | G66: 4.75 | H66: {=XLOOKUP(B66,'Discount calculation'!A:A,'Discount calculation'!D:D)} -> #N/A | I66: =F66-SUM(G66:H66) -> #N/A | J66: 135.4 | K66: =I66-J66 -> #N/A | L66: 13.5 | M66: 7.52 | N66: NA | O66: 4.55 | P66: =K66-SUM(L66:O66) -> #N/A | Q66: {=XLOOKUP(B66,'Calculations As per GA Data'!B84:B205,'Calculations As per GA Data'!J84:J205)} -> #VALUE! | R66: {=XLOOKUP(B66,'Calculations As per GA Data'!B84:B205,'Calculations As per GA Data'!F84:F205)} -> NA | S66: =P66-Q66 -> #N/A | T66: =S66/I66 -> #N/A | U66: 229 | V66: =S66-U66 -> #N/A | W66: =V66/I66 -> #N/A
A67: SFP+AR+Apron | B67: Dabble Sensory Painting Kit | C67: Combo | D67: {=XLOOKUP(B67,'Calculations As per GA Data'!B85:B206,'Calculations As per GA Data'!G85:G206)} -> 1712 | E67: 1747 | F67: =E67/1.18 -> 1480.5085 | G67: 4.75 | H67: {=XLOOKUP(B67,'Discount calculation'!A:A,'Discount calculation'!D:D)} -> 22.688 | I67: =F67-SUM(G67:H67) -> 1453.0705 | J67: 435.83 | K67: =I67-J67 -> 1017.2405 | L67: 20 | M67: 7.52 | N67: 505.33 | O67: 4.55 | P67: =K67-SUM(L67:O67) -> 479.84047 | Q67: {=XLOOKUP(B67,'Calculations As per GA Data'!B85:B206,'Calculations As per GA Data'!J85:J206)} -> 2955.9723 | R67: {=XLOOKUP(B67,'Calculations As per GA Data'!B85:B206,'Calculations As per GA Data'!F85:F206)} -> 1 | S67: =P67-Q67 -> -2476.1318 | T67: =S67/I67 -> -1.7040687 | U67: 229 | V67: =S67-U67 -> -2705.1318 | W67: =V67/I67 -> -1.861666
A68: Glue+FP3+B8 | B68: Dabble 3 In 1 Easy-Clean Fun Pack | C68: Combo | D68: {=XLOOKUP(B68,'Calculations As per GA Data'!B86:B207,'Calculations As per GA Data'!G86:G207)} -> 1418 | E68: 1447 | F68: =E68/1.18 -> 1226.2712 | G68: 4.75 | H68: {=XLOOKUP(B68,'Discount calculation'!A:A,'Discount calculation'!D:D)} -> 13.818333 | I68: =F68-SUM(G68:H68) -> 1207.7029 | J68: 174.27 | K68: =I68-J68 -> 1033.4329 | L68: 16.5 | M68: 7.52 | N68: 407.32 | O68: 4.55 | P68: =K68-SUM(L68:O68) -> 597.54285 | Q68: {=XLOOKUP(B68,'Calculations As per GA Data'!B86:B207,'Calculations As per GA Data'!J86:J207)} -> 3329.7159 | R68: {=XLOOKUP(B68,'Calculations As per GA Data'!B86:B207,'Calculations As per GA Data'!F86:F207)} -> 1 | S68: =P68-Q68 -> -2732.1731 | T68: =S68/I68 -> -2.2622892 | U68: 229 | V68: =S68-U68 -> -2961.1731 | W68: =V68/I68 -> -2.4519054
A69: Canvas & Stand | B69: Canvas and Stand | C69: Canvas & Stand | D69: {=XLOOKUP(B69,'Calculations As per GA Data'!B87:B208,'Calculations As per GA Data'!G87:G208)} -> 14112 | E69: 160 | F69: =E69/1.18 -> 135.59322 | G69: 4.75 | H69: {=XLOOKUP(B69,'Discount calculation'!A:A,'Discount calculation'!D:D)} -> 1.5457685 | I69: =F69-SUM(G69:H69) -> 129.29745 | K69: =I69-J69 -> 129.29745 | M69: 7.52 | N69: 103.91962 | O69: 4.55 | P69: =K69-SUM(L69:O69) -> 13.307833 | Q69: {=XLOOKUP(B69,'Calculations As per GA Data'!B87:B208,'Calculations As per GA Data'!J87:J208)} -> 59.216523 | R69: {=XLOOKUP(B69,'Calculations As per GA Data'!B87:B208,'Calculations As per GA Data'!F87:F208)} -> 105 | S69: =P69-Q69 -> -45.90869 | T69: =S69/I69 -> -0.3550626 | U69: 229 | V69: =S69-U69 -> -274.90869 | W69: =V69/I69 -> -2.1261725
A70: FF Unicorn + Dino | B70: Flip Flap Play Pack | Activity Book | | C70: Combo | D70: {=XLOOKUP(B70,'Calculations As per GA Data'!B88:B209,'Calculations As per GA Data'!G88:G209)} -> 2534.9999 | E70: 1098 | F70: =E70/1.18 -> 930.50847 | G70: 4.75 | H70: {=XLOOKUP(B70,'Discount calculation'!A:A,'Discount calculation'!D:D)} -> 11.02 | I70: =F70-SUM(G70:H70) -> 914.73847 | J70: 212 | K70: =I70-J70 -> 702.73847 | L70: 11 | M70: 7.52 | N70: 87.66 | O70: 4.55 | P70: =K70-SUM(L70:O70) -> 592.00847 | Q70: {=XLOOKUP(B70,'Calculations As per GA Data'!B88:B209,'Calculations As per GA Data'!J88:J209)} -> 2219.8106 | R70: {=XLOOKUP(B70,'Calculations As per GA Data'!B88:B209,'Calculations As per GA Data'!F88:F209)} -> 3 | S70: =P70-Q70 -> -1627.8022 | T70: =S70/I70 -> -1.7795274 | U70: 229 | V70: =S70-U70 -> -1856.8022 | W70: =V70/I70 -> -2.0298722
A71: FF Unicorn | B71: Dabble Flip Flap Dress-Up Your Own Unicorn & Princesses | Travel-Friendly No Mess DIY Activity Set | C71: FF Unicorn | D71: {=XLOOKUP(B71,'Calculations As per GA Data'!B89:B210,'Calculations As per GA Data'!G89:G210)} -> 0 | E71: 549 | F71: =E71/1.18 -> 465.25424 | G71: 4.75 | H71: {=XLOOKUP(B71,'Discount calculation'!A:A,'Discount calculation'!D:D)} -> #N/A | I71: =F71-SUM(G71:H71) -> #N/A | J71: 106 | K71: =I71-J71 -> #N/A | L71: 5.5 | M71: 7.52 | N71: NA | O71: 4.55 | P71: =K71-SUM(L71:O71) -> #N/A | Q71: {=XLOOKUP(B71,'Calculations As per GA Data'!B89:B210,'Calculations As per GA Data'!J89:J210)} -> #DIV/0! | R71: {=XLOOKUP(B71,'Calculations As per GA Data'!B89:B210,'Calculations As per GA Data'!F89:F210)} -> 0 | S71: =P71-Q71 -> #N/A | T71: =S71/I71 -> #N/A | U71: 229 | V71: =S71-U71 -> #N/A | W71: =V71/I71 -> #N/A
A72: Activity Pack | B72: Numbers 1-10 Printable Activity Pack | C72: Activity Pack | D72: {=XLOOKUP(B72,'Calculations As per GA Data'!B90:B211,'Calculations As per GA Data'!G90:G211)} -> 792.00005 | E72: 99 | F72: =E72/1.18 -> 83.898305 | G72: 4.75 | H72: {=XLOOKUP(B72,'Discount calculation'!A:A,'Discount calculation'!D:D)} -> 0.91926829 | I72: =F72-SUM(G72:H72) -> 78.229037 | K72: =I72-J72 -> 78.229037 | M72: 7.52 | N72: NA | O72: 4.55 | P72: =K72-SUM(L72:O72) -> 66.159037 | Q72: {=XLOOKUP(B72,'Calculations As per GA Data'!B90:B211,'Calculations As per GA Data'!J90:J211)} -> 832.42899 | R72: {=XLOOKUP(B72,'Calculations As per GA Data'!B90:B211,'Calculations As per GA Data'!F90:F211)} -> 8 | S72: =P72-Q72 -> -766.26995 | T72: =S72/I72 -> -9.7952114 | U72: 229 | V72: =S72-U72 -> -995.26995 | W72: =V72/I72 -> -12.722513
A73: DP+Glue | B73: Dabble Reusable Colouring Pages + Glue Combo Kit | C73: Combo | D73: {=XLOOKUP(B73,'Calculations As per GA Data'!B91:B212,'Calculations As per GA Data'!G91:G212)} -> 1420.0001 | E73: 748 | F73: =E73/1.18 -> 633.89831 | G73: 4.75 | H73: {=XLOOKUP(B73,'Discount calculation'!A:A,'Discount calculation'!D:D)} -> 8.0978261 | I73: =F73-SUM(G73:H73) -> 621.05048 | J73: 104.42 | K73: =I73-J73 -> 516.63048 | L73: 13.5 | M73: 7.52 | N73: 110.26 | O73: 4.55 | P73: =K73-SUM(L73:O73) -> 380.80048 | Q73: {=XLOOKUP(B73,'Calculations As per GA Data'!B91:B212,'Calculations As per GA Data'!J91:J212)} -> 1477.9862 | R73: {=XLOOKUP(B73,'Calculations As per GA Data'!B91:B212,'Calculations As per GA Data'!F91:F212)} -> 2 | S73: =P73-Q73 -> -1097.1857 | T73: =S73/I73 -> -1.766661 | U73: 229 | V73: =S73-U73 -> -1326.1857 | W73: =V73/I73 -> -2.1353911
A74: ABC Crayons | B74: My Dabble ABC Trace & Colour Kit | Multi-Sensory Alphabet Learning for Kids - Crayons | C74: ABC Crayons | D74: {=XLOOKUP(B74,'Calculations As per GA Data'!B92:B213,'Calculations As per GA Data'!G92:G213)} -> 0 | E74: 699 | F74: =E74/1.18 -> 592.37288 | G74: 4.75 | H74: {=XLOOKUP(B74,'Discount calculation'!A:A,'Discount calculation'!D:D)} -> #N/A | I74: =F74-SUM(G74:H74) -> #N/A | J74: 105 | K74: =I74-J74 -> #N/A | L74: 8.5 | M74: 7.52 | N74: #DIV/0! | O74: 4.55 | P74: =K74-SUM(L74:O74) -> #N/A | Q74: {=XLOOKUP(B74,'Calculations As per GA Data'!B92:B213,'Calculations As per GA Data'!J92:J213)} -> #DIV/0! | R74: {=XLOOKUP(B74,'Calculations As per GA Data'!B92:B213,'Calculations As per GA Data'!F92:F213)} -> 0 | S74: =P74-Q74 -> #N/A | T74: =S74/I74 -> #N/A | U74: 229 | V74: =S74-U74 -> #N/A | W74: =V74/I74 -> #N/A
A75: FF Dino | B75: Dabble Flip Flap Make Your Own Dinosaur | Travel-Friendly No Mess DIY Activity Set | C75: FF Dino | D75: {=XLOOKUP(B75,'Calculations As per GA Data'!B93:B214,'Calculations As per GA Data'!G93:G214)} -> 844 | E75: 549 | F75: =E75/1.18 -> 465.25424 | G75: 4.75 | H75: {=XLOOKUP(B75,'Discount calculation'!A:A,'Discount calculation'!D:D)} -> 0.059039409 | I75: =F75-SUM(G75:H75) -> 460.4452 | K75: =I75-J75 -> 460.4452 | M75: 7.52 | N75: #VALUE! | O75: 4.55 | P75: =K75-SUM(L75:O75) -> #VALUE! | Q75: {=XLOOKUP(B75,'Calculations As per GA Data'!B93:B214,'Calculations As per GA Data'!J93:J214)} -> 130.65071 | R75: {=XLOOKUP(B75,'Calculations As per GA Data'!B93:B214,'Calculations As per GA Data'!F93:F214)} -> 181 | S75: =P75-Q75 -> #VALUE! | T75: =S75/I75 -> #VALUE! | U75: 229 | V75: =S75-U75 -> #VALUE! | W75: =V75/I75 -> #VALUE!
A76: P&B | B76: Palette & Brush | C76: P&B | D76: {=XLOOKUP(B76,'Calculations As per GA Data'!B94:B215,'Calculations As per GA Data'!G94:G215)} -> 298.99998 | E76: 299 | F76: =E76/1.18 -> 253.38983 | G76: 4.75 | H76: {=XLOOKUP(B76,'Discount calculation'!A:A,'Discount calculation'!D:D)} -> 7.41 | I76: =F76-SUM(G76:H76) -> 241.22983 | J76: 34 | K76: =I76-J76 -> 207.22983 | L76: 4 | M76: 7.52 | N76: 74.04 | O76: 4.55 | P76: =K76-SUM(L76:O76) -> 117.11983 | Q76: {=XLOOKUP(B76,'Calculations As per GA Data'!B94:B215,'Calculations As per GA Data'!J94:J215)} -> 883.39403 | R76: {=XLOOKUP(B76,'Calculations As per GA Data'!B94:B215,'Calculations As per GA Data'!F94:F215)} -> 1 | S76: =P76-Q76 -> -766.2742 | T76: =S76/I76 -> -3.1765317 | U76: 229 | V76: =S76-U76 -> -995.2742 | W76: =V76/I76 -> -4.1258338
A77: B3+AR | B77: Baby&#39;s First Art Set | C77: Combo | D77: {=XLOOKUP(B77,'Calculations As per GA Data'!B95:B216,'Calculations As per GA Data'!G95:G216)} -> 0 | E77: NA | F77: =E77/1.18 -> #VALUE! | G77: 4.75 | H77: {=XLOOKUP(B77,'Discount calculation'!A:A,'Discount calculation'!D:D)} -> #N/A | I77: =F77-SUM(G77:H77) -> #VALUE! | K77: =I77-J77 -> #VALUE! | M77: 7.52 | N77: #VALUE! | O77: 4.55 | P77: =K77-SUM(L77:O77) -> #VALUE! | Q77: {=XLOOKUP(B77,'Calculations As per GA Data'!B95:B216,'Calculations As per GA Data'!J95:J216)} -> #DIV/0! | R77: {=XLOOKUP(B77,'Calculations As per GA Data'!B95:B216,'Calculations As per GA Data'!F95:F216)} -> 0 | S77: =P77-Q77 -> #VALUE! | T77: =S77/I77 -> #VALUE! | U77: 229 | V77: =S77-U77 -> #VALUE! | W77: =V77/I77 -> #VALUE!
A78: NA | B78: Bake dough- (Green) | C78: NA | D78: {=XLOOKUP(B78,'Calculations As per GA Data'!B96:B217,'Calculations As per GA Data'!G96:G217)} -> #N/A | E78: NA | F78: NA | G78: 4.75 | H78: {=XLOOKUP(B78,'Discount calculation'!A:A,'Discount calculation'!D:D)} -> #N/A | I78: =F78-SUM(G78:H78) -> #N/A | K78: =I78-J78 -> #N/A | M78: 7.52 | N78: #VALUE! | O78: 4.55 | P78: =K78-SUM(L78:O78) -> #N/A | Q78: {=XLOOKUP(B78,'Calculations As per GA Data'!B96:B217,'Calculations As per GA Data'!J96:J217)} -> #VALUE! | R78: {=XLOOKUP(B78,'Calculations As per GA Data'!B96:B217,'Calculations As per GA Data'!F96:F217)} -> NA | S78: =P78-Q78 -> #N/A | T78: =S78/I78 -> #N/A | U78: 229 | V78: =S78-U78 -> #N/A | W78: =V78/I78 -> #N/A
A79: NA | B79: Bakedough-Pizza Blue | C79: NA | D79: {=XLOOKUP(B79,'Calculations As per GA Data'!B97:B218,'Calculations As per GA Data'!G97:G218)} -> #N/A | E79: NA | F79: NA | G79: 4.75 | H79: {=XLOOKUP(B79,'Discount calculation'!A:A,'Discount calculation'!D:D)} -> #N/A | I79: =F79-SUM(G79:H79) -> #N/A | K79: =I79-J79 -> #N/A | M79: 7.52 | N79: #VALUE! | O79: 4.55 | P79: =K79-SUM(L79:O79) -> #N/A | Q79: {=XLOOKUP(B79,'Calculations As per GA Data'!B97:B218,'Calculations As per GA Data'!J97:J218)} -> #VALUE! | R79: {=XLOOKUP(B79,'Calculations As per GA Data'!B97:B218,'Calculations As per GA Data'!F97:F218)} -> NA | S79: =P79-Q79 -> #N/A | T79: =S79/I79 -> #N/A | U79: 229 | V79: =S79-U79 -> #N/A | W79: =V79/I79 -> #N/A
A80: NA | B80: Bakedough-Pizza Green | C80: NA | D80: {=XLOOKUP(B80,'Calculations As per GA Data'!B98:B219,'Calculations As per GA Data'!G98:G219)} -> #N/A | E80: NA | F80: NA | G80: 4.75 | H80: {=XLOOKUP(B80,'Discount calculation'!A:A,'Discount calculation'!D:D)} -> #N/A | I80: =F80-SUM(G80:H80) -> #N/A | K80: =I80-J80 -> #N/A | M80: 7.52 | N80: #VALUE! | O80: 4.55 | P80: =K80-SUM(L80:O80) -> #N/A | Q80: {=XLOOKUP(B80,'Calculations As per GA Data'!B98:B219,'Calculations As per GA Data'!J98:J219)} -> #VALUE! | R80: {=XLOOKUP(B80,'Calculations As per GA Data'!B98:B219,'Calculations As per GA Data'!F98:F219)} -> NA | S80: =P80-Q80 -> #N/A | T80: =S80/I80 -> #N/A | U80: 229 | V80: =S80-U80 -> #N/A | W80: =V80/I80 -> #N/A
A81: DP | B81: Dabble Baby&#39;s First Big Colouring Pages | C81: DP | D81: {=XLOOKUP(B81,'Calculations As per GA Data'!B99:B220,'Calculations As per GA Data'!G99:G220)} -> 0 | E81: NA | F81: =E81/1.18 -> #VALUE! | G81: 4.75 | H81: {=XLOOKUP(B81,'Discount calculation'!A:A,'Discount calculation'!D:D)} -> #N/A | I81: =F81-SUM(G81:H81) -> #VALUE! | K81: =I81-J81 -> #VALUE! | M81: 7.52 | N81: #VALUE! | O81: 4.55 | P81: =K81-SUM(L81:O81) -> #VALUE! | Q81: {=XLOOKUP(B81,'Calculations As per GA Data'!B99:B220,'Calculations As per GA Data'!J99:J220)} -> #DIV/0! | R81: {=XLOOKUP(B81,'Calculations As per GA Data'!B99:B220,'Calculations As per GA Data'!F99:F220)} -> 0 | S81: =P81-Q81 -> #VALUE! | T81: =S81/I81 -> #VALUE! | U81: 229 | V81: =S81-U81 -> #VALUE! | W81: =V81/I81 -> #VALUE!
A82: CC8 | B82: Dabble Christmas Crayons | C82: CC8 | D82: {=XLOOKUP(B82,'Calculations As per GA Data'!B100:B221,'Calculations As per GA Data'!G100:G221)} -> #N/A | E82: NA | F82: =E82/1.18 -> #VALUE! | G82: 4.75 | H82: {=XLOOKUP(B82,'Discount calculation'!A:A,'Discount calculation'!D:D)} -> #N/A | I82: =F82-SUM(G82:H82) -> #VALUE! | K82: =I82-J82 -> #VALUE! | M82: 7.52 | N82: #VALUE! | O82: 4.55 | P82: =K82-SUM(L82:O82) -> #VALUE! | Q82: {=XLOOKUP(B82,'Calculations As per GA Data'!B100:B221,'Calculations As per GA Data'!J100:J221)} -> #VALUE! | R82: {=XLOOKUP(B82,'Calculations As per GA Data'!B100:B221,'Calculations As per GA Data'!F100:F221)} -> NA | S82: =P82-Q82 -> #VALUE! | T82: =S82/I82 -> #VALUE! | U82: 229 | V82: =S82-U82 -> #VALUE! | W82: =V82/I82 -> #VALUE!
A83: CC8+SFP | B83: Dabble Christmas Crayons + Mini Starter Fun Pack | C83: Combo | D83: {=XLOOKUP(B83,'Calculations As per GA Data'!B101:B222,'Calculations As per GA Data'!G101:G222)} -> #N/A | E83: NA | F83: =E83/1.18 -> #VALUE! | G83: 4.75 | H83: {=XLOOKUP(B83,'Discount calculation'!A:A,'Discount calculation'!D:D)} -> #N/A | I83: =F83-SUM(G83:H83) -> #VALUE! | K83: =I83-J83 -> #VALUE! | M83: 7.52 | N83: #VALUE! | O83: 4.55 | P83: =K83-SUM(L83:O83) -> #VALUE! | Q83: {=XLOOKUP(B83,'Calculations As per GA Data'!B101:B222,'Calculations As per GA Data'!J101:J222)} -> #VALUE! | R83: {=XLOOKUP(B83,'Calculations As per GA Data'!B101:B222,'Calculations As per GA Data'!F101:F222)} -> NA | S83: =P83-Q83 -> #VALUE! | T83: =S83/I83 -> #VALUE! | U83: 229 | V83: =S83-U83 -> #VALUE! | W83: =V83/I83 -> #VALUE!
A84: CC8+SJ | B84: Dabble Christmas Crayons + My Swingin Jungle | C84: Combo | D84: {=XLOOKUP(B84,'Calculations As per GA Data'!B102:B223,'Calculations As per GA Data'!G102:G223)} -> #N/A | E84: NA | F84: =E84/1.18 -> #VALUE! | G84: 4.75 | H84: {=XLOOKUP(B84,'Discount calculation'!A:A,'Discount calculation'!D:D)} -> #N/A | I84: =F84-SUM(G84:H84) -> #VALUE! | K84: =I84-J84 -> #VALUE! | M84: 7.52 | N84: #VALUE! | O84: 4.55 | P84: =K84-SUM(L84:O84) -> #VALUE! | Q84: {=XLOOKUP(B84,'Calculations As per GA Data'!B102:B223,'Calculations As per GA Data'!J102:J223)} -> #VALUE! | R84: {=XLOOKUP(B84,'Calculations As per GA Data'!B102:B223,'Calculations As per GA Data'!F102:F223)} -> NA | S84: =P84-Q84 -> #VALUE! | T84: =S84/I84 -> #VALUE! | U84: 229 | V84: =S84-U84 -> #VALUE! | W84: =V84/I84 -> #VALUE!
A85: B8+FP3+AR | B85: Dabble Combo Pack | Crayons + Finger Paints + Art Roll | C85: Combo | D85: {=XLOOKUP(B85,'Calculations As per GA Data'!B103:B224,'Calculations As per GA Data'!G103:G224)} -> 3466 | E85: 1797 | F85: =E85/1.18 -> 1522.8814 | G85: 4.75 | H85: {=XLOOKUP(B85,'Discount calculation'!A:A,'Discount calculation'!D:D)} -> 40.045 | I85: =F85-SUM(G85:H85) -> 1478.0864 | K85: =I85-J85 -> 1478.0864 | M85: 7.52 | N85: 3456.93 | O85: 4.55 | P85: =K85-SUM(L85:O85) -> -1990.9136 | Q85: {=XLOOKUP(B85,'Calculations As per GA Data'!B103:B224,'Calculations As per GA Data'!J103:J224)} -> 594.59213 | R85: {=XLOOKUP(B85,'Calculations As per GA Data'!B103:B224,'Calculations As per GA Data'!F103:F224)} -> 2 | S85: =P85-Q85 -> -2585.5058 | T85: =S85/I85 -> -1.7492251 | U85: 229 | V85: =S85-U85 -> -2814.5058 | W85: =V85/I85 -> -1.9041552
A86: Dino Kit | B86: Dabble DINOSAUR STENCIL ART & CRAFT Kit - Pack of 1 | C86: Dino Kit | D86: {=XLOOKUP(B86,'Calculations As per GA Data'!B104:B225,'Calculations As per GA Data'!G104:G225)} -> 0 | E86: 399 | F86: =E86/1.18 -> 338.13559 | G86: 4.75 | H86: {=XLOOKUP(B86,'Discount calculation'!A:A,'Discount calculation'!D:D)} -> #N/A | I86: =F86-SUM(G86:H86) -> #N/A | K86: =I86-J86 -> #N/A | M86: 7.52 | N86: #DIV/0! | O86: 4.55 | P86: =K86-SUM(L86:O86) -> #N/A | Q86: {=XLOOKUP(B86,'Calculations As per GA Data'!B104:B225,'Calculations As per GA Data'!J104:J225)} -> #DIV/0! | R86: {=XLOOKUP(B86,'Calculations As per GA Data'!B104:B225,'Calculations As per GA Data'!F104:F225)} -> 0 | S86: =P86-Q86 -> #N/A | T86: =S86/I86 -> #N/A | U86: 229 | V86: =S86-U86 -> #N/A | W86: =V86/I86 -> #N/A
A87: Dino Kit | B87: Dabble DINOSAUR STENCIL ART & CRAFT Kit - Pack of 10 | C87: Dino Kit | D87: {=XLOOKUP(B87,'Calculations As per GA Data'!B105:B226,'Calculations As per GA Data'!G105:G226)} -> #N/A | E87: 3990 | F87: =E87/1.18 -> 3381.3559 | G87: 4.75 | H87: {=XLOOKUP(B87,'Discount calculation'!A:A,'Discount calculation'!D:D)} -> #N/A | I87: =F87-SUM(G87:H87) -> #N/A | K87: =I87-J87 -> #N/A | M87: 7.52 | N87: #VALUE! | O87: 4.55 | P87: =K87-SUM(L87:O87) -> #N/A | Q87: {=XLOOKUP(B87,'Calculations As per GA Data'!B105:B226,'Calculations As per GA Data'!J105:J226)} -> #VALUE! | R87: {=XLOOKUP(B87,'Calculations As per GA Data'!B105:B226,'Calculations As per GA Data'!F105:F226)} -> NA | S87: =P87-Q87 -> #N/A | T87: =S87/I87 -> #N/A | U87: 229 | V87: =S87-U87 -> #N/A | W87: =V87/I87 -> #N/A
A88: Dino Kit | B88: Dabble DINOSAUR STENCIL ART & CRAFT Kit - Pack of 5 | C88: Dino Kit | D88: {=XLOOKUP(B88,'Calculations As per GA Data'!B106:B227,'Calculations As per GA Data'!G106:G227)} -> #N/A | E88: 1995 | F88: =E88/1.18 -> 1690.678 | G88: 4.75 | H88: {=XLOOKUP(B88,'Discount calculation'!A:A,'Discount calculation'!D:D)} -> #N/A | I88: =F88-SUM(G88:H88) -> #N/A | K88: =I88-J88 -> #N/A | M88: 7.52 | N88: #VALUE! | O88: 4.55 | P88: =K88-SUM(L88:O88) -> #N/A | Q88: {=XLOOKUP(B88,'Calculations As per GA Data'!B106:B227,'Calculations As per GA Data'!J106:J227)} -> #VALUE! | R88: {=XLOOKUP(B88,'Calculations As per GA Data'!B106:B227,'Calculations As per GA Data'!F106:F227)} -> NA | S88: =P88-Q88 -> #N/A | T88: =S88/I88 -> #N/A | U88: 229 | V88: =S88-U88 -> #N/A | W88: =V88/I88 -> #N/A
A89: Dino Kit | B89: Dabble DINOSAUR STENCIL ART &amp; CRAFT Kit - Pack of 1 | C89: Dino Kit | D89: {=XLOOKUP(B89,'Calculations As per GA Data'!B107:B228,'Calculations As per GA Data'!G107:G228)} -> #N/A | E89: NA | F89: =E89/1.18 -> #VALUE! | G89: 4.75 | H89: {=XLOOKUP(B89,'Discount calculation'!A:A,'Discount calculation'!D:D)} -> #N/A | I89: =F89-SUM(G89:H89) -> #VALUE! | K89: =I89-J89 -> #VALUE! | M89: 7.52 | N89: #VALUE! | O89: 4.55 | P89: =K89-SUM(L89:O89) -> #VALUE! | Q89: {=XLOOKUP(B89,'Calculations As per GA Data'!B107:B228,'Calculations As per GA Data'!J107:J228)} -> #VALUE! | R89: {=XLOOKUP(B89,'Calculations As per GA Data'!B107:B228,'Calculations As per GA Data'!F107:F228)} -> NA | S89: =P89-Q89 -> #VALUE! | T89: =S89/I89 -> #VALUE! | U89: 229 | V89: =S89-U89 -> #VALUE! | W89: =V89/I89 -> #VALUE!
A90: Dino Kit | B90: Dabble DINOSAUR STENCIL ART &amp; CRAFT Kit - Pack of 5 | C90: Dino Kit | D90: {=XLOOKUP(B90,'Calculations As per GA Data'!B108:B229,'Calculations As per GA Data'!G108:G229)} -> #N/A | E90: 1995 | F90: =E90/1.18 -> 1690.678 | G90: 4.75 | H90: {=XLOOKUP(B90,'Discount calculation'!A:A,'Discount calculation'!D:D)} -> #N/A | I90: =F90-SUM(G90:H90) -> #N/A | K90: =I90-J90 -> #N/A | M90: 7.52 | N90: #VALUE! | O90: 4.55 | P90: =K90-SUM(L90:O90) -> #N/A | Q90: {=XLOOKUP(B90,'Calculations As per GA Data'!B108:B229,'Calculations As per GA Data'!J108:J229)} -> #VALUE! | R90: {=XLOOKUP(B90,'Calculations As per GA Data'!B108:B229,'Calculations As per GA Data'!F108:F229)} -> NA | S90: =P90-Q90 -> #N/A | T90: =S90/I90 -> #N/A | U90: 229 | V90: =S90-U90 -> #N/A | W90: =V90/I90 -> #N/A
A91: FF Unicorn | B91: Dabble Flip Flap Dress-Up Your Own Unicorn & Princesses | Travel-Friendly No Mess DIY Activity Set - | C91: FF Unicorn | D91: {=XLOOKUP(B91,'Calculations As per GA Data'!B109:B230,'Calculations As per GA Data'!G109:G230)} -> #N/A | E91: 549 | F91: =E91/1.18 -> 465.25424 | G91: 4.75 | H91: {=XLOOKUP(B91,'Discount calculation'!A:A,'Discount calculation'!D:D)} -> #N/A | I91: =F91-SUM(G91:H91) -> #N/A | K91: =I91-J91 -> #N/A | M91: 7.52 | N91: #VALUE! | O91: 4.55 | P91: =K91-SUM(L91:O91) -> #N/A | Q91: {=XLOOKUP(B91,'Calculations As per GA Data'!B109:B230,'Calculations As per GA Data'!J109:J230)} -> #VALUE! | R91: {=XLOOKUP(B91,'Calculations As per GA Data'!B109:B230,'Calculations As per GA Data'!F109:F230)} -> NA | S91: =P91-Q91 -> #N/A | T91: =S91/I91 -> #N/A | U91: 229 | V91: =S91-U91 -> #N/A | W91: =V91/I91 -> #N/A
A92: FF Dino | B92: Dabble Flip Flap Make Your Own Dinosaur | Travel-Friendly No Mess DIY Activity Set - Dinosaur | C92: FF Dino | D92: {=XLOOKUP(B92,'Calculations As per GA Data'!B110:B231,'Calculations As per GA Data'!G110:G231)} -> 0 | E92: 549 | F92: =E92/1.18 -> 465.25424 | G92: 4.75 | H92: {=XLOOKUP(B92,'Discount calculation'!A:A,'Discount calculation'!D:D)} -> #N/A | I92: =F92-SUM(G92:H92) -> #N/A | K92: =I92-J92 -> #N/A | M92: 7.52 | N92: #DIV/0! | O92: 4.55 | P92: =K92-SUM(L92:O92) -> #N/A | Q92: {=XLOOKUP(B92,'Calculations As per GA Data'!B110:B231,'Calculations As per GA Data'!J110:J231)} -> #DIV/0! | R92: {=XLOOKUP(B92,'Calculations As per GA Data'!B110:B231,'Calculations As per GA Data'!F110:F231)} -> 0 | S92: =P92-Q92 -> #N/A | T92: =S92/I92 -> #N/A | U92: 229 | V92: =S92-U92 -> #N/A | W92: =V92/I92 -> #N/A
A93: FF Unicorn | B93: Dabble Flip Flap Make Your Own Dinosaur | Travel-Friendly No Mess DIY Activity Set - Unicorn & Princ | C93: FF Unicorn | D93: {=XLOOKUP(B93,'Calculations As per GA Data'!B111:B232,'Calculations As per GA Data'!G111:G232)} -> #N/A | E93: 549 | F93: =E93/1.18 -> 465.25424 | G93: 4.75 | H93: {=XLOOKUP(B93,'Discount calculation'!A:A,'Discount calculation'!D:D)} -> #N/A | I93: =F93-SUM(G93:H93) -> #N/A | K93: =I93-J93 -> #N/A | M93: 7.52 | N93: #VALUE! | O93: 4.55 | P93: =K93-SUM(L93:O93) -> #N/A | Q93: {=XLOOKUP(B93,'Calculations As per GA Data'!B111:B232,'Calculations As per GA Data'!J111:J232)} -> #VALUE! | R93: {=XLOOKUP(B93,'Calculations As per GA Data'!B111:B232,'Calculations As per GA Data'!F111:F232)} -> NA | S93: =P93-Q93 -> #N/A | T93: =S93/I93 -> #N/A | U93: 229 | V93: =S93-U93 -> #N/A | W93: =V93/I93 -> #N/A
A94: GC | B94: Dabble Gift Card | C94: GC | D94: {=XLOOKUP(B94,'Calculations As per GA Data'!B112:B233,'Calculations As per GA Data'!G112:G233)} -> 0 | E94: NA | F94: =E94/1.18 -> #VALUE! | G94: 4.75 | H94: {=XLOOKUP(B94,'Discount calculation'!A:A,'Discount calculation'!D:D)} -> #N/A | I94: =F94-SUM(G94:H94) -> #VALUE! | K94: =I94-J94 -> #VALUE! | M94: 7.52 | N94: #VALUE! | O94: 4.55 | P94: =K94-SUM(L94:O94) -> #VALUE! | Q94: {=XLOOKUP(B94,'Calculations As per GA Data'!B112:B233,'Calculations As per GA Data'!J112:J233)} -> #DIV/0! | R94: {=XLOOKUP(B94,'Calculations As per GA Data'!B112:B233,'Calculations As per GA Data'!F112:F233)} -> 0 | S94: =P94-Q94 -> #VALUE! | T94: =S94/I94 -> #VALUE! | U94: 229 | V94: =S94-U94 -> #VALUE! | W94: =V94/I94 -> #VALUE!
A95: GC | B95: Dabble Gift Card - â‚¹5,000.00 | C95: GC | D95: {=XLOOKUP(B95,'Calculations As per GA Data'!B113:B234,'Calculations As per GA Data'!G113:G234)} -> #N/A | E95: NA | F95: =E95/1.18 -> #VALUE! | G95: 4.75 | H95: {=XLOOKUP(B95,'Discount calculation'!A:A,'Discount calculation'!D:D)} -> #N/A | I95: =F95-SUM(G95:H95) -> #VALUE! | K95: =I95-J95 -> #VALUE! | M95: 7.52 | N95: #VALUE! | O95: 4.55 | P95: =K95-SUM(L95:O95) -> #VALUE! | Q95: {=XLOOKUP(B95,'Calculations As per GA Data'!B113:B234,'Calculations As per GA Data'!J113:J234)} -> #VALUE! | R95: {=XLOOKUP(B95,'Calculations As per GA Data'!B113:B234,'Calculations As per GA Data'!F113:F234)} -> NA | S95: =P95-Q95 -> #VALUE! | T95: =S95/I95 -> #VALUE! | U95: 229 | V95: =S95-U95 -> #VALUE! | W95: =V95/I95 -> #VALUE!
A96: GC | B96: Dabble Gift Card - â‚¹500.00 | C96: GC | D96: {=XLOOKUP(B96,'Calculations As per GA Data'!B114:B235,'Calculations As per GA Data'!G114:G235)} -> #N/A | E96: NA | F96: =E96/1.18 -> #VALUE! | G96: 4.75 | H96: {=XLOOKUP(B96,'Discount calculation'!A:A,'Discount calculation'!D:D)} -> #N/A | I96: =F96-SUM(G96:H96) -> #VALUE! | K96: =I96-J96 -> #VALUE! | M96: 7.52 | N96: #VALUE! | O96: 4.55 | P96: =K96-SUM(L96:O96) -> #VALUE! | Q96: {=XLOOKUP(B96,'Calculations As per GA Data'!B114:B235,'Calculations As per GA Data'!J114:J235)} -> #VALUE! | R96: {=XLOOKUP(B96,'Calculations As per GA Data'!B114:B235,'Calculations As per GA Data'!F114:F235)} -> NA | S96: =P96-Q96 -> #VALUE! | T96: =S96/I96 -> #VALUE! | U96: 229 | V96: =S96-U96 -> #VALUE! | W96: =V96/I96 -> #VALUE!
A97: FP3+B8 | B97: Dabble Gift Set | Crayons + Finger Paints | C97: Combo | D97: {=XLOOKUP(B97,'Calculations As per GA Data'!B115:B236,'Calculations As per GA Data'!G115:G236)} -> 5379.9999 | E97: 1098 | F97: =E97/1.18 -> 930.50847 | G97: 4.75 | H97: {=XLOOKUP(B97,'Discount calculation'!A:A,'Discount calculation'!D:D)} -> 23.293333 | I97: =F97-SUM(G97:H97) -> 902.46514 | K97: =I97-J97 -> 902.46514 | M97: 7.52 | N97: 104.266 | O97: 4.55 | P97: =K97-SUM(L97:O97) -> 786.12914 | Q97: {=XLOOKUP(B97,'Calculations As per GA Data'!B115:B236,'Calculations As per GA Data'!J115:J236)} -> 597.9898 | R97: {=XLOOKUP(B97,'Calculations As per GA Data'!B115:B236,'Calculations As per GA Data'!F115:F236)} -> 5 | S97: =P97-Q97 -> 188.13934 | T97: =S97/I97 -> 0.20847269 | U97: 229 | V97: =S97-U97 -> -40.860661 | W97: =V97/I97 -> -0.04527672
A98: Dino Patch | B98: Dabble Iron On Patch - Dinosaur | C98: Dino Patch | D98: {=XLOOKUP(B98,'Calculations As per GA Data'!B116:B237,'Calculations As per GA Data'!G116:G237)} -> #N/A | E98: 200 | F98: =E98/1.18 -> 169.49153 | G98: 4.75 | H98: {=XLOOKUP(B98,'Discount calculation'!A:A,'Discount calculation'!D:D)} -> #N/A | I98: =F98-SUM(G98:H98) -> #N/A | K98: =I98-J98 -> #N/A | M98: 7.52 | N98: #VALUE! | O98: 4.55 | P98: =K98-SUM(L98:O98) -> #N/A | Q98: {=XLOOKUP(B98,'Calculations As per GA Data'!B116:B237,'Calculations As per GA Data'!J116:J237)} -> #VALUE! | R98: {=XLOOKUP(B98,'Calculations As per GA Data'!B116:B237,'Calculations As per GA Data'!F116:F237)} -> NA | S98: =P98-Q98 -> #N/A | T98: =S98/I98 -> #N/A | U98: 229 | V98: =S98-U98 -> #N/A | W98: =V98/I98 -> #N/A
A99: Unicorn Patch | B99: Dabble Iron On Patch - Unicorn | C99: Unicorn Patch | D99: {=XLOOKUP(B99,'Calculations As per GA Data'!B117:B238,'Calculations As per GA Data'!G117:G238)} -> #N/A | E99: 200 | F99: =E99/1.18 -> 169.49153 | G99: 4.75 | H99: {=XLOOKUP(B99,'Discount calculation'!A:A,'Discount calculation'!D:D)} -> #N/A | I99: =F99-SUM(G99:H99) -> #N/A | K99: =I99-J99 -> #N/A | M99: 7.52 | N99: #VALUE! | O99: 4.55 | P99: =K99-SUM(L99:O99) -> #N/A | Q99: {=XLOOKUP(B99,'Calculations As per GA Data'!B117:B238,'Calculations As per GA Data'!J117:J238)} -> #VALUE! | R99: {=XLOOKUP(B99,'Calculations As per GA Data'!B117:B238,'Calculations As per GA Data'!F117:F238)} -> NA | S99: =P99-Q99 -> #N/A | T99: =S99/I99 -> #N/A | U99: 229 | V99: =S99-U99 -> #N/A | W99: =V99/I99 -> #N/A
A100: Unicorn Kit | B100: Dabble UNICORN STENCIL ART & CRAFT Kit - Pack of 1 | C100: Unicorn Kit | D100: {=XLOOKUP(B100,'Calculations As per GA Data'!B118:B239,'Calculations As per GA Data'!G118:G239)} -> #N/A | E100: 399 | F100: =E100/1.18 -> 338.13559 | G100: 4.75 | H100: {=XLOOKUP(B100,'Discount calculation'!A:A,'Discount calculation'!D:D)} -> #N/A | I100: =F100-SUM(G100:H100) -> #N/A | K100: =I100-J100 -> #N/A | M100: 7.52 | N100: #VALUE! | O100: 4.55 | P100: =K100-SUM(L100:O100) -> #N/A | Q100: {=XLOOKUP(B100,'Calculations As per GA Data'!B118:B239,'Calculations As per GA Data'!J118:J239)} -> #VALUE! | R100: {=XLOOKUP(B100,'Calculations As per GA Data'!B118:B239,'Calculations As per GA Data'!F118:F239)} -> NA | S100: =P100-Q100 -> #N/A | T100: =S100/I100 -> #N/A | U100: 229 | V100: =S100-U100 -> #N/A | W100: =V100/I100 -> #N/A
A101: Unicorn Kit | B101: Dabble UNICORN STENCIL ART & CRAFT Kit - Pack of 10 | C101: Unicorn Kit | D101: {=XLOOKUP(B101,'Calculations As per GA Data'!B119:B240,'Calculations As per GA Data'!G119:G240)} -> #N/A | E101: 3990 | F101: =E101/1.18 -> 3381.3559 | G101: 4.75 | H101: {=XLOOKUP(B101,'Discount calculation'!A:A,'Discount calculation'!D:D)} -> #N/A | I101: =F101-SUM(G101:H101) -> #N/A | K101: =I101-J101 -> #N/A | M101: 7.52 | N101: #VALUE! | O101: 4.55 | P101: =K101-SUM(L101:O101) -> #N/A | Q101: {=XLOOKUP(B101,'Calculations As per GA Data'!B119:B240,'Calculations As per GA Data'!J119:J240)} -> #VALUE! | R101: {=XLOOKUP(B101,'Calculations As per GA Data'!B119:B240,'Calculations As per GA Data'!F119:F240)} -> NA | S101: =P101-Q101 -> #N/A | T101: =S101/I101 -> #N/A | U101: 229 | V101: =S101-U101 -> #N/A | W101: =V101/I101 -> #N/A
A102: Unicorn Kit | B102: Dabble UNICORN STENCIL ART & CRAFT Kit - Pack of 5 | C102: Unicorn Kit | D102: {=XLOOKUP(B102,'Calculations As per GA Data'!B120:B241,'Calculations As per GA Data'!G120:G241)} -> #N/A | E102: 1995 | F102: =E102/1.18 -> 1690.678 | G102: 4.75 | H102: {=XLOOKUP(B102,'Discount calculation'!A:A,'Discount calculation'!D:D)} -> #N/A | I102: =F102-SUM(G102:H102) -> #N/A | K102: =I102-J102 -> #N/A | M102: 7.52 | N102: #VALUE! | O102: 4.55 | P102: =K102-SUM(L102:O102) -> #N/A | Q102: {=XLOOKUP(B102,'Calculations As per GA Data'!B120:B241,'Calculations As per GA Data'!J120:J241)} -> #VALUE! | R102: {=XLOOKUP(B102,'Calculations As per GA Data'!B120:B241,'Calculations As per GA Data'!F120:F241)} -> NA | S102: =P102-Q102 -> #N/A | T102: =S102/I102 -> #N/A | U102: 229 | V102: =S102-U102 -> #N/A | W102: =V102/I102 -> #N/A
A103: Digital Playbook | B103: Digital Playbook worth â‚¹499 | C103: Digital Book | D103: {=XLOOKUP(B103,'Calculations As per GA Data'!B121:B242,'Calculations As per GA Data'!G121:G242)} -> 0 | E103: NA | F103: NA | G103: 4.75 | H103: {=XLOOKUP(B103,'Discount calculation'!A:A,'Discount calculation'!D:D)} -> #N/A | I103: =F103-SUM(G103:H103) -> #N/A | K103: =I103-J103 -> #N/A | M103: 7.52 | N103: #VALUE! | O103: 4.55 | P103: =K103-SUM(L103:O103) -> #N/A | Q103: {=XLOOKUP(B103,'Calculations As per GA Data'!B121:B242,'Calculations As per GA Data'!J121:J242)} -> 69.347533 | R103: {=XLOOKUP(B103,'Calculations As per GA Data'!B121:B242,'Calculations As per GA Data'!F121:F242)} -> 1511 | S103: =P103-Q103 -> #N/A | T103: =S103/I103 -> #N/A | U103: 229 | V103: =S103-U103 -> #N/A | W103: =V103/I103 -> #N/A
A104: FF Unicorn+B8 | B104: Flip Flap Crayon Play Pack Unicorn & Princesses Themed | Activity Book with Crayons | | C104: Combo | D104: {=XLOOKUP(B104,'Calculations As per GA Data'!B122:B243,'Calculations As per GA Data'!G122:G243)} -> 978 | E104: 998 | F104: =E104/1.18 -> 845.76271 | G104: 4.75 | H104: {=XLOOKUP(B104,'Discount calculation'!A:A,'Discount calculation'!D:D)} -> 20.61 | I104: =F104-SUM(G104:H104) -> 820.40271 | K104: =I104-J104 -> 820.40271 | M104: 7.52 | N104: 62.79 | O104: 4.55 | P104: =K104-SUM(L104:O104) -> 745.54271 | Q104: {=XLOOKUP(B104,'Calculations As per GA Data'!B122:B243,'Calculations As per GA Data'!J122:J243)} -> 1494.9745 | R104: {=XLOOKUP(B104,'Calculations As per GA Data'!B122:B243,'Calculations As per GA Data'!F122:F243)} -> 1 | S104: =P104-Q104 -> -749.43179 | T104: =S104/I104 -> -0.91349259 | U104: 229 | V104: =S104-U104 -> -978.43179 | W104: =V104/I104 -> -1.1926238
A105: Fridge Magnet | B105: Fridge Magnet work â‚¹299 | C105: Fridge Magnet | D105: {=XLOOKUP(B105,'Calculations As per GA Data'!B123:B244,'Calculations As per GA Data'!G123:G244)} -> 0 | E105: NA | F105: NA | G105: 4.75 | H105: {=XLOOKUP(B105,'Discount calculation'!A:A,'Discount calculation'!D:D)} -> #N/A | I105: =F105-SUM(G105:H105) -> #N/A | K105: =I105-J105 -> #N/A | M105: 7.52 | N105: #VALUE! | O105: 4.55 | P105: =K105-SUM(L105:O105) -> #N/A | Q105: {=XLOOKUP(B105,'Calculations As per GA Data'!B123:B244,'Calculations As per GA Data'!J123:J244)} -> 67.025062 | R105: {=XLOOKUP(B105,'Calculations As per GA Data'!B123:B244,'Calculations As per GA Data'!F123:F244)} -> 549 | S105: =P105-Q105 -> #N/A | T105: =S105/I105 -> #N/A | U105: 229 | V105: =S105-U105 -> #N/A | W105: =V105/I105 -> #N/A
A106: ABC Caryons | B106: My Dabble ABC Trace & Colour Kit | Multi-Sensory Alphabet Learning for Kids - Crayons - Crayons | C106: ABC Caryons | D106: {=XLOOKUP(B106,'Calculations As per GA Data'!B124:B245,'Calculations As per GA Data'!G124:G245)} -> #N/A | E106: NA | F106: =E106/1.18 -> #VALUE! | G106: 4.75 | H106: {=XLOOKUP(B106,'Discount calculation'!A:A,'Discount calculation'!D:D)} -> #N/A | I106: =F106-SUM(G106:H106) -> #VALUE! | K106: =I106-J106 -> #VALUE! | M106: 7.52 | N106: #VALUE! | O106: 4.55 | P106: =K106-SUM(L106:O106) -> #VALUE! | Q106: {=XLOOKUP(B106,'Calculations As per GA Data'!B124:B245,'Calculations As per GA Data'!J124:J245)} -> #VALUE! | R106: {=XLOOKUP(B106,'Calculations As per GA Data'!B124:B245,'Calculations As per GA Data'!F124:F245)} -> NA | S106: =P106-Q106 -> #VALUE! | T106: =S106/I106 -> #VALUE! | U106: 229 | V106: =S106-U106 -> #VALUE! | W106: =V106/I106 -> #VALUE!
A107: ABC Paint | B107: My Dabble ABC Trace & Colour Kit | Multi-Sensory Alphabet Learning for Kids - Paints | C107: ABC Paint | D107: {=XLOOKUP(B107,'Calculations As per GA Data'!B125:B246,'Calculations As per GA Data'!G125:G246)} -> 0 | E107: NA | F107: =E107/1.18 -> #VALUE! | G107: 7.7 | H107: {=XLOOKUP(B107,'Discount calculation'!A:A,'Discount calculation'!D:D)} -> #N/A | I107: =F107-SUM(G107:H107) -> #VALUE! | K107: =I107-J107 -> #VALUE! | M107: 6.3131216 | N107: 48.945942 | O107: 3.2017966 | P107: =K107-SUM(L107:O107) -> #VALUE! | Q107: {=XLOOKUP(B107,'Calculations As per GA Data'!B125:B246,'Calculations As per GA Data'!J125:J246)} -> #DIV/0! | R107: {=XLOOKUP(B107,'Calculations As per GA Data'!B125:B246,'Calculations As per GA Data'!F125:F246)} -> 0 | S107: =P107-Q107 -> #VALUE! | T107: =S107/I107 -> #VALUE! | U107: 270 | V107: =S107-U107 -> #VALUE! | W107: =V107/I107 -> #VALUE!
A108: ABC Paint | B108: My Dabble ABC Trace & Colour Kit | Multi-Sensory Alphabet Learning for Kids - Paints - Paints | C108: ABC Paint | D108: {=XLOOKUP(B108,'Calculations As per GA Data'!B126:B247,'Calculations As per GA Data'!G126:G247)} -> #N/A | E108: 599 | F108: =E108/1.18 -> 507.62712 | G108: 7.7 | H108: {=XLOOKUP(B108,'Discount calculation'!A:A,'Discount calculation'!D:D)} -> #N/A | I108: =F108-SUM(G108:H108) -> #N/A | K108: =I108-J108 -> #N/A | M108: 6.3131216 | N108: 48.945942 | O108: 3.2017966 | P108: =K108-SUM(L108:O108) -> #N/A | Q108: {=XLOOKUP(B108,'Calculations As per GA Data'!B126:B247,'Calculations As per GA Data'!J126:J247)} -> #VALUE! | R108: {=XLOOKUP(B108,'Calculations As per GA Data'!B126:B247,'Calculations As per GA Data'!F126:F247)} -> NA | S108: =P108-Q108 -> #N/A | T108: =S108/I108 -> #N/A | U108: 270 | V108: =S108-U108 -> #N/A | W108: =V108/I108 -> #N/A
A109: ABC Caryons | B109: My Dabble ABC Trace &amp; Colour Kit | Multi-Sensory Alphabet Learning for Kids - Crayons | C109: ABC Caryons | D109: {=XLOOKUP(B109,'Calculations As per GA Data'!B127:B248,'Calculations As per GA Data'!G127:G248)} -> 0 | E109: NA | F109: =E109/1.18 -> #VALUE! | G109: 7.7 | H109: {=XLOOKUP(B109,'Discount calculation'!A:A,'Discount calculation'!D:D)} -> #N/A | I109: =F109-SUM(G109:H109) -> #VALUE! | K109: =I109-J109 -> #VALUE! | M109: 6.3131216 | N109: 48.945942 | O109: 3.2017966 | P109: =K109-SUM(L109:O109) -> #VALUE! | Q109: {=XLOOKUP(B109,'Calculations As per GA Data'!B127:B248,'Calculations As per GA Data'!J127:J248)} -> #DIV/0! | R109: {=XLOOKUP(B109,'Calculations As per GA Data'!B127:B248,'Calculations As per GA Data'!F127:F248)} -> 0 | S109: =P109-Q109 -> #VALUE! | T109: =S109/I109 -> #VALUE! | U109: 270 | V109: =S109-U109 -> #VALUE! | W109: =V109/I109 -> #VALUE!
A110: ABC Paints | B110: My Dabble ABC Trace &amp; Colour Kit | Multi-Sensory Alphabet Learning for Kids - Paints | C110: ABC Paints | D110: {=XLOOKUP(B110,'Calculations As per GA Data'!B128:B249,'Calculations As per GA Data'!G128:G249)} -> 0 | E110: NA | F110: =E110/1.18 -> #VALUE! | G110: 7.7 | H110: {=XLOOKUP(B110,'Discount calculation'!A:A,'Discount calculation'!D:D)} -> #N/A | I110: =F110-SUM(G110:H110) -> #VALUE! | K110: =I110-J110 -> #VALUE! | M110: 6.3131216 | N110: 48.945942 | O110: 3.2017966 | P110: =K110-SUM(L110:O110) -> #VALUE! | Q110: {=XLOOKUP(B110,'Calculations As per GA Data'!B128:B249,'Calculations As per GA Data'!J128:J249)} -> #DIV/0! | R110: {=XLOOKUP(B110,'Calculations As per GA Data'!B128:B249,'Calculations As per GA Data'!F128:F249)} -> 0 | S110: =P110-Q110 -> #VALUE! | T110: =S110/I110 -> #VALUE! | U110: 270 | V110: =S110-U110 -> #VALUE! | W110: =V110/I110 -> #VALUE!
A111: Puzzle Set | B111: My First Dabble Puzzle Colouring Set - Emotions, Shapes &amp; Colours | C111: Puzzle Set | D111: {=XLOOKUP(B111,'Calculations As per GA Data'!B129:B250,'Calculations As per GA Data'!G129:G250)} -> 0 | E111: 999 | F111: =E111/1.18 -> 846.61017 | G111: 7.7 | H111: {=XLOOKUP(B111,'Discount calculation'!A:A,'Discount calculation'!D:D)} -> #N/A | I111: =F111-SUM(G111:H111) -> #N/A | K111: =I111-J111 -> #N/A | M111: 6.3131216 | N111: 48.945942 | O111: 3.2017966 | P111: =K111-SUM(L111:O111) -> #N/A | Q111: {=XLOOKUP(B111,'Calculations As per GA Data'!B129:B250,'Calculations As per GA Data'!J129:J250)} -> #DIV/0! | R111: {=XLOOKUP(B111,'Calculations As per GA Data'!B129:B250,'Calculations As per GA Data'!F129:F250)} -> 0 | S111: =P111-Q111 -> #N/A | T111: =S111/I111 -> #N/A | U111: 270 | V111: =S111-U111 -> #N/A | W111: =V111/I111 -> #N/A
A112: T&F+FP3 | B112: My first dabble Touch & Feel Colouring pages for toddlers + Baby's First Finger Paints | C112: Combo | D112: {=XLOOKUP(B112,'Calculations As per GA Data'!B130:B251,'Calculations As per GA Data'!G130:G251)} -> 1470 | E112: NA | F112: =E112/1.18 -> #VALUE! | G112: 7.7 | H112: {=XLOOKUP(B112,'Discount calculation'!A:A,'Discount calculation'!D:D)} -> 23.985185 | I112: =F112-SUM(G112:H112) -> #VALUE! | K112: =I112-J112 -> #VALUE! | M112: 6.3131216 | N112: 48.945942 | O112: 3.2017966 | P112: =K112-SUM(L112:O112) -> #VALUE! | Q112: {=XLOOKUP(B112,'Calculations As per GA Data'!B130:B251,'Calculations As per GA Data'!J130:J251)} -> 2242.4618 | R112: {=XLOOKUP(B112,'Calculations As per GA Data'!B130:B251,'Calculations As per GA Data'!F130:F251)} -> 1 | S112: =P112-Q112 -> #VALUE! | T112: =S112/I112 -> #VALUE! | U112: 270 | V112: =S112-U112 -> #VALUE! | W112: =V112/I112 -> #VALUE!
...

Sheet Calculations As per GA Data
C2: April | D2: May | E2: June
B3: Shipping Charges | C3: 1,54,407 | D3: 99613 | E3: 1,42,649 | F3: =SUM(C3:E3) -> 99613
B4: Shipping Collection | C4: 8869 | D4: 13524 | E4: 25774 | F4: =SUM(C4:E4) -> 48167 | G4: =F3-F4 -> 51446 | H4: =G4/$C$14 -> 10.475667
B5: Cancellations/returns | C5: 8283 | D5: 3966 | E5: 11097 | F5: =SUM(C5:E5) -> 23346 | H5: =F5/$C$14 -> 4.753818
B6: Discounts | C6: 117671 | D6: 151369 | E6: 151614 | F6: =SUM(C6:E6) -> 420654 | H6: =F6/$C$14 -> 85.655467
B7: Razor pay Deductions | C7: 10612 | D7: 14239 | E7: 12100 | F7: =SUM(C7:E7) -> 36951 | H7: =F7/$C$14 -> 7.5241295
B8: COD Costs | C8: 10073 | D8: 5605 | E8: 6697 | F8: =SUM(C8:E8) -> 22375 | H8: =F8/$C$14 -> 4.5560986
B9: OH Costs | C9: 234 | D9: 191 | E9: 263 | F9: =SUM(C9:E9) -> 688
B10: Google+meta | C10: 352262 | D10: 610707 | E10: 561939 | F10: =SUM(C10:E10) -> 1524908
B11: Bik | C11: 30000 | D11: 15000 | E11: 0 | F11: =SUM(C11:E11) -> 45000
B12: Total Marketing Cost | F12: =SUM(F3:F11) -> 2221702
B13: Cost Per Session | C13: =F12/SUM(D21:D141) -> 33.976693 | H13: =F12/C14 -> 452.393
B14: Total Units Sold In the Last 3 Months | C14: =SUM(F21:F135) -> 4911
B15: Total Sessions | C15: =SUM(D21:D141) -> 65389
B20: Item name | C20: Product | D20: Sessions | E20: Cost Spent | F20: Units sold | G20: Revenue | H20: Items viewed | I20: Items added to cart | J20: Marketing Cost | K20: Item name | L20: Product | M20: CONV
B21: Magic Paint Dust – Baby’s First Painting Kit | C21: =IFERROR(VLOOKUP(B21,K:L,2,0),"NA") -> magic paint dust | D21: {=XLOOKUP(B21,'Google analytics'!A:A,'Google analytics'!F:F)} -> 7147 | E21: =D21*$C$13 -> 242831.43 | F21: {=XLOOKUP(B21,'Data Analytics rawData'!A:A,'Data Analytics rawData'!D:D)} -> 221 | G21: {=XLOOKUP(B21,'Data Analytics rawData'!A:A,'Data Analytics rawData'!E:E)} -> 192044 | H21: {=XLOOKUP(B21,'Data Analytics rawData'!A:A,'Data Analytics rawData'!B:B)} -> 7870 | I21: {=XLOOKUP(B21,'Data Analytics rawData'!A:A,'Data Analytics rawData'!C:C)} -> 781 | J21: =E21/F21 -> 1098.7847 | K21: dabble Sensory Playdough | L21: Playdough | M21: =F21/D21 -> 0.030922065
B22: dabble Sensory Playdough | C22: =IFERROR(VLOOKUP(B22,K:L,2,0),"NA") -> Playdough | D22: {=XLOOKUP(B22,'Google analytics'!A:A,'Google analytics'!F:F)} -> 6541 | E22: =D22*$C$13 -> 222241.55 | F22: {=XLOOKUP(B22,'Data Analytics rawData'!A:A,'Data Analytics rawData'!D:D)} -> 214 | G22: {=XLOOKUP(B22,'Data Analytics rawData'!A:A,'Data Analytics rawData'!E:E)} -> 190336 | H22: {=XLOOKUP(B22,'Data Analytics rawData'!A:A,'Data Analytics rawData'!B:B)} -> 7039 | I22: {=XLOOKUP(B22,'Data Analytics rawData'!A:A,'Data Analytics rawData'!C:C)} -> 761 | J22: =E22/F22 -> 1038.5119 | K22: Magic Paint Dust – Baby’s First Painting Kit | L22: magic paint dust | M22: =F22/D22 -> 0.03271671
B23: Dabble Finger Painting Fun Pack | C23: =IFERROR(VLOOKUP(B23,K:L,2,0),"NA") -> FP8+CB | D23: {=XLOOKUP(B23,'Google analytics'!A:A,'Google analytics'!F:F)} -> 2341 | E23: =D23*$C$13 -> 79539.439 | F23: {=XLOOKUP(B23,'Data Analytics rawData'!A:A,'Data Analytics rawData'!D:D)} -> 122 | G23: {=XLOOKUP(B23,'Data Analytics rawData'!A:A,'Data Analytics rawData'!E:E)} -> 157681 | H23: {=XLOOKUP(B23,'Data Analytics rawData'!A:A,'Data Analytics rawData'!B:B)} -> 2509 | I23: {=XLOOKUP(B23,'Data Analytics rawData'!A:A,'Data Analytics rawData'!C:C)} -> 408 | J23: =E23/F23 -> 651.96262 | K23: Dabble Playart Chunkies | L23: B3 | M23: =F23/D23 -> 0.052114481
B24: Babyâ€™s first handprint and footprint kit | C24: Canvas Kit | D24: {=XLOOKUP(B24,'Google analytics'!A:A,'Google analytics'!F:F)} -> 5252 | E24: =D24*$C$13 -> 178445.59 | F24: {=XLOOKUP(B24,'Data Analytics rawData'!A:A,'Data Analytics rawData'!D:D)} -> 160 | G24: {=XLOOKUP(B24,'Data Analytics rawData'!A:A,'Data Analytics rawData'!E:E)} -> 113540 | H24: {=XLOOKUP(B24,'Data Analytics rawData'!A:A,'Data Analytics rawData'!B:B)} -> 5707 | I24: {=XLOOKUP(B24,'Data Analytics rawData'!A:A,'Data Analytics rawData'!C:C)} -> 623 | J24: =E24/F24 -> 1115.285 | K24: Dabble Finger Painting Fun Pack | L24: FP8+CB | M24: =F24/D24 -> 0.030464585
B25: Mini Starter Finger Painting Fun Pack | C25: =IFERROR(VLOOKUP(B25,K:L,2,0),"NA") -> SFP | D25: {=XLOOKUP(B25,'Google analytics'!A:A,'Google analytics'!F:F)} -> 2316 | E25: =D25*$C$13 -> 78690.022 | F25: {=XLOOKUP(B25,'Data Analytics rawData'!A:A,'Data Analytics rawData'!D:D)} -> 171 | G25: {=XLOOKUP(B25,'Data Analytics rawData'!A:A,'Data Analytics rawData'!E:E)} -> 101319 | H25: {=XLOOKUP(B25,'Data Analytics rawData'!A:A,'Data Analytics rawData'!B:B)} -> 2356 | I25: {=XLOOKUP(B25,'Data Analytics rawData'!A:A,'Data Analytics rawData'!C:C)} -> 636 | J25: =E25/F25 -> 460.17557 | K25: Baby’s Starter Painting + Jumbo Brush Combo Kit | L25: SFP+JB | M25: =F25/D25 -> 0.073834197
B26: Babyâ€™s Starter Painting + Jumbo Brush Combo Kit | C26: SFP+JB | D26: {=XLOOKUP(B26,'Google analytics'!A:A,'Google analytics'!F:F)} -> 1055 | E26: =D26*$C$13 -> 35845.411 | F26: {=XLOOKUP(B26,'Data Analytics rawData'!A:A,'Data Analytics rawData'!D:D)} -> 75 | G26: {=XLOOKUP(B26,'Data Analytics rawData'!A:A,'Data Analytics rawData'!E:E)} -> 79281 | H26: {=XLOOKUP(B26,'Data Analytics rawData'!A:A,'Data Analytics rawData'!B:B)} -> 1094 | I26: {=XLOOKUP(B26,'Data Analytics rawData'!A:A,'Data Analytics rawData'!C:C)} -> 221 | J26: =E26/F26 -> 477.93882 | K26: Mini Starter Finger Painting Fun Pack | L26: SFP | M26: =F26/D26 -> 0.071090047
B27: Dabble Playart Chunkies | C27: =IFERROR(VLOOKUP(B27,K:L,2,0),"NA") -> B3 | D27: {=XLOOKUP(B27,'Google analytics'!A:A,'Google analytics'!F:F)} -> 3472 | E27: =D27*$C$13 -> 117967.08 | F27: {=XLOOKUP(B27,'Data Analytics rawData'!A:A,'Data Analytics rawData'!D:D)} -> 129 | G27: {=XLOOKUP(B27,'Data Analytics rawData'!A:A,'Data Analytics rawData'!E:E)} -> 70820.999 | H27: {=XLOOKUP(B27,'Data Analytics rawData'!A:A,'Data Analytics rawData'!B:B)} -> 3746 | I27: {=XLOOKUP(B27,'Data Analytics rawData'!A:A,'Data Analytics rawData'!C:C)} -> 458 | J27: =E27/F27 -> 914.47348 | K27: Magic Paint Dust + Jumbo Brush Combo Kit – Baby’s First Painting Kit | L27: magic paint dust+jb | M27: =F27/D27 -> 0.037154378
B28: Little Artist Combo Kit | C28: =IFERROR(VLOOKUP(B28,K:L,2,0),"NA") -> FP8, B8, CB | D28: {=XLOOKUP(B28,'Google analytics'!A:A,'Google analytics'!F:F)} -> 1113 | E28: =D28*$C$13 -> 37816.06 | F28: {=XLOOKUP(B28,'Data Analytics rawData'!A:A,'Data Analytics rawData'!D:D)} -> 47 | G28: {=XLOOKUP(B28,'Data Analytics rawData'!A:A,'Data Analytics rawData'!E:E)} -> 81477 | H28: {=XLOOKUP(B28,'Data Analytics rawData'!A:A,'Data Analytics rawData'!B:B)} -> 1235 | I28: {=XLOOKUP(B28,'Data Analytics rawData'!A:A,'Data Analytics rawData'!C:C)} -> 158 | J28: =E28/F28 -> 804.59701 | K28: Little Artist Combo Kit | L28: FP8, B8, CB | M28: =F28/D28 -> 0.042228212
B29: Dabble Starter Painting + Chubby Brush Combo Kit | C29: =IFERROR(VLOOKUP(B29,K:L,2,0),"NA") -> SFP+CB | D29: {=XLOOKUP(B29,'Google analytics'!A:A,'Google analytics'!F:F)} -> 1333 | E29: =D29*$C$13 -> 45290.932 | F29: {=XLOOKUP(B29,'Data Analytics rawData'!A:A,'Data Analytics rawData'!D:D)} -> 90 | G29: {=XLOOKUP(B29,'Data Analytics rawData'!A:A,'Data Analytics rawData'!E:E)} -> 90842 | H29: {=XLOOKUP(B29,'Data Analytics rawData'!A:A,'Data Analytics rawData'!B:B)} -> 1383 | I29: {=XLOOKUP(B29,'Data Analytics rawData'!A:A,'Data Analytics rawData'!C:C)} -> 279 | J29: =E29/F29 -> 503.23258 | K29: Dabble Starter Painting + Chubby Brush Combo Kit | L29: SFP+CB | M29: =F29/D29 -> 0.067516879
B30: Dabble Finger Paints For Toddlers | C30: =IFERROR(VLOOKUP(B30,K:L,2,0),"NA") -> FP3 | D30: {=XLOOKUP(B30,'Google analytics'!A:A,'Google analytics'!F:F)} -> 1422 | E30: =D30*$C$13 -> 48314.858 | F30: {=XLOOKUP(B30,'Data Analytics rawData'!A:A,'Data Analytics rawData'!D:D)} -> 101 | G30: {=XLOOKUP(B30,'Data Analytics rawData'!A:A,'Data Analytics rawData'!E:E)} -> 63589 | H30: {=XLOOKUP(B30,'Data Analytics rawData'!A:A,'Data Analytics rawData'!B:B)} -> 1426 | I30: {=XLOOKUP(B30,'Data Analytics rawData'!A:A,'Data Analytics rawData'!C:C)} -> 350 | J30: =E30/F30 -> 478.36493 | K30: My Dabble ABC Trace & Colour Kit | Multi-Sensory Alphabet Learning for Kids | L30: ABC Kit | M30: =F30/D30 -> 0.071026723
B31: Dabble Art Roll | C31: =IFERROR(VLOOKUP(B31,K:L,2,0),"NA") -> AR | D31: {=XLOOKUP(B31,'Google analytics'!A:A,'Google analytics'!F:F)} -> 718 | E31: =D31*$C$13 -> 24395.266 | F31: {=XLOOKUP(B31,'Data Analytics rawData'!A:A,'Data Analytics rawData'!D:D)} -> 72 | G31: {=XLOOKUP(B31,'Data Analytics rawData'!A:A,'Data Analytics rawData'!E:E)} -> 50328 | H31: {=XLOOKUP(B31,'Data Analytics rawData'!A:A,'Data Analytics rawData'!B:B)} -> 596 | I31: {=XLOOKUP(B31,'Data Analytics rawData'!A:A,'Data Analytics rawData'!C:C)} -> 235 | J31: =E31/F31 -> 338.82314 | K31: Dabble Art Roll | L31: AR | M31: =F31/D31 -> 0.10027855
B32: Magic Paint Dust + Jumbo Brush Combo Kit â€“ Babyâ€™s First Painting Kit | C32: magic paint dust+jb | D32: {=XLOOKUP(B32,'Google analytics'!A:A,'Google analytics'!F:F)} -> 967 | E32: =D32*$C$13 -> 32855.462 | F32: {=XLOOKUP(B32,'Data Analytics rawData'!A:A,'Data Analytics rawData'!D:D)} -> 34 | G32: {=XLOOKUP(B32,'Data Analytics rawData'!A:A,'Data Analytics rawData'!E:E)} -> 45782 | H32: {=XLOOKUP(B32,'Data Analytics rawData'!A:A,'Data Analytics rawData'!B:B)} -> 1002 | I32: {=XLOOKUP(B32,'Data Analytics rawData'!A:A,'Data Analytics rawData'!C:C)} -> 110 | J32: =E32/F32 -> 966.33713 | K32: My First Dabble Swingin’ Jungle Adventure + Crayons Combo | L32: SJ+B8 | M32: =F32/D32 -> 0.03516029
B33: My First Dabble Swinginâ€™ Jungle Adventure + Crayons Combo | C33: SJ+B8 | D33: {=XLOOKUP(B33,'Google analytics'!A:A,'Google analytics'!F:F)} -> 808 | E33: =D33*$C$13 -> 27453.168 | F33: {=XLOOKUP(B33,'Data Analytics rawData'!A:A,'Data Analytics rawData'!D:D)} -> 29 | G33: {=XLOOKUP(B33,'Data Analytics rawData'!A:A,'Data Analytics rawData'!E:E)} -> 26411 | H33: {=XLOOKUP(B33,'Data Analytics rawData'!A:A,'Data Analytics rawData'!B:B)} -> 881 | I33: {=XLOOKUP(B33,'Data Analytics rawData'!A:A,'Data Analytics rawData'!C:C)} -> 129 | J33: =E33/F33 -> 946.66097 | K33: Magic Paint Dust + PlayArt Roll – Baby’s First Painting Kit | L33: MPD+AR | M33: =F33/D33 -> 0.035891089
B34: Masterpiece Set | C34: =IFERROR(VLOOKUP(B34,K:L,2,0),"NA") -> FP8+AR+CB | D34: {=XLOOKUP(B34,'Google analytics'!A:A,'Google analytics'!F:F)} -> 935 | E34: =D34*$C$13 -> 31768.208 | F34: {=XLOOKUP(B34,'Data Analytics rawData'!A:A,'Data Analytics rawData'!D:D)} -> 41 | G34: {=XLOOKUP(B34,'Data Analytics rawData'!A:A,'Data Analytics rawData'!E:E)} -> 80419 | H34: {=XLOOKUP(B34,'Data Analytics rawData'!A:A,'Data Analytics rawData'!B:B)} -> 1018 | I34: {=XLOOKUP(B34,'Data Analytics rawData'!A:A,'Data Analytics rawData'!C:C)} -> 156 | J34: =E34/F34 -> 774.83435 | K34: Baby's First Art Set | L34: B3+AR | M34: =F34/D34 -> 0.043850267
B35: Magic Paint Dust + PlayArt Roll â€“ Babyâ€™s First Painting Kit | C35: MPD+AR | D35: {=XLOOKUP(B35,'Google analytics'!A:A,'Google analytics'!F:F)} -> 729 | E35: =D35*$C$13 -> 24769.009 | F35: {=XLOOKUP(B35,'Data Analytics rawData'!A:A,'Data Analytics rawData'!D:D)} -> 25 | G35: {=XLOOKUP(B35,'Data Analytics rawData'!A:A,'Data Analytics rawData'!E:E)} -> 38622 | H35: {=XLOOKUP(B35,'Data Analytics rawData'!A:A,'Data Analytics rawData'!B:B)} -> 750 | I35: {=XLOOKUP(B35,'Data Analytics rawData'!A:A,'Data Analytics rawData'!C:C)} -> 73 | J35: =E35/F35 -> 990.76038 | K35: Dabble Painting Art Apron | L35: Apron | M35: =F35/D35 -> 0.034293553
B36: Baby's First Art Set | C36: =IFERROR(VLOOKUP(B36,K:L,2,0),"NA") -> B3+AR | D36: {=XLOOKUP(B36,'Google analytics'!A:A,'Google analytics'!F:F)} -> 549 | E36: =D36*$C$13 -> 18653.205 | F36: {=XLOOKUP(B36,'Data Analytics rawData'!A:A,'Data Analytics rawData'!D:D)} -> 12 | G36: {=XLOOKUP(B36,'Data Analytics rawData'!A:A,'Data Analytics rawData'!E:E)} -> 15345 | H36: {=XLOOKUP(B36,'Data Analytics rawData'!A:A,'Data Analytics rawData'!B:B)} -> 590 | I36: {=XLOOKUP(B36,'Data Analytics rawData'!A:A,'Data Analytics rawData'!C:C)} -> 56 | J36: =E36/F36 -> 1554.4337 | K36: Dabble Finger Paints For Toddlers | L36: FP3 | M36: =F36/D36 -> 0.021857924
B37: Dabble Reusable Colouring Pages Kit | C37: =IFERROR(VLOOKUP(B37,K:L,2,0),"NA") -> DP | D37: {=XLOOKUP(B37,'Google analytics'!A:A,'Google analytics'!F:F)} -> 659 | E37: =D37*$C$13 -> 22390.641 | F37: {=XLOOKUP(B37,'Data Analytics rawData'!A:A,'Data Analytics rawData'!D:D)} -> 67 | G37: {=XLOOKUP(B37,'Data Analytics rawData'!A:A,'Data Analytics rawData'!E:E)} -> 24159.85 | H37: {=XLOOKUP(B37,'Data Analytics rawData'!A:A,'Data Analytics rawData'!B:B)} -> 599 | I37: {=XLOOKUP(B37,'Data Analytics rawData'!A:A,'Data Analytics rawData'!C:C)} -> 115 | J37: =E37/F37 -> 334.18867 | K37: Dabble Reusable Colouring Pages Kit | L37: DP | M37: =F37/D37 -> 0.1016692
B38: Dabble Painting Art Apron | C38: =IFERROR(VLOOKUP(B38,K:L,2,0),"NA") -> Apron | D38: {=XLOOKUP(B38,'Google analytics'!A:A,'Google analytics'!F:F)} -> 475 | E38: =D38*$C$13 -> 16138.929 | F38: {=XLOOKUP(B38,'Data Analytics rawData'!A:A,'Data Analytics rawData'!D:D)} -> 50 | G38: {=XLOOKUP(B38,'Data Analytics rawData'!A:A,'Data Analytics rawData'!E:E)} -> 38751.5 | H38: {=XLOOKUP(B38,'Data Analytics rawData'!A:A,'Data Analytics rawData'!B:B)} -> 381 | I38: {=XLOOKUP(B38,'Data Analytics rawData'!A:A,'Data Analytics rawData'!C:C)} -> 131 | J38: =E38/F38 -> 322.77859 | K38: Masterpiece Set | L38: FP8+AR+CB | M38: =F38/D38 -> 0.10526316
B39: My Dabble ABC Trace & Colour Kit | Multi-Sensory Alphabet Learning for Kids | C39: =IFERROR(VLOOKUP(B39,K:L,2,0),"NA") -> ABC Kit | D39: {=XLOOKUP(B39,'Google analytics'!A:A,'Google analytics'!F:F)} -> 2473 | E39: =D39*$C$13 -> 84024.363 | F39: {=XLOOKUP(B39,'Data Analytics rawData'!A:A,'Data Analytics rawData'!D:D)} -> 98 | G39: {=XLOOKUP(B39,'Data Analytics rawData'!A:A,'Data Analytics rawData'!E:E)} -> 58561.999 | H39: {=XLOOKUP(B39,'Data Analytics rawData'!A:A,'Data Analytics rawData'!B:B)} -> 2650 | I39: {=XLOOKUP(B39,'Data Analytics rawData'!A:A,'Data Analytics rawData'!C:C)} -> 330 | J39: =E39/F39 -> 857.39146 | K39: Dabble Playart Finger Paints | L39: FP8 | M39: =F39/D39 -> 0.039627982
B40: Dabble Playart Finger Paints | C40: =IFERROR(VLOOKUP(B40,K:L,2,0),"NA") -> FP8 | D40: {=XLOOKUP(B40,'Google analytics'!A:A,'Google analytics'!F:F)} -> 814 | E40: =D40*$C$13 -> 27657.028 | F40: {=XLOOKUP(B40,'Data Analytics rawData'!A:A,'Data Analytics rawData'!D:D)} -> 60 | G40: {=XLOOKUP(B40,'Data Analytics rawData'!A:A,'Data Analytics rawData'!E:E)} -> 53295 | H40: {=XLOOKUP(B40,'Data Analytics rawData'!A:A,'Data Analytics rawData'!B:B)} -> 853 | I40: {=XLOOKUP(B40,'Data Analytics rawData'!A:A,'Data Analytics rawData'!C:C)} -> 200 | J40: =E40/F40 -> 460.95047 | K40: My First Dabble Swingin’ Jungle Adventure + Mini Starter Fun Pack + Chubby Brushes Combo | L40: SJ+SFP+CB | M40: =F40/D40 -> 0.073710074
B41: Imagination Spark Kit | Dabble Sensory Play Dough + Magic Paint Dust | C41: =IFERROR(VLOOKUP(B41,K:L,2,0),"NA") -> Playdough+MPD | D41: {=XLOOKUP(B41,'Google analytics'!A:A,'Google analytics'!F:F)} -> 345 | E41: =D41*$C$13 -> 11721.959 | F41: {=XLOOKUP(B41,'Data Analytics rawData'!A:A,'Data Analytics rawData'!D:D)} -> 11 | G41: {=XLOOKUP(B41,'Data Analytics rawData'!A:A,'Data Analytics rawData'!E:E)} -> 19004 | H41: {=XLOOKUP(B41,'Data Analytics rawData'!A:A,'Data Analytics rawData'!B:B)} -> 366 | I41: {=XLOOKUP(B41,'Data Analytics rawData'!A:A,'Data Analytics rawData'!C:C)} -> 33 | J41: =E41/F41 -> 1065.6327 | K41: Dabble Christmas Crayons | L41: CC8 | M41: =F41/D41 -> 0.031884058
B42: Dabble Magic Bubbles POP n PLAY | C42: =IFERROR(VLOOKUP(B42,K:L,2,0),"NA") -> Bubbles | D42: {=XLOOKUP(B42,'Google analytics'!A:A,'Google analytics'!F:F)} -> 1154 | E42: =D42*$C$13 -> 39209.104 | F42: {=XLOOKUP(B42,'Data Analytics rawData'!A:A,'Data Analytics rawData'!D:D)} -> 48 | G42: {=XLOOKUP(B42,'Data Analytics rawData'!A:A,'Data Analytics rawData'!E:E)} -> 20025.399 | H42: {=XLOOKUP(B42,'Data Analytics rawData'!A:A,'Data Analytics rawData'!B:B)} -> 1154 | I42: {=XLOOKUP(B42,'Data Analytics rawData'!A:A,'Data Analytics rawData'!C:C)} -> 63 | J42: =E42/F42 -> 816.85634 | K42: Imagination Spark Kit | Dabble Sensory Play Dough + Magic Paint Dust | L42: Playdough+MPD | M42: =F42/D42 -> 0.041594454
B43: Dabble Starter Pack | Chunkies + Finger Paints + Art Roll | C43: =IFERROR(VLOOKUP(B43,K:L,2,0),"NA") -> FP3+B3+AR | D43: {=XLOOKUP(B43,'Google analytics'!A:A,'Google analytics'!F:F)} -> 174 | E43: =D43*$C$13 -> 5911.9446 | F43: {=XLOOKUP(B43,'Data Analytics rawData'!A:A,'Data Analytics rawData'!D:D)} -> 7 | G43: {=XLOOKUP(B43,'Data Analytics rawData'!A:A,'Data Analytics rawData'!E:E)} -> 12785 | H43: {=XLOOKUP(B43,'Data Analytics rawData'!A:A,'Data Analytics rawData'!B:B)} -> 191 | I43: {=XLOOKUP(B43,'Data Analytics rawData'!A:A,'Data Analytics rawData'!C:C)} -> 28 | J43: =E43/F43 -> 844.56352 | K43: Dabble Starter Pack | Chunkies + Finger Paints + Art Roll | L43: FP3+B3+AR | M43: =F43/D43 -> 0.040229885
B44: Preschool Art and Craft Kit | C44: =IFERROR(VLOOKUP(B44,K:L,2,0),"NA") -> Preschool kit | D44: {=XLOOKUP(B44,'Google analytics'!A:A,'Google analytics'!F:F)} -> 965 | E44: =D44*$C$13 -> 32787.509 | F44: {=XLOOKUP(B44,'Data Analytics rawData'!A:A,'Data Analytics rawData'!D:D)} -> 61 | G44: {=XLOOKUP(B44,'Data Analytics rawData'!A:A,'Data Analytics rawData'!E:E)} -> 35911.001 | H44: {=XLOOKUP(B44,'Data Analytics rawData'!A:A,'Data Analytics rawData'!B:B)} -> 1004 | I44: {=XLOOKUP(B44,'Data Analytics rawData'!A:A,'Data Analytics rawData'!C:C)} -> 180 | J44: =E44/F44 -> 537.50015 | K44: Dabble Playart Crayons | L44: B8 | M44: =F44/D44 -> 0.063212435
B45: My First Dabble Swinginâ€™ Jungle Adventure + Mini Starter Fun Pack + Chubby Brushes Combo | C45: SJ+SFP+CB | D45: {=XLOOKUP(B45,'Google analytics'!A:A,'Google analytics'!F:F)} -> 419 | E45: =D45*$C$13 -> 14236.235 | F45: {=XLOOKUP(B45,'Data Analytics rawData'!A:A,'Data Analytics rawData'!D:D)} -> 21 | G45: {=XLOOKUP(B45,'Data Analytics rawData'!A:A,'Data Analytics rawData'!E:E)} -> 31366 | H45: {=XLOOKUP(B45,'Data Analytics rawData'!A:A,'Data Analytics rawData'!B:B)} -> 476 | I45: {=XLOOKUP(B45,'Data Analytics rawData'!A:A,'Data Analytics rawData'!C:C)} -> 74 | J45: =E45/F45 -> 677.91593 | K45: Dabble Sensory Rice Play Kit | L45: SR | M45: =F45/D45 -> 0.050119332
B46: Dabble Playart Crayons | C46: =IFERROR(VLOOKUP(B46,K:L,2,0),"NA") -> B8 | D46: {=XLOOKUP(B46,'Google analytics'!A:A,'Google analytics'!F:F)} -> 684 | E46: =D46*$C$13 -> 23240.058 | F46: {=XLOOKUP(B46,'Data Analytics rawData'!A:A,'Data Analytics rawData'!D:D)} -> 52 | G46: {=XLOOKUP(B46,'Data Analytics rawData'!A:A,'Data Analytics rawData'!E:E)} -> 23018 | H46: {=XLOOKUP(B46,'Data Analytics rawData'!A:A,'Data Analytics rawData'!B:B)} -> 671 | I46: {=XLOOKUP(B46,'Data Analytics rawData'!A:A,'Data Analytics rawData'!C:C)} -> 173 | J46: =E46/F46 -> 446.9242 | K46: My First Shape Explorer Stamp Kit | L46: Stamp kit | M46: =F46/D46 -> 0.076023392
B47: Dabble Sensory Rice Play Kit | C47: =IFERROR(VLOOKUP(B47,K:L,2,0),"NA") -> SR | D47: {=XLOOKUP(B47,'Google analytics'!A:A,'Google analytics'!F:F)} -> 1065 | E47: =D47*$C$13 -> 36185.178 | F47: {=XLOOKUP(B47,'Data Analytics rawData'!A:A,'Data Analytics rawData'!D:D)} -> 28 | G47: {=XLOOKUP(B47,'Data Analytics rawData'!A:A,'Data Analytics rawData'!E:E)} -> 19372 | H47: {=XLOOKUP(B47,'Data Analytics rawData'!A:A,'Data Analytics rawData'!B:B)} -> 1102 | I47: {=XLOOKUP(B47,'Data Analytics rawData'!A:A,'Data Analytics rawData'!C:C)} -> 93 | J47: =E47/F47 -> 1292.3278 | K47: Dabble Starter Finger Painting Fun Pack + Apron ComboKit | L47: SFP+Apron | M47: =F47/D47 -> 0.02629108
B48: My First Shape Explorer Stamp Kit | C48: =IFERROR(VLOOKUP(B48,K:L,2,0),"NA") -> Stamp kit | D48: {=XLOOKUP(B48,'Google analytics'!A:A,'Google analytics'!F:F)} -> 399 | E48: =D48*$C$13 -> 13556.701 | F48: {=XLOOKUP(B48,'Data Analytics rawData'!A:A,'Data Analytics rawData'!D:D)} -> 37 | G48: {=XLOOKUP(B48,'Data Analytics rawData'!A:A,'Data Analytics rawData'!E:E)} -> 36963 | H48: {=XLOOKUP(B48,'Data Analytics rawData'!A:A,'Data Analytics rawData'!B:B)} -> 415 | I48: {=XLOOKUP(B48,'Data Analytics rawData'!A:A,'Data Analytics rawData'!C:C)} -> 91 | J48: =E48/F48 -> 366.39731 | K48: Dabble Magic Bubbles POP n PLAY | L48: Bubbles | M48: =F48/D48 -> 0.09273183
B49: Sensory Discovery Kit | Dabble Sensory Rice + Sensory Play Dough | C49: =IFERROR(VLOOKUP(B49,K:L,2,0),"NA") -> SR+Playdough | D49: {=XLOOKUP(B49,'Google analytics'!A:A,'Google analytics'!F:F)} -> 485 | E49: =D49*$C$13 -> 16478.696 | F49: {=XLOOKUP(B49,'Data Analytics rawData'!A:A,'Data Analytics rawData'!D:D)} -> 20 | G49: {=XLOOKUP(B49,'Data Analytics rawData'!A:A,'Data Analytics rawData'!E:E)} -> 30792 | H49: {=XLOOKUP(B49,'Data Analytics rawData'!A:A,'Data Analytics rawData'!B:B)} -> 532 | I49: {=XLOOKUP(B49,'Data Analytics rawData'!A:A,'Data Analytics rawData'!C:C)} -> 48 | J49: =E49/F49 -> 823.93481 | K49: Dabble Baby's First Big Colouring Pages | L49: DP | M49: =F49/D49 -> 0.041237113
B50: Toddler's First Painting Set | Finger Paints + Jumbo Brushes | C50: =IFERROR(VLOOKUP(B50,K:L,2,0),"NA") -> FP3+JB | D50: {=XLOOKUP(B50,'Google analytics'!A:A,'Google analytics'!F:F)} -> 305 | E50: =D50*$C$13 -> 10362.891 | F50: {=XLOOKUP(B50,'Data Analytics rawData'!A:A,'Data Analytics rawData'!D:D)} -> 12 | G50: {=XLOOKUP(B50,'Data Analytics rawData'!A:A,'Data Analytics rawData'!E:E)} -> 13325 | H50: {=XLOOKUP(B50,'Data Analytics rawData'!A:A,'Data Analytics rawData'!B:B)} -> 321 | I50: {=XLOOKUP(B50,'Data Analytics rawData'!A:A,'Data Analytics rawData'!C:C)} -> 38 | J50: =E50/F50 -> 863.57429 | K50: Sensory Discovery Kit | Dabble Sensory Rice + Sensory Play Dough | L50: SR+Playdough | M50: =F50/D50 -> 0.039344262
B51: Dabble DIY Sensory Playdough Kit | C51: Mini SPD | D51: {=XLOOKUP(B51,'Google analytics'!A:A,'Google analytics'!F:F)} -> 1015 | E51: =D51*$C$13 -> 34486.344 | F51: {=XLOOKUP(B51,'Data Analytics rawData'!A:A,'Data Analytics rawData'!D:D)} -> 34 | G51: {=XLOOKUP(B51,'Data Analytics rawData'!A:A,'Data Analytics rawData'!E:E)} -> 18643 | H51: {=XLOOKUP(B51,'Data Analytics rawData'!A:A,'Data Analytics rawData'!B:B)} -> 1123 | I51: {=XLOOKUP(B51,'Data Analytics rawData'!A:A,'Data Analytics rawData'!C:C)} -> 130 | J51: =E51/F51 -> 1014.3042 | K51: Preschool Art and Craft Kit | L51: Preschool kit | M51: =F51/D51 -> 0.033497537
B52: Endless Creations Pack | Dabble Reusable Colouring Pages + Sensory Play Dough | C52: =IFERROR(VLOOKUP(B52,K:L,2,0),"NA") -> DP+Playdough | D52: {=XLOOKUP(B52,'Google analytics'!A:A,'Google analytics'!F:F)} -> 233 | E52: =D52*$C$13 -> 7916.5695 | F52: {=XLOOKUP(B52,'Data Analytics rawData'!A:A,'Data Analytics rawData'!D:D)} -> 6 | G52: {=XLOOKUP(B52,'Data Analytics rawData'!A:A,'Data Analytics rawData'!E:E)} -> 7476 | H52: {=XLOOKUP(B52,'Data Analytics rawData'!A:A,'Data Analytics rawData'!B:B)} -> 253 | I52: {=XLOOKUP(B52,'Data Analytics rawData'!A:A,'Data Analytics rawData'!C:C)} -> 17 | J52: =E52/F52 -> 1319.4283 | K52: Dabble Reusable Colouring Pages + Crayons Combo Kit | L52: DP+B8 | M52: =F52/D52 -> 0.025751073
B53: Little Makerâ€™s Set | Dabble Sensory Play Dough + Painting Apron | C53: Playdough+AR | D53: {=XLOOKUP(B53,'Google analytics'!A:A,'Google analytics'!F:F)} -> 485 | E53: =D53*$C$13 -> 16478.696 | F53: {=XLOOKUP(B53,'Data Analytics rawData'!A:A,'Data Analytics rawData'!D:D)} -> 11 | G53: {=XLOOKUP(B53,'Data Analytics rawData'!A:A,'Data Analytics rawData'!E:E)} -> 17315 | H53: {=XLOOKUP(B53,'Data Analytics rawData'!A:A,'Data Analytics rawData'!B:B)} -> 519 | I53: {=XLOOKUP(B53,'Data Analytics rawData'!A:A,'Data Analytics rawData'!C:C)} -> 61 | J53: =E53/F53 -> 1498.0633 | K53: My First Dabble Swingin’ Jungle Adventure | Reusable Story Card Set | L53: SJ | M53: =F53/D53 -> 0.022680412
B54: Toddlers First Colouring Set | Playart Crayons + Art Roll | C54: =IFERROR(VLOOKUP(B54,K:L,2,0),"NA") -> B8+AR | D54: {=XLOOKUP(B54,'Google analytics'!A:A,'Google analytics'!F:F)} -> 151 | E54: =D54*$C$13 -> 5130.4807 | F54: {=XLOOKUP(B54,'Data Analytics rawData'!A:A,'Data Analytics rawData'!D:D)} -> 7 | G54: {=XLOOKUP(B54,'Data Analytics rawData'!A:A,'Data Analytics rawData'!E:E)} -> 7279.0001 | H54: {=XLOOKUP(B54,'Data Analytics rawData'!A:A,'Data Analytics rawData'!B:B)} -> 159 | I54: {=XLOOKUP(B54,'Data Analytics rawData'!A:A,'Data Analytics rawData'!C:C)} -> 20 | J54: =E54/F54 -> 732.92581 | K54: Dabble Painting set | Finger Paints + Chubby Brushes | L54: FP3+CB | M54: =F54/D54 -> 0.046357616
B55: Dabble Jumbo Paint Brush Set | C55: =IFERROR(VLOOKUP(B55,K:L,2,0),"NA") -> JB | D55: {=XLOOKUP(B55,'Google analytics'!A:A,'Google analytics'!F:F)} -> 652 | E55: =D55*$C$13 -> 22152.804 | F55: {=XLOOKUP(B55,'Data Analytics rawData'!A:A,'Data Analytics rawData'!D:D)} -> 31 | G55: {=XLOOKUP(B55,'Data Analytics rawData'!A:A,'Data Analytics rawData'!E:E)} -> 14469 | H55: {=XLOOKUP(B55,'Data Analytics rawData'!A:A,'Data Analytics rawData'!B:B)} -> 636 | I55: {=XLOOKUP(B55,'Data Analytics rawData'!A:A,'Data Analytics rawData'!C:C)} -> 106 | J55: =E55/F55 -> 714.60658 | K55: Baby’s first Diwali handprint and footprint kit | L55: Canvas kit | M55: =F55/D55 -> 0.047546012
B56: Dabble Dessert Party Pretend Playdough Set | C56: Mini Dessert Party | D56: {=XLOOKUP(B56,'Google analytics'!A:A,'Google analytics'!F:F)} -> 1113 | E56: =D56*$C$13 -> 37816.06 | F56: {=XLOOKUP(B56,'Data Analytics rawData'!A:A,'Data Analytics rawData'!D:D)} -> 22 | G56: {=XLOOKUP(B56,'Data Analytics rawData'!A:A,'Data Analytics rawData'!E:E)} -> 12172 | H56: {=XLOOKUP(B56,'Data Analytics rawData'!A:A,'Data Analytics rawData'!B:B)} -> 1196 | I56: {=XLOOKUP(B56,'Data Analytics rawData'!A:A,'Data Analytics rawData'!C:C)} -> 74 | J56: =E56/F56 -> 1718.9118 | K56: Dabble Jumbo Paint Brush Set | L56: JB | M56: =F56/D56 -> 0.019766397
B57: Dabble Gift Pack | Chunkies + Finger Paints | C57: =IFERROR(VLOOKUP(B57,K:L,2,0),"NA") -> FP3+B3 | D57: {=XLOOKUP(B57,'Google analytics'!A:A,'Google analytics'!F:F)} -> 170 | E57: =D57*$C$13 -> 5776.0379 | F57: {=XLOOKUP(B57,'Data Analytics rawData'!A:A,'Data Analytics rawData'!D:D)} -> 7 | G57: {=XLOOKUP(B57,'Data Analytics rawData'!A:A,'Data Analytics rawData'!E:E)} -> 8038 | H57: {=XLOOKUP(B57,'Data Analytics rawData'!A:A,'Data Analytics rawData'!B:B)} -> 184 | I57: {=XLOOKUP(B57,'Data Analytics rawData'!A:A,'Data Analytics rawData'!C:C)} -> 39 | J57: =E57/F57 -> 825.14827 | K57: Creative Wonder Set | Dabble Play Art Chunkies + Sensory Play Dough | L57: B3+Playdough | M57: =F57/D57 -> 0.041176471
B58: Creative Wonder Set | Dabble Play Art Chunkies + Sensory Play Dough | C58: =IFERROR(VLOOKUP(B58,K:L,2,0),"NA") -> B3+Playdough | D58: {=XLOOKUP(B58,'Google analytics'!A:A,'Google analytics'!F:F)} -> 295 | E58: =D58*$C$13 -> 10023.125 | F58: {=XLOOKUP(B58,'Data Analytics rawData'!A:A,'Data Analytics rawData'!D:D)} -> 10 | G58: {=XLOOKUP(B58,'Data Analytics rawData'!A:A,'Data Analytics rawData'!E:E)} -> 13926 | H58: {=XLOOKUP(B58,'Data Analytics rawData'!A:A,'Data Analytics rawData'!B:B)} -> 325 | I58: {=XLOOKUP(B58,'Data Analytics rawData'!A:A,'Data Analytics rawData'!C:C)} -> 31 | J58: =E58/F58 -> 1002.3125 | K58: Magic Paint Dust + Jumbo Brush Combo Kit + PlayArt Roll – Baby’s First Painting Kit | L58: MPD+AR+JB | M58: =F58/D58 -> 0.033898305
B59: Dabble Canvas Art Board | C59: =IFERROR(VLOOKUP(B59,K:L,2,0),"NA") -> Canvas | D59: {=XLOOKUP(B59,'Google analytics'!A:A,'Google analytics'!F:F)} -> 199 | E59: =D59*$C$13 -> 6761.362 | F59: {=XLOOKUP(B59,'Data Analytics rawData'!A:A,'Data Analytics rawData'!D:D)} -> 35 | G59: {=XLOOKUP(B59,'Data Analytics rawData'!A:A,'Data Analytics rawData'!E:E)} -> 6080.0002 | H59: {=XLOOKUP(B59,'Data Analytics rawData'!A:A,'Data Analytics rawData'!B:B)} -> 161 | I59: {=XLOOKUP(B59,'Data Analytics rawData'!A:A,'Data Analytics rawData'!C:C)} -> 53 | J59: =E59/F59 -> 193.18177 | K59: Toddler's First Painting Set | Finger Paints + Jumbo Brushes | L59: FP3+JB | M59: =F59/D59 -> 0.1758794
B60: Magic Paint Dust + Jumbo Brush Combo Kit + PlayArt Roll â€“ Babyâ€™s First Painting Kit | C60: MPD+AR+JB | D60: {=XLOOKUP(B60,'Google analytics'!A:A,'Google analytics'!F:F)} -> 319 | E60: =D60*$C$13 -> 10838.565 | F60: {=XLOOKUP(B60,'Data Analytics rawData'!A:A,'Data Analytics rawData'!D:D)} -> 1 | G60: {=XLOOKUP(B60,'Data Analytics rawData'!A:A,'Data Analytics rawData'!E:E)} -> 1992 | H60: {=XLOOKUP(B60,'Data Analytics rawData'!A:A,'Data Analytics rawData'!B:B)} -> 356 | I60: {=XLOOKUP(B60,'Data Analytics rawData'!A:A,'Data Analytics rawData'!C:C)} -> 13 | J60: =E60/F60 -> 10838.565 | K60: Dabble Finger Painting Super Pack | L60: FP8+CB+Apron | M60: =F60/D60 -> 0.0031347962
B61: Dabble Baby's First Big Colouring Pages | C61: =IFERROR(VLOOKUP(B61,K:L,2,0),"NA") -> DP | D61: {=XLOOKUP(B61,'Google analytics'!A:A,'Google analytics'!F:F)} -> 592 | E61: =D61*$C$13 -> 20114.202 | F61: {=XLOOKUP(B61,'Data Analytics rawData'!A:A,'Data Analytics rawData'!D:D)} -> 37 | G61: {=XLOOKUP(B61,'Data Analytics rawData'!A:A,'Data Analytics rawData'!E:E)} -> 32903 | H61: {=XLOOKUP(B61,'Data Analytics rawData'!A:A,'Data Analytics rawData'!B:B)} -> 654 | I61: {=XLOOKUP(B61,'Data Analytics rawData'!A:A,'Data Analytics rawData'!C:C)} -> 123 | J61: =E61/F61 -> 543.62709 | K61: Dabble Canvas Art Board | L61: Canvas | M61: =F61/D61 -> 0.0625
B62: My First Dabble Swinginâ€™ Jungle Adventure | Reusable Story Card Set | C62: SJ | D62: {=XLOOKUP(B62,'Google analytics'!A:A,'Google analytics'!F:F)} -> 593 | E62: =D62*$C$13 -> 20148.179 | F62: {=XLOOKUP(B62,'Data Analytics rawData'!A:A,'Data Analytics rawData'!D:D)} -> 21 | G62: {=XLOOKUP(B62,'Data Analytics rawData'!A:A,'Data Analytics rawData'!E:E)} -> 10479 | H62: {=XLOOKUP(B62,'Data Analytics rawData'!A:A,'Data Analytics rawData'!B:B)} -> 641 | I62: {=XLOOKUP(B62,'Data Analytics rawData'!A:A,'Data Analytics rawData'!C:C)} -> 94 | J62: =E62/F62 -> 959.4371 | K62: Baby’s first handprint and footprint kit | L62: Canvas kit | M62: =F62/D62 -> 0.035413153
B63: Dabble Reusable Colouring Pages + Crayons Combo Kit | C63: =IFERROR(VLOOKUP(B63,K:L,2,0),"NA") -> DP+B8 | D63: {=XLOOKUP(B63,'Google analytics'!A:A,'Google analytics'!F:F)} -> 200 | E63: =D63*$C$13 -> 6795.3387 | F63: {=XLOOKUP(B63,'Data Analytics rawData'!A:A,'Data Analytics rawData'!D:D)} -> 9 | G63: {=XLOOKUP(B63,'Data Analytics rawData'!A:A,'Data Analytics rawData'!E:E)} -> 7341 | H63: {=XLOOKUP(B63,'Data Analytics rawData'!A:A,'Data Analytics rawData'!B:B)} -> 228 | I63: {=XLOOKUP(B63,'Data Analytics rawData'!A:A,'Data Analytics rawData'!C:C)} -> 30 | J63: =E63/F63 -> 755.03763 | K63: Little Maker’s Set | Dabble Sensory Play Dough + Painting Apron | L63: Playdough+AR | M63: =F63/D63 -> 0.045
B64: Multi Sensory Painting Set | C64: =IFERROR(VLOOKUP(B64,K:L,2,0),"NA") -> FP3+AR | D64: {=XLOOKUP(B64,'Google analytics'!A:A,'Google analytics'!F:F)} -> 88 | E64: =D64*$C$13 -> 2989.949 | F64: {=XLOOKUP(B64,'Data Analytics rawData'!A:A,'Data Analytics rawData'!D:D)} -> 2 | G64: {=XLOOKUP(B64,'Data Analytics rawData'!A:A,'Data Analytics rawData'!E:E)} -> 2605 | H64: {=XLOOKUP(B64,'Data Analytics rawData'!A:A,'Data Analytics rawData'!B:B)} -> 88 | I64: {=XLOOKUP(B64,'Data Analytics rawData'!A:A,'Data Analytics rawData'!C:C)} -> 17 | J64: =E64/F64 -> 1494.9745 | K64: Endless Creations Pack | Dabble Reusable Colouring Pages + Sensory Play Dough | L64: DP+Playdough | M64: =F64/D64 -> 0.022727273
B65: Dabble Chubby Brushes | C65: =IFERROR(VLOOKUP(B65,K:L,2,0),"NA") -> CB | D65: {=XLOOKUP(B65,'Google analytics'!A:A,'Google analytics'!F:F)} -> 302 | E65: =D65*$C$13 -> 10260.961 | F65: {=XLOOKUP(B65,'Data Analytics rawData'!A:A,'Data Analytics rawData'!D:D)} -> 16 | G65: {=XLOOKUP(B65,'Data Analytics rawData'!A:A,'Data Analytics rawData'!E:E)} -> 7984 | H65: {=XLOOKUP(B65,'Data Analytics rawData'!A:A,'Data Analytics rawData'!B:B)} -> 272 | I65: {=XLOOKUP(B65,'Data Analytics rawData'!A:A,'Data Analytics rawData'!C:C)} -> 78 | J65: =E65/F65 -> 641.31009 | K65: Toddlers First Colouring Set | Playart Crayons + Art Roll | L65: B8+AR | M65: =F65/D65 -> 0.052980132
B66: Dabble Reusable Colouring Pages + Mini Finger Paints Combo Kit | C66: =IFERROR(VLOOKUP(B66,K:L,2,0),"NA") -> DP+SFP | D66: {=XLOOKUP(B66,'Google analytics'!A:A,'Google analytics'!F:F)} -> 110 | E66: =D66*$C$13 -> 3737.4363 | F66: {=XLOOKUP(B66,'Data Analytics rawData'!A:A,'Data Analytics rawData'!D:D)} -> 4 | G66: {=XLOOKUP(B66,'Data Analytics rawData'!A:A,'Data Analytics rawData'!E:E)} -> 3823 | H66: {=XLOOKUP(B66,'Data Analytics rawData'!A:A,'Data Analytics rawData'!B:B)} -> 123 | I66: {=XLOOKUP(B66,'Data Analytics rawData'!A:A,'Data Analytics rawData'!C:C)} -> 22 | J66: =E66/F66 -> 934.35907 | K66: Palette & Brush | L66: P&B | M66: =F66/D66 -> 0.036363636
B67: Dabble Magic Dough Lab â€” Colour Mixing STEAM Kit | C67: Magic Dough | D67: {=XLOOKUP(B67,'Google analytics'!A:A,'Google analytics'!F:F)} -> 560 | E67: =D67*$C$13 -> 19026.948 | F67: {=XLOOKUP(B67,'Data Analytics rawData'!A:A,'Data Analytics rawData'!D:D)} -> 10 | G67: {=XLOOKUP(B67,'Data Analytics rawData'!A:A,'Data Analytics rawData'!E:E)} -> 5519.9999 | H67: {=XLOOKUP(B67,'Data Analytics rawData'!A:A,'Data Analytics rawData'!B:B)} -> 571 | I67: {=XLOOKUP(B67,'Data Analytics rawData'!A:A,'Data Analytics rawData'!C:C)} -> 67 | J67: =E67/F67 -> 1902.6948 | K67: Dabble Gift Pack | Chunkies + Finger Paints | L67: FP3+B3 | M67: =F67/D67 -> 0.017857143
B68: My First Dabble Puzzle Colouring Set - Emotions, Shapes & Colours | C68: =IFERROR(VLOOKUP(B68,K:L,2,0),"NA") -> Puzzle Kit | D68: {=XLOOKUP(B68,'Google analytics'!A:A,'Google analytics'!F:F)} -> 351 | E68: =D68*$C$13 -> 11925.819 | F68: {=XLOOKUP(B68,'Data Analytics rawData'!A:A,'Data Analytics rawData'!D:D)} -> 7 | G68: {=XLOOKUP(B68,'Data Analytics rawData'!A:A,'Data Analytics rawData'!E:E)} -> 6433.0001 | H68: {=XLOOKUP(B68,'Data Analytics rawData'!A:A,'Data Analytics rawData'!B:B)} -> 368 | I68: {=XLOOKUP(B68,'Data Analytics rawData'!A:A,'Data Analytics rawData'!C:C)} -> 12 | J68: =E68/F68 -> 1703.6885 | K68: All In One Paint Kit | L68: A1 Kit | M68: =F68/D68 -> 0.01994302
B69: Dabble DINOSAUR STENCIL ART & CRAFT Kit | C69: =IFERROR(VLOOKUP(B69,K:L,2,0),"NA") -> Dino Kit | D69: {=XLOOKUP(B69,'Google analytics'!A:A,'Google analytics'!F:F)} -> 843 | E69: =D69*$C$13 -> 28642.352 | F69: {=XLOOKUP(B69,'Data Analytics rawData'!A:A,'Data Analytics rawData'!D:D)} -> 16 | G69: {=XLOOKUP(B69,'Data Analytics rawData'!A:A,'Data Analytics rawData'!E:E)} -> 10552 | H69: {=XLOOKUP(B69,'Data Analytics rawData'!A:A,'Data Analytics rawData'!B:B)} -> 897 | I69: {=XLOOKUP(B69,'Data Analytics rawData'!A:A,'Data Analytics rawData'!C:C)} -> 38 | J69: =E69/F69 -> 1790.147 | K69: Dabble UNICORN STENCIL ART & CRAFT Kit | L69: Unicorn Kit | M69: =F69/D69 -> 0.018979834
B70: All In One Paint Kit | C70: =IFERROR(VLOOKUP(B70,K:L,2,0),"NA") -> A1 Kit | D70: {=XLOOKUP(B70,'Google analytics'!A:A,'Google analytics'!F:F)} -> 313 | E70: =D70*$C$13 -> 10634.705 | F70: {=XLOOKUP(B70,'Data Analytics rawData'!A:A,'Data Analytics rawData'!D:D)} -> 18 | G70: {=XLOOKUP(B70,'Data Analytics rawData'!A:A,'Data Analytics rawData'!E:E)} -> 8620.0002 | H70: {=XLOOKUP(B70,'Data Analytics rawData'!A:A,'Data Analytics rawData'!B:B)} -> 309 | I70: {=XLOOKUP(B70,'Data Analytics rawData'!A:A,'Data Analytics rawData'!C:C)} -> 69 | J70: =E70/F70 -> 590.81695 | K70: My First Dabble Puzzle Colouring Set - Emotions, Shapes & Colours | L70: Puzzle Kit | M70: =F70/D70 -> 0.057507987
B71: Dabble Finger Painting Super Pack | C71: =IFERROR(VLOOKUP(B71,K:L,2,0),"NA") -> FP8+CB+Apron | D71: {=XLOOKUP(B71,'Google analytics'!A:A,'Google analytics'!F:F)} -> 100 | E71: =D71*$C$13 -> 3397.6693 | F71: {=XLOOKUP(B71,'Data Analytics rawData'!A:A,'Data Analytics rawData'!D:D)} -> 1 | G71: {=XLOOKUP(B71,'Data Analytics rawData'!A:A,'Data Analytics rawData'!E:E)} -> 2104 | H71: {=XLOOKUP(B71,'Data Analytics rawData'!A:A,'Data Analytics rawData'!B:B)} -> 107 | I71: {=XLOOKUP(B71,'Data Analytics rawData'!A:A,'Data Analytics rawData'!C:C)} -> 9 | J71: =E71/F71 -> 3397.6693 | K71: Dabble Chubby Brushes | L71: CB | M71: =F71/D71 -> 0.01
B72: Dabble UNICORN STENCIL ART & CRAFT Kit | C72: =IFERROR(VLOOKUP(B72,K:L,2,0),"NA") -> Unicorn Kit | D72: {=XLOOKUP(B72,'Google analytics'!A:A,'Google analytics'!F:F)} -> 341 | E72: =D72*$C$13 -> 11586.052 | F72: {=XLOOKUP(B72,'Data Analytics rawData'!A:A,'Data Analytics rawData'!D:D)} -> 9 | G72: {=XLOOKUP(B72,'Data Analytics rawData'!A:A,'Data Analytics rawData'!E:E)} -> 6462.0001 | H72: {=XLOOKUP(B72,'Data Analytics rawData'!A:A,'Data Analytics rawData'!B:B)} -> 349 | I72: {=XLOOKUP(B72,'Data Analytics rawData'!A:A,'Data Analytics rawData'!C:C)} -> 22 | J72: =E72/F72 -> 1287.3392 | K72: Dabble DINOSAUR STENCIL ART & CRAFT Kit | L72: Dino Kit | M72: =F72/D72 -> 0.026392962
B73: All In One Paint Kit + Playart Crayons Combo | C73: =IFERROR(VLOOKUP(B73,K:L,2,0),"NA") -> A1 Kit+B8 | D73: {=XLOOKUP(B73,'Google analytics'!A:A,'Google analytics'!F:F)} -> 178 | E73: =D73*$C$13 -> 6047.8514 | F73: {=XLOOKUP(B73,'Data Analytics rawData'!A:A,'Data Analytics rawData'!D:D)} -> 2 | G73: {=XLOOKUP(B73,'Data Analytics rawData'!A:A,'Data Analytics rawData'!E:E)} -> 1994 | H73: {=XLOOKUP(B73,'Data Analytics rawData'!A:A,'Data Analytics rawData'!B:B)} -> 198 | I73: {=XLOOKUP(B73,'Data Analytics rawData'!A:A,'Data Analytics rawData'!C:C)} -> 18 | J73: =E73/F73 -> 3023.9257 | K73: Dabble Chunky Glue | L73: Glue | M73: =F73/D73 -> 0.011235955
B74: My dabble India Map Art | India maps for kids learning | C74: =IFERROR(VLOOKUP(B74,K:L,2,0),"NA") -> India Map Kit | D74: {=XLOOKUP(B74,'Google analytics'!A:A,'Google analytics'!F:F)} -> 131 | E74: =D74*$C$13 -> 4450.9468 | F74: {=XLOOKUP(B74,'Data Analytics rawData'!A:A,'Data Analytics rawData'!D:D)} -> 4 | G74: {=XLOOKUP(B74,'Data Analytics rawData'!A:A,'Data Analytics rawData'!E:E)} -> 4280 | H74: {=XLOOKUP(B74,'Data Analytics rawData'!A:A,'Data Analytics rawData'!B:B)} -> 140 | I74: {=XLOOKUP(B74,'Data Analytics rawData'!A:A,'Data Analytics rawData'!C:C)} -> 11 | J74: =E74/F74 -> 1112.7367 | K74: Dabble POP n PLAY | POP n PLAY Magic Bubbles | L74: Bubbles | M74: =F74/D74 -> 0.030534351
B75: Dabble Starter Finger Painting Fun Pack + Apron ComboKit | C75: =IFERROR(VLOOKUP(B75,K:L,2,0),"NA") -> SFP+Apron | D75: {=XLOOKUP(B75,'Google analytics'!A:A,'Google analytics'!F:F)} -> 179 | E75: =D75*$C$13 -> 6081.8281 | F75: {=XLOOKUP(B75,'Data Analytics rawData'!A:A,'Data Analytics rawData'!D:D)} -> 14 | G75: {=XLOOKUP(B75,'Data Analytics rawData'!A:A,'Data Analytics rawData'!E:E)} -> 18726 | H75: {=XLOOKUP(B75,'Data Analytics rawData'!A:A,'Data Analytics rawData'!B:B)} -> 180 | I75: {=XLOOKUP(B75,'Data Analytics rawData'!A:A,'Data Analytics rawData'!C:C)} -> 40 | J75: =E75/F75 -> 434.41629 | K75: My First Dabble Swingin’ Jungle Adventure + Mini Starter Fun Pack Combo | L75: SJ+SFP | M75: =F75/D75 -> 0.078212291
B76: Dabble Finger Paints + Canvas Art Board | C76: =IFERROR(VLOOKUP(B76,K:L,2,0),"NA") -> FP8+Canvs | D76: {=XLOOKUP(B76,'Google analytics'!A:A,'Google analytics'!F:F)} -> 122 | E76: =D76*$C$13 -> 4145.1566 | F76: {=XLOOKUP(B76,'Data Analytics rawData'!A:A,'Data Analytics rawData'!D:D)} -> 4 | G76: {=XLOOKUP(B76,'Data Analytics rawData'!A:A,'Data Analytics rawData'!E:E)} -> 4202 | H76: {=XLOOKUP(B76,'Data Analytics rawData'!A:A,'Data Analytics rawData'!B:B)} -> 131 | I76: {=XLOOKUP(B76,'Data Analytics rawData'!A:A,'Data Analytics rawData'!C:C)} -> 26 | J76: =E76/F76 -> 1036.2891 | K76: Multi Sensory Painting Set | L76: FP3+AR | M76: =F76/D76 -> 0.032786885
B77: Dabble Playtime Prep Kit | C77: =IFERROR(VLOOKUP(B77,K:L,2,0),"NA") -> SFP+CB+Canvas | D77: {=XLOOKUP(B77,'Google analytics'!A:A,'Google analytics'!F:F)} -> 103 | E77: =D77*$C$13 -> 3499.5994 | F77: {=XLOOKUP(B77,'Data Analytics rawData'!A:A,'Data Analytics rawData'!D:D)} -> 4 | G77: {=XLOOKUP(B77,'Data Analytics rawData'!A:A,'Data Analytics rawData'!E:E)} -> 4778 | H77: {=XLOOKUP(B77,'Data Analytics rawData'!A:A,'Data Analytics rawData'!B:B)} -> 123 | I77: {=XLOOKUP(B77,'Data Analytics rawData'!A:A,'Data Analytics rawData'!C:C)} -> 16 | J77: =E77/F77 -> 874.89985 | K77: Baby's Handprint And Footprint | L77: Canvas kit | M77: =F77/D77 -> 0.038834951
B78: A-Z Alphabet Printable Activity Pack | C78: =IFERROR(VLOOKUP(B78,K:L,2,0),"NA") -> Activity Pack | D78: {=XLOOKUP(B78,'Google analytics'!A:A,'Google analytics'!F:F)} -> 1448 | E78: =D78*$C$13 -> 49198.252 | F78: {=XLOOKUP(B78,'Data Analytics rawData'!A:A,'Data Analytics rawData'!D:D)} -> 40 | G78: {=XLOOKUP(B78,'Data Analytics rawData'!A:A,'Data Analytics rawData'!E:E)} -> 3960.0001 | H78: {=XLOOKUP(B78,'Data Analytics rawData'!A:A,'Data Analytics rawData'!B:B)} -> 1518 | I78: {=XLOOKUP(B78,'Data Analytics rawData'!A:A,'Data Analytics rawData'!C:C)} -> 247 | J78: =E78/F78 -> 1229.9563 | K78: Dabble Sensory Touch & Feel Reusable Colouring Pages for Toddlers | L78: T&F | M78: =F78/D78 -> 0.027624309
B79: Dabble Chunky Glue | C79: =IFERROR(VLOOKUP(B79,K:L,2,0),"NA") -> Glue | D79: {=XLOOKUP(B79,'Google analytics'!A:A,'Google analytics'!F:F)} -> 215 | E79: =D79*$C$13 -> 7304.9891 | F79: {=XLOOKUP(B79,'Data Analytics rawData'!A:A,'Data Analytics rawData'!D:D)} -> 25 | G79: {=XLOOKUP(B79,'Data Analytics rawData'!A:A,'Data Analytics rawData'!E:E)} -> 8725.0001 | H79: {=XLOOKUP(B79,'Data Analytics rawData'!A:A,'Data Analytics rawData'!B:B)} -> 190 | I79: {=XLOOKUP(B79,'Data Analytics rawData'!A:A,'Data Analytics rawData'!C:C)} -> 66 | J79: =E79/F79 -> 292.19956 | K79: Dabble Gift Set | Crayons + Finger Paints | L79: FP3+B8 | M79: =F79/D79 -> 0.11627907
... B84: My First Dabble Art Set For Toddlers | C84: =IFERROR(VLOOKUP(B84,K:L,2,0),"NA") -> FP3+Glue+AR+B3 | D84: {=XLOOKUP(B84,'Google analytics'!A:A,'Google analytics'!F:F)} -> 105 | E84: =D84*$C$13 -> 3567.5528 | F84: {=XLOOKUP(B84,'Data Analytics rawData'!A:A,'Data Analytics rawData'!D:D)} -> 0 | G84: {=XLOOKUP(B84,'Data Analytics rawData'!A:A,'Data Analytics rawData'!E:E)} -> 0 | H84: {=XLOOKUP(B84,'Data Analytics rawData'!A:A,'Data Analytics rawData'!B:B)} -> 111 | I84: {=XLOOKUP(B84,'Data Analytics rawData'!A:A,'Data Analytics rawData'!C:C)} -> 8 | J84: =E84/F84 -> #DIV/0! | K84: My First Dabble Art Set For Toddlers | L84: FP3+Glue+AR+B3 | M84: =F84/D84 -> 0
B85: Dabble Christmas Crayons + Dabble Pages | C85: =IFERROR(VLOOKUP(B85,K:L,2,0),"NA") -> CC8+DP | D85: NA | E85: =D85*$C$13 -> #VALUE! | F85: NA | G85: {=XLOOKUP(B85,'Data Analytics rawData'!A:A,'Data Analytics rawData'!E:E)} -> #N/A | H85: {=XLOOKUP(B85,'Data Analytics rawData'!A:A,'Data Analytics rawData'!B:B)} -> #N/A | I85: {=XLOOKUP(B85,'Data Analytics rawData'!A:A,'Data Analytics rawData'!C:C)} -> #N/A | J85: =E85/F85 -> #VALUE! | K85: Dabble Christmas Crayons + Dabble Pages | L85: CC8+DP | M85: =F85/D85 -> #VALUE!
B86: Dabble Sensory Painting Kit | C86: =IFERROR(VLOOKUP(B86,K:L,2,0),"NA") -> SFP+AR+Apron | D86: {=XLOOKUP(B86,'Google analytics'!A:A,'Google analytics'!F:F)} -> 87 | E86: =D86*$C$13 -> 2955.9723 | F86: {=XLOOKUP(B86,'Data Analytics rawData'!A:A,'Data Analytics rawData'!D:D)} -> 1 | G86: {=XLOOKUP(B86,'Data Analytics rawData'!A:A,'Data Analytics rawData'!E:E)} -> 1712 | H86: {=XLOOKUP(B86,'Data Analytics rawData'!A:A,'Data Analytics rawData'!B:B)} -> 96 | I86: {=XLOOKUP(B86,'Data Analytics rawData'!A:A,'Data Analytics rawData'!C:C)} -> 7 | J86: =E86/F86 -> 2955.9723 | K86: Dabble Reusable Colouring Pages + Mini Finger Paints Combo Kit | L86: DP+SFP | M86: =F86/D86 -> 0.011494253
B87: Dabble 3 In 1 Easy-Clean Fun Pack | C87: =IFERROR(VLOOKUP(B87,K:L,2,0),"NA") -> Glue+FP3+B8 | D87: {=XLOOKUP(B87,'Google analytics'!A:A,'Google analytics'!F:F)} -> 98 | E87: =D87*$C$13 -> 3329.7159 | F87: {=XLOOKUP(B87,'Data Analytics rawData'!A:A,'Data Analytics rawData'!D:D)} -> 1 | G87: {=XLOOKUP(B87,'Data Analytics rawData'!A:A,'Data Analytics rawData'!E:E)} -> 1418 | H87: {=XLOOKUP(B87,'Data Analytics rawData'!A:A,'Data Analytics rawData'!B:B)} -> 108 | I87: {=XLOOKUP(B87,'Data Analytics rawData'!A:A,'Data Analytics rawData'!C:C)} -> 6 | J87: =E87/F87 -> 3329.7159 | K87: PlayArt Diwali Paint-Your-Own Rocket Kit | L87: Diwali Kit | M87: =F87/D87 -> 0.010204082
B88: Canvas and Stand | C88: Canvas & Stand | D88: {=XLOOKUP(B88,'Google analytics'!A:A,'Google analytics'!F:F)} -> 183 | E88: =D88*$C$13 -> 6217.7349 | F88: {=XLOOKUP(B88,'Data Analytics rawData'!A:A,'Data Analytics rawData'!D:D)} -> 105 | G88: {=XLOOKUP(B88,'Data Analytics rawData'!A:A,'Data Analytics rawData'!E:E)} -> 14112 | H88: {=XLOOKUP(B88,'Data Analytics rawData'!A:A,'Data Analytics rawData'!B:B)} -> 0 | I88: {=XLOOKUP(B88,'Data Analytics rawData'!A:A,'Data Analytics rawData'!C:C)} -> 0 | J88: =E88/F88 -> 59.216523 | K88: Dabble Christmas Crayons + Mini Starter Fun Pack | L88: CC8+SFP | M88: =F88/D88 -> 0.57377049
B89: Flip Flap Play Pack | Activity Book | | C89: =IFERROR(VLOOKUP(B89,K:L,2,0),"NA") -> FF Unicorn + Dino | D89: {=XLOOKUP(B89,'Google analytics'!A:A,'Google analytics'!F:F)} -> 196 | E89: =D89*$C$13 -> 6659.4319 | F89: {=XLOOKUP(B89,'Data Analytics rawData'!A:A,'Data Analytics rawData'!D:D)} -> 3 | G89: {=XLOOKUP(B89,'Data Analytics rawData'!A:A,'Data Analytics rawData'!E:E)} -> 2534.9999 | H89: {=XLOOKUP(B89,'Data Analytics rawData'!A:A,'Data Analytics rawData'!B:B)} -> 201 | I89: {=XLOOKUP(B89,'Data Analytics rawData'!A:A,'Data Analytics rawData'!C:C)} -> 10 | J89: =E89/F89 -> 2219.8106 | K89: Dabble Playtime Prep Kit | L89: SFP+CB+Canvas | M89: =F89/D89 -> 0.015306122
B90: Dabble Flip Flap Dress-Up Your Own Unicorn & Princesses | Travel-Friendly No Mess DIY Activity Set | C90: =IFERROR(VLOOKUP(B90,K:L,2,0),"NA") -> FF Unicorn | D90: {=XLOOKUP(B90,'Google analytics'!A:A,'Google analytics'!F:F)} -> 126 | E90: =D90*$C$13 -> 4281.0634 | F90: {=XLOOKUP(B90,'Data Analytics rawData'!A:A,'Data Analytics rawData'!D:D)} -> 0 | G90: {=XLOOKUP(B90,'Data Analytics rawData'!A:A,'Data Analytics rawData'!E:E)} -> 0 | H90: {=XLOOKUP(B90,'Data Analytics rawData'!A:A,'Data Analytics rawData'!B:B)} -> 127 | I90: {=XLOOKUP(B90,'Data Analytics rawData'!A:A,'Data Analytics rawData'!C:C)} -> 2 | J90: =E90/F90 -> #DIV/0! | K90: Dabble Reusable Colouring Pages + Glue Combo Kit | L90: DP+Glue | M90: =F90/D90 -> 0
B91: Numbers 1-10 Printable Activity Pack | C91: =IFERROR(VLOOKUP(B91,K:L,2,0),"NA") -> Activity Pack | D91: {=XLOOKUP(B91,'Google analytics'!A:A,'Google analytics'!F:F)} -> 196 | E91: =D91*$C$13 -> 6659.4319 | F91: {=XLOOKUP(B91,'Data Analytics rawData'!A:A,'Data Analytics rawData'!D:D)} -> 8 | G91: {=XLOOKUP(B91,'Data Analytics rawData'!A:A,'Data Analytics rawData'!E:E)} -> 792.00005 | H91: {=XLOOKUP(B91,'Data Analytics rawData'!A:A,'Data Analytics rawData'!B:B)} -> 179 | I91: {=XLOOKUP(B91,'Data Analytics rawData'!A:A,'Data Analytics rawData'!C:C)} -> 51 | J91: =E91/F91 -> 832.42899 | K91: Dabble 3 In 1 Easy-Clean Fun Pack | L91: Glue+FP3+B8 | M91: =F91/D91 -> 0.040816327
B92: Dabble Reusable Colouring Pages + Glue Combo Kit | C92: =IFERROR(VLOOKUP(B92,K:L,2,0),"NA") -> DP+Glue | D92: {=XLOOKUP(B92,'Google analytics'!A:A,'Google analytics'!F:F)} -> 87 | E92: =D92*$C$13 -> 2955.9723 | F92: {=XLOOKUP(B92,'Data Analytics rawData'!A:A,'Data Analytics rawData'!D:D)} -> 2 | G92: {=XLOOKUP(B92,'Data Analytics rawData'!A:A,'Data Analytics rawData'!E:E)} -> 1420.0001 | H92: {=XLOOKUP(B92,'Data Analytics rawData'!A:A,'Data Analytics rawData'!B:B)} -> 91 | I92: {=XLOOKUP(B92,'Data Analytics rawData'!A:A,'Data Analytics rawData'!C:C)} -> 9 | J92: =E92/F92 -> 1477.9862 | K92: Pet Paw Print Keep Sake Kit | L92: Pet Paw Kit | M92: =F92/D92 -> 0.022988506
B93: My Dabble ABC Trace & Colour Kit | Multi-Sensory Alphabet Learning for Kids - Crayons | C93: =IFERROR(VLOOKUP(B93,K:L,2,0),"NA") -> ABC Crayons | D93: {=XLOOKUP(B93,'Google analytics'!A:A,'Google analytics'!F:F)} -> 6 | E93: =D93*$C$13 -> 203.86016 | F93: {=XLOOKUP(B93,'Data Analytics rawData'!A:A,'Data Analytics rawData'!D:D)} -> 0 | G93: {=XLOOKUP(B93,'Data Analytics rawData'!A:A,'Data Analytics rawData'!E:E)} -> 0 | H93: {=XLOOKUP(B93,'Data Analytics rawData'!A:A,'Data Analytics rawData'!B:B)} -> 0 | I93: {=XLOOKUP(B93,'Data Analytics rawData'!A:A,'Data Analytics rawData'!C:C)} -> 8 | J93: =E93/F93 -> #DIV/0! | K93: Flip Flap Play Pack | Activity Book | | L93: FF Unicorn + Dino | M93: =F93/D93 -> 0
B94: Dabble Flip Flap Make Your Own Dinosaur | Travel-Friendly No Mess DIY Activity Set | C94: =IFERROR(VLOOKUP(B94,K:L,2,0),"NA") -> FF Dino | D94: {=XLOOKUP(B94,'Google analytics'!A:A,'Google analytics'!F:F)} -> 696 | E94: =D94*$C$13 -> 23647.779 | F94: {=XLOOKUP(B94,'Data Analytics rawData'!A:A,'Data Analytics rawData'!D:D)} -> 181 | G94: {=XLOOKUP(B94,'Data Analytics rawData'!A:A,'Data Analytics rawData'!E:E)} -> 844 | H94: {=XLOOKUP(B94,'Data Analytics rawData'!A:A,'Data Analytics rawData'!B:B)} -> 455 | I94: {=XLOOKUP(B94,'Data Analytics rawData'!A:A,'Data Analytics rawData'!C:C)} -> 12 | J94: =E94/F94 -> 130.65071 | K94: Dabble Essentials Pack | L94: SFP+CB+Apron | M94: =F94/D94 -> 0.26005747
B95: Palette & Brush | C95: =IFERROR(VLOOKUP(B95,K:L,2,0),"NA") -> P&B | D95: {=XLOOKUP(B95,'Google analytics'!A:A,'Google analytics'!F:F)} -> 26 | E95: =D95*$C$13 -> 883.39403 | F95: {=XLOOKUP(B95,'Data Analytics rawData'!A:A,'Data Analytics rawData'!D:D)} -> 1 | G95: {=XLOOKUP(B95,'Data Analytics rawData'!A:A,'Data Analytics rawData'!E:E)} -> 298.99998 | H95: {=XLOOKUP(B95,'Data Analytics rawData'!A:A,'Data Analytics rawData'!B:B)} -> 26 | I95: {=XLOOKUP(B95,'Data Analytics rawData'!A:A,'Data Analytics rawData'!C:C)} -> 5 | J95: =E95/F95 -> 883.39403 | K95: Dabble Christmas Crayons + My Swingin Jungle | L95: CC8+SJ | M95: =F95/D95 -> 0.038461538
B96: Baby&#39;s First Art Set | C96: =IFERROR(VLOOKUP(B96,K:L,2,0),"NA") -> B3+AR | D96: {=XLOOKUP(B96,'Google analytics'!A:A,'Google analytics'!F:F)} -> 6 | E96: =D96*$C$13 -> 203.86016 | F96: {=XLOOKUP(B96,'Data Analytics rawData'!A:A,'Data Analytics rawData'!D:D)} -> 0 | G96: {=XLOOKUP(B96,'Data Analytics rawData'!A:A,'Data Analytics rawData'!E:E)} -> 0 | H96: {=XLOOKUP(B96,'Data Analytics rawData'!A:A,'Data Analytics rawData'!B:B)} -> 0 | I96: {=XLOOKUP(B96,'Data Analytics rawData'!A:A,'Data Analytics rawData'!C:C)} -> 0 | J96: =E96/F96 -> #DIV/0! | K96: Dabble Flip Flap Make Your Own Dinosaur | Travel-Friendly No Mess DIY Activity Set | L96: FF Dino | M96: =F96/D96 -> 0
B97: Bake dough- (Green) | C97: =IFERROR(VLOOKUP(B97,K:L,2,0),"NA") -> NA | D97: NA | E97: =D97*$C$13 -> #VALUE! | F97: NA | G97: {=XLOOKUP(B97,'Data Analytics rawData'!A:A,'Data Analytics rawData'!E:E)} -> #N/A | H97: {=XLOOKUP(B97,'Data Analytics rawData'!A:A,'Data Analytics rawData'!B:B)} -> #N/A | I97: {=XLOOKUP(B97,'Data Analytics rawData'!A:A,'Data Analytics rawData'!C:C)} -> #N/A | J97: =E97/F97 -> #VALUE! | K97: Flip Flap Crayon Play Pack Dinosaur Themed | Activity Book with Crayons | | L97: Dino+B8 | M97: =F97/D97 -> #VALUE!
B98: Bakedough-Pizza Blue | C98: =IFERROR(VLOOKUP(B98,K:L,2,0),"NA") -> NA | D98: NA | E98: =D98*$C$13 -> #VALUE! | F98: NA | G98: {=XLOOKUP(B98,'Data Analytics rawData'!A:A,'Data Analytics rawData'!E:E)} -> #N/A | H98: {=XLOOKUP(B98,'Data Analytics rawData'!A:A,'Data Analytics rawData'!B:B)} -> #N/A | I98: {=XLOOKUP(B98,'Data Analytics rawData'!A:A,'Data Analytics rawData'!C:C)} -> #N/A | J98: =E98/F98 -> #VALUE! | K98: Flip Flap Crayon Play Pack Unicorn & Princesses Themed | Activity Book with Crayons | | L98: FF Unicorn+B8 | M98: =F98/D98 -> #VALUE!
B99: Bakedough-Pizza Green | C99: =IFERROR(VLOOKUP(B99,K:L,2,0),"NA") -> NA | D99: NA | E99: =D99*$C$13 -> #VALUE! | F99: NA | G99: {=XLOOKUP(B99,'Data Analytics rawData'!A:A,'Data Analytics rawData'!E:E)} -> #N/A | H99: {=XLOOKUP(B99,'Data Analytics rawData'!A:A,'Data Analytics rawData'!B:B)} -> #N/A | I99: {=XLOOKUP(B99,'Data Analytics rawData'!A:A,'Data Analytics rawData'!C:C)} -> #N/A | J99: =E99/F99 -> #VALUE! | K99: A-Z Alphabet Printable Activity Pack | L99: Activity Pack | M99: =F99/D99 -> #VALUE!
B100: Dabble Baby&#39;s First Big Colouring Pages | C100: =IFERROR(VLOOKUP(B100,K:L,2,0),"NA") -> DP | D100: {=XLOOKUP(B100,'Google analytics'!A:A,'Google analytics'!F:F)} -> 1 | E100: =D100*$C$13 -> 33.976693 | F100: {=XLOOKUP(B100,'Data Analytics rawData'!A:A,'Data Analytics rawData'!D:D)} -> 0 | G100: {=XLOOKUP(B100,'Data Analytics rawData'!A:A,'Data Analytics rawData'!E:E)} -> 0 | H100: {=XLOOKUP(B100,'Data Analytics rawData'!A:A,'Data Analytics rawData'!B:B)} -> 0 | I100: {=XLOOKUP(B100,'Data Analytics rawData'!A:A,'Data Analytics rawData'!C:C)} -> 0 | J100: =E100/F100 -> #DIV/0! | K100: Dabble Rakhi Playart Kit | DIY Rakhi + Washable Paints + Reusable Colouring Pages | L100: DIY+SFP+DP | M100: =F100/D100 -> 0
B101: Dabble Christmas Crayons | C101: =IFERROR(VLOOKUP(B101,K:L,2,0),"NA") -> CC8 | D101: NA | E101: =D101*$C$13 -> #VALUE! | F101: NA | G101: {=XLOOKUP(B101,'Data Analytics rawData'!A:A,'Data Analytics rawData'!E:E)} -> #N/A | H101: {=XLOOKUP(B101,'Data Analytics rawData'!A:A,'Data Analytics rawData'!B:B)} -> #N/A | I101: {=XLOOKUP(B101,'Data Analytics rawData'!A:A,'Data Analytics rawData'!C:C)} -> #N/A | J101: =E101/F101 -> #VALUE! | K101: My Dabble ABC Trace & Colour Kit | Multi-Sensory Alphabet Learning for Kids - Crayons | L101: ABC Crayons | M101: =F101/D101 -> #VALUE!
B102: Dabble Christmas Crayons + Mini Starter Fun Pack | C102: =IFERROR(VLOOKUP(B102,K:L,2,0),"NA") -> CC8+SFP | D102: NA | E102: =D102*$C$13 -> #VALUE! | F102: NA | G102: {=XLOOKUP(B102,'Data Analytics rawData'!A:A,'Data Analytics rawData'!E:E)} -> #N/A | H102: {=XLOOKUP(B102,'Data Analytics rawData'!A:A,'Data Analytics rawData'!B:B)} -> #N/A | I102: {=XLOOKUP(B102,'Data Analytics rawData'!A:A,'Data Analytics rawData'!C:C)} -> #N/A | J102: =E102/F102 -> #VALUE! | K102: My Dabble ABC Trace & Colour Kit | Multi-Sensory Alphabet Learning for Kids - Paints | L102: ABC Paint | M102: =F102/D102 -> #VALUE!
B103: Dabble Christmas Crayons + My Swingin Jungle | C103: =IFERROR(VLOOKUP(B103,K:L,2,0),"NA") -> CC8+SJ | D103: NA | E103: =D103*$C$13 -> #VALUE! | F103: NA | G103: {=XLOOKUP(B103,'Data Analytics rawData'!A:A,'Data Analytics rawData'!E:E)} -> #N/A | H103: {=XLOOKUP(B103,'Data Analytics rawData'!A:A,'Data Analytics rawData'!B:B)} -> #N/A | I103: {=XLOOKUP(B103,'Data Analytics rawData'!A:A,'Data Analytics rawData'!C:C)} -> #N/A | J103: =E103/F103 -> #VALUE! | K103: Dabble Flip Flap Dress-Up Your Own Unicorn & Princesses | Travel-Friendly No Mess DIY Activity Set | L103: FF Unicorn | M103: =F103/D103 -> #VALUE!
B104: Dabble Combo Pack | Crayons + Finger Paints + Art Roll | C104: =IFERROR(VLOOKUP(B104,K:L,2,0),"NA") -> B8+FP3+AR | D104: {=XLOOKUP(B104,'Google analytics'!A:A,'Google analytics'!F:F)} -> 35 | E104: =D104*$C$13 -> 1189.1843 | F104: {=XLOOKUP(B104,'Data Analytics rawData'!A:A,'Data Analytics rawData'!D:D)} -> 2 | G104: {=XLOOKUP(B104,'Data Analytics rawData'!A:A,'Data Analytics rawData'!E:E)} -> 3466 | H104: {=XLOOKUP(B104,'Data Analytics rawData'!A:A,'Data Analytics rawData'!B:B)} -> 33 | I104: {=XLOOKUP(B104,'Data Analytics rawData'!A:A,'Data Analytics rawData'!C:C)} -> 7 | J104: =E104/F104 -> 594.59213 | K104: Numbers 1-10 Printable Activity Pack | L104: Activity Pack | M104: =F104/D104 -> 0.057142857
B105: Dabble DINOSAUR STENCIL ART & CRAFT Kit - Pack of 1 | C105: =IFERROR(VLOOKUP(B105,K:L,2,0),"NA") -> Dino Kit | D105: {=XLOOKUP(B105,'Google analytics'!A:A,'Google analytics'!F:F)} -> 1 | E105: =D105*$C$13 -> 33.976693 | F105: {=XLOOKUP(B105,'Data Analytics rawData'!A:A,'Data Analytics rawData'!D:D)} -> 0 | G105: {=XLOOKUP(B105,'Data Analytics rawData'!A:A,'Data Analytics rawData'!E:E)} -> 0 | H105: {=XLOOKUP(B105,'Data Analytics rawData'!A:A,'Data Analytics rawData'!B:B)} -> 0 | I105: {=XLOOKUP(B105,'Data Analytics rawData'!A:A,'Data Analytics rawData'!C:C)} -> 1 | J105: =E105/F105 -> #DIV/0! | K105: Baby&#39;s First Art Set | L105: B3+AR | M105: =F105/D105 -> 0
B106: Dabble DINOSAUR STENCIL ART & CRAFT Kit - Pack of 10 | C106: =IFERROR(VLOOKUP(B106,K:L,2,0),"NA") -> Dino Kit | D106: NA | E106: =D106*$C$13 -> #VALUE! | F106: NA | G106: {=XLOOKUP(B106,'Data Analytics rawData'!A:A,'Data Analytics rawData'!E:E)} -> #N/A | H106: {=XLOOKUP(B106,'Data Analytics rawData'!A:A,'Data Analytics rawData'!B:B)} -> #N/A | I106: {=XLOOKUP(B106,'Data Analytics rawData'!A:A,'Data Analytics rawData'!C:C)} -> #N/A | J106: =E106/F106 -> #VALUE! | K106: Baby&#39;s Handprint And Footprint | L106: Canvas Kit | M106: =F106/D106 -> #VALUE!
B107: Dabble DINOSAUR STENCIL ART & CRAFT Kit - Pack of 5 | C107: =IFERROR(VLOOKUP(B107,K:L,2,0),"NA") -> Dino Kit | D107: NA | E107: =D107*$C$13 -> #VALUE! | F107: NA | G107: {=XLOOKUP(B107,'Data Analytics rawData'!A:A,'Data Analytics rawData'!E:E)} -> #N/A | H107: {=XLOOKUP(B107,'Data Analytics rawData'!A:A,'Data Analytics rawData'!B:B)} -> #N/A | I107: {=XLOOKUP(B107,'Data Analytics rawData'!A:A,'Data Analytics rawData'!C:C)} -> #N/A | J107: =E107/F107 -> #VALUE! | K107: Dabble Baby&#39;s First Big Colouring Pages | L107: DP | M107: =F107/D107 -> #VALUE!
B108: Dabble DINOSAUR STENCIL ART &amp; CRAFT Kit - Pack of 1 | C108: =IFERROR(VLOOKUP(B108,K:L,2,0),"NA") -> Dino Kit | D108: NA | E108: =D108*$C$13 -> #VALUE! | F108: NA | G108: {=XLOOKUP(B108,'Data Analytics rawData'!A:A,'Data Analytics rawData'!E:E)} -> #N/A | H108: {=XLOOKUP(B108,'Data Analytics rawData'!A:A,'Data Analytics rawData'!B:B)} -> #N/A | I108: {=XLOOKUP(B108,'Data Analytics rawData'!A:A,'Data Analytics rawData'!C:C)} -> #N/A | J108: =E108/F108 -> #VALUE! | K108: Dabble Combo Pack | Crayons + Finger Paints + Art Roll | L108: B8+FP3+AR | M108: =F108/D108 -> #VALUE!
B109: Dabble DINOSAUR STENCIL ART &amp; CRAFT Kit - Pack of 5 | C109: Dino Kit | D109: NA | E109: =D109*$C$13 -> #VALUE! | F109: NA | G109: {=XLOOKUP(B109,'Data Analytics rawData'!A:A,'Data Analytics rawData'!E:E)} -> #N/A | H109: {=XLOOKUP(B109,'Data Analytics rawData'!A:A,'Data Analytics rawData'!B:B)} -> #N/A | I109: {=XLOOKUP(B109,'Data Analytics rawData'!A:A,'Data Analytics rawData'!C:C)} -> #N/A | J109: =E109/F109 -> #VALUE! | K109: Dabble DINOSAUR STENCIL ART & CRAFT Kit - Pack of 1 | L109: Dino Kit | M109: =F109/D109 -> #VALUE!
...

Sheet Sheet9
A1: Products Name | B1: Apr | C1: May | D1: Jun | E1: Grand Total | G1: Product Name | H1: Apr | I1: May | J1: Jun | K1: Grand Total
A2: All In One Paint Kit | B2: 205.32 | C2: 191.467 | D2: 1231.677 | E2: 1628.464 | G2: dabble Sensory Playdough | H2: ₹15,089.60 | I2: ₹10,922.39 | J2: ₹9,838.09 | K2: ₹35,850.08
A3: All In One Paint Kit + Playart Crayons Combo | C3: 1192.312 | D3: 245.971 | E3: 1438.283 | G3: Magic Paint Dust – Baby’s First Painting Kit | H3: ₹10,277.79 | I3: ₹11,150.20 | J3: ₹11,835.25 | K3: ₹33,263.25
A4: A-Z Alphabet Printable Activity Pack | D4: 0 | E4: 0 | G4: Mini Starter Finger Painting Fun Pack | H4: ₹9,699.69 | I4: ₹11,058.35 | J4: ₹9,345.18 | K4: ₹30,103.23
A5: B8 | C5: 64.747 | D5: 0 | E5: 64.747 | G5: Babyâ€™s first handprint and footprint kit | H5: ₹1,160.67 | I5: ₹16,600.05 | J5: ₹9,654.80 | K5: ₹27,415.51
A6: Baby's First Art Set | B6: 2382.491 | C6: 3027.609 | D6: 2076.104 | E6: 7486.204 | G6: Dabble Finger Painting Fun Pack | H6: ₹7,590.02 | I6: ₹10,377.61 | J6: ₹5,103.18 | K6: ₹23,070.81
A7: Babys first handprint and footprint kit | B7: 2055.465 | C7: 26923.807 | D7: 3563.503 | E7: 32542.775 | G7: Dabble Flip Flap Make Your Own Dinosaur | Travel-Friendly No Mess DIY Activity Set - Dinosaur | H7: ₹5,106.52 | I7: ₹5,870.69 | J7: ₹8,659.37 | K7: ₹19,636.58
A8: Babys Starter Painting + Jumbo Brush Combo Kit | B8: 3138.673 | C8: 6113.258 | D8: 6768.898 | E8: 16020.829 | G8: Dabble Finger Paints For Toddlers | H8: ₹2,899.19 | I8: ₹5,482.37 | J8: ₹5,699.44 | K8: ₹14,081.00
A9: Creative Wonder Set | Dabble Play Art Chunkies + Sensory Play Dough | B9: 309.608 | C9: 1401.615 | D9: 643.171 | E9: 2354.394 | G9: Dabble Starter Painting + Chubby Brush Combo Kit | H9: ₹4,069.51 | I9: ₹5,478.88 | J9: ₹3,274.42 | K9: ₹12,822.82
A10: Dabble 3 In 1 Easy-Clean Fun Pack | C10: 315.768 | D10: 0 | E10: 315.768 | G10: Dabble Playart Chunkies | H10: ₹4,285.90 | I10: ₹3,898.73 | J10: ₹4,264.85 | K10: ₹12,449.49
A11: Dabble Art Roll | B11: 3639.873 | C11: 7650.734 | D11: 5753.636 | E11: 17044.243 | G11: Dabble Playart Finger Paints | H11: ₹2,344.89 | I11: ₹5,837.72 | J11: ₹3,736.06 | K11: ₹11,918.68
A12: Dabble Baby's First Art Set | Learning &amp; Development Friendly Combo Pack | D12: 571.309 | E12: 571.309 | G12: Babyâ€™s Starter Painting + Jumbo Brush Combo Kit | H12: ₹3,946.53 | I12: ₹4,322.09 | J12: ₹3,247.21 | K12: ₹11,515.82
A13: Dabble Baby's First Big Colouring Pages | B13: 729.146 | C13: 1423.032 | D13: 428.824 | E13: 2581.002 | G13: Canvas and Stand | H13: ₹3,327.82 | I13: ₹3,675.98 | J13: ₹3,907.77 | K13: ₹10,911.56
A14: Dabble Canvas Art Board | B14: 1003.083 | C14: 2511.524 | D14: 779.354 | E14: 4293.961 | G14: Dabble Art Roll | H14: ₹3,308.18 | I14: ₹5,768.12 | J14: ₹1,376.94 | K14: ₹10,453.24
A15: Dabble Christmas Crayons | B15: 565.999 | D15: 0 | E15: 565.999 | G15: Masterpiece Set | H15: ₹3,068.91 | I15: ₹5,332.28 | J15: ₹1,490.90 | K15: ₹9,892.09
A16: Dabble Christmas Crayons + Dabble Pages | B16: 156.916 | D16: 0 | E16: 156.916 | G16: My Dabble ABC Trace & Colour Kit | Multi-Sensory Alphabet Learning for Kids - Crayons | H16: ₹2,791.89 | I16: ₹3,721.26 | J16: ₹2,789.84 | K16: ₹9,302.99
A17: Dabble Chubby Brushes | B17: 420.552 | C17: 1765.452 | D17: 1464.979 | E17: 3650.983 | G17: Little Artist Combo Kit | H17: ₹2,039.12 | I17: ₹3,095.68 | J17: ₹2,902.16 | K17: ₹8,036.96
A18: Dabble Chunky Glue | B18: 1111.371 | C18: 249.051 | D18: 1127.962 | E18: 2488.384 | G18: Preschool Art and Craft Kit | H18: ₹1,931.32 | I18: ₹3,548.83 | J18: ₹1,958.56 | K18: ₹7,438.71
A19: Dabble Dessert Party Pretend Playdough Set | D19: 4108.948 | E19: 4108.948 | G19: Dabble Combo Pack | Crayons + Finger Paints + Art Roll | H19: ₹0.00 | I19: ₹6,913.86 | J19: ₹0.00 | K19: ₹6,913.86
A20: Dabble DINOSAUR STENCIL ART & CRAFT Kit - Pack of 1 | B20: 205.32 | D20: 302.127 | E20: 507.447 | G20: Dabble Reusable Colouring Pages Kit | H20: ₹1,632.65 | I20: ₹2,681.18 | J20: ₹2,167.51 | K20: ₹6,481.34
A21: Dabble DINOSAUR STENCIL ART & CRAFT Kit - Pack of 10 | C21: 714.136 | D21: 0 | E21: 714.136 | G21: Magic Paint Dust + PlayArt Roll â€“ Babyâ€™s First Painting Kit | H21: ₹3,170.51 | I21: ₹2,162.78 | J21: ₹929.08 | K21: ₹6,262.37
A22: Dabble DINOSAUR STENCIL ART & CRAFT Kit - Pack of 5 | B22: 363.062 | D22: 647.466 | E22: 1010.528 | G22: Dabble Painting Art Apron | H22: ₹1,286.97 | I22: ₹2,512.16 | J22: ₹1,696.81 | K22: ₹5,495.95
A23: Dabble DIY Sensory Playdough Kit | D23: 4283.671 | E23: 4283.671 | G23: Dabble Baby's First Big Colouring Pages | H23: ₹918.63 | I23: ₹2,069.89 | J23: ₹2,400.00 | K23: ₹5,388.53
A24: Dabble Essentials Pack | D24: 233.215 | E24: 233.215 | G24: Dabble Playart Crayons | H24: ₹1,196.67 | I24: ₹1,744.04 | J24: ₹2,313.13 | K24: ₹5,253.83
A25: Dabble Finger Painting Fun Pack | B25: 6901.333 | C25: 11844.587 | D25: 8362.185 | E25: 27108.105 | G25: My First Shape Explorer Stamp Kit | H25: ₹1,412.67 | I25: ₹2,778.39 | J25: ₹924.76 | K25: ₹5,115.81
A26: Dabble Finger Painting Super Pack | C26: 390.131 | D26: 0 | E26: 390.131 | G26: Magic Paint Dust + Jumbo Brush Combo Kit â€“ Babyâ€™s First Painting Kit | H26: ₹1,286.40 | I26: ₹2,366.33 | J26: ₹1,279.27 | K26: ₹4,932.00
A27: Dabble Finger Paints + Canvas Art Board | C27: 988.059 | D27: 520.51 | E27: 1508.569 | G27: Dabble Magic Bubbles POP n PLAY | H27: ₹972.19 | I27: ₹2,556.05 | J27: ₹1,306.89 | K27: ₹4,835.14
A28: Dabble Finger Paints For Toddlers | B28: 3660.771 | C28: 5752.859 | D28: 5078.156 | E28: 14491.786 | G28: Dabble DIY Sensory Playdough Kit | H28: ₹1,211.45 | I28: ₹1,799.99 | J28: ₹1,589.27 | K28: ₹4,600.71
A29: Dabble Flip Flap Dress-Up Your Own Unicorn & Princesses | Travel-Friendly No Mess DIY Activity Set - Unicorn & Princesses | C29: 86.376 | D29: 0 | E29: 86.376 | G29: My Dabble ABC Trace & Colour Kit | Multi-Sensory Alphabet Learning for Kids - Paints | H29: ₹1,520.97 | I29: ₹1,620.80 | J29: ₹1,016.38 | K29: ₹4,158.15
A30: Dabble Flip Flap Make Your Own Dinosaur | Travel-Friendly No Mess DIY Activity Set - Unicorn & Princesses | B30: 232.726 | D30: 0 | E30: 232.726 | G30: Baby's First Art Set | H30: ₹1,194.77 | I30: ₹1,053.75 | J30: ₹1,897.23 | K30: ₹4,145.75
A31: Dabble Gift Pack | Chunkies + Finger Paints | B31: 766.764 | C31: 1007.011 | D31: 247.918 | E31: 2021.693 | G31: My First Dabble Swinginâ€™ Jungle Adventure + Crayons Combo | H31: ₹1,187.25 | I31: ₹1,191.51 | J31: ₹1,650.67 | K31: ₹4,029.43
A32: Dabble Gift Set | Crayons + Finger Paints | D32: 169.188 | E32: 169.188 | G32: Dabble Canvas Art Board | H32: ₹1,781.27 | I32: ₹1,091.47 | J32: ₹960.21 | K32: ₹3,832.95
A33: Dabble Jumbo Paint Brush Set | B33: 1573.341 | C33: 2179.952 | D33: 1125.165 | E33: 4878.458 | G33: Dabble Sensory Rice Play Kit | H33: ₹1,922.63 | I33: ₹1,006.94 | J33: ₹500.57 | K33: ₹3,430.15
A34: Dabble Magic Bubbles POP n PLAY | B34: 626.58 | C34: 942.725 | D34: 994.291 | E34: 2563.596 | G34: Dabble Jumbo Paint Brush Set | H34: ₹1,473.82 | I34: ₹1,090.16 | J34: ₹615.36 | K34: ₹3,179.34
A35: Dabble Magic Dough Lab Colour Mixing STEAM Kit | D35: 1446.614 | E35: 1446.614 | G35: Sensory Discovery Kit | Dabble Sensory Rice + Sensory Play Dough | H35: ₹1,024.59 | I35: ₹1,577.16 | J35: ₹546.60 | K35: ₹3,148.36
A36: Dabble magic paint dust | C36: 205.32 | D36: 0 | E36: 205.32 | G36: Dabble Finger Paints + Sensory Playdough Combo | H36: ₹348.01 | I36: ₹1,049.61 | J36: ₹1,604.07 | K36: ₹3,001.69
A37: Dabble Painting Art Apron | B37: 1586.642 | C37: 1391.928 | D37: 2688.536 | E37: 5667.106 | G37: My First Dabble Swinginâ€™ Jungle Adventure + Mini Starter Fun Pack + Chubby Brushes Combo | H37: ₹1,067.02 | I37: ₹635.54 | J37: ₹1,105.34 | K37: ₹2,807.90
A38: Dabble Painting set | Finger Paints + Chubby Brushes | C38: 168.433 | D38: 427.419 | E38: 595.852 | G38: Dabble Chunky Glue | H38: ₹1,138.78 | I38: ₹781.68 | J38: ₹448.01 | K38: ₹2,368.47
A39: Dabble Playart Chunkies | B39: 5854.738 | C39: 6385.983 | D39: 4912.862 | E39: 17153.583 | G39: My First Dabble Swinginâ€™ Jungle Adventure | Reusable Story Card Set | H39: ₹292.55 | I39: ₹1,474.64 | J39: ₹418.40 | K39: ₹2,185.59
A40: Dabble Playart Crayons | B40: 1599.455 | C40: 2500.728 | D40: 2149.938 | E40: 6250.121 | G40: All In One Paint Kit | H40: ₹462.28 | I40: ₹1,217.72 | J40: ₹477.32 | K40: ₹2,157.31
A41: Dabble Playart Finger Paints | B41: 1007.927 | C41: 2989.387 | D41: 3962.847 | E41: 7960.161 | G41: Dabble Dessert Party Pretend Playdough Set | H41: ₹299.92 | I41: ₹524.73 | J41: ₹1,032.79 | K41: ₹1,857.44
A42: Dabble Playtime Prep Kit | D42: 156.916 | E42: 156.916 | G42: Dabble DINOSAUR STENCIL ART & CRAFT Kit - Pack of 1 | H42: ₹272.05 | I42: ₹1,280.99 | J42: ₹215.77 | K42: ₹1,768.82
A43: Dabble Reusable Colouring Pages + Crayons Combo Kit | B43: 394.285 | C43: 1066.767 | D43: 430.779 | E43: 1891.831 | G43: Imagination Spark Kit | Dabble Sensory Play Dough + Magic Paint Dust | H43: ₹909.15 | I43: ₹677.99 | J43: ₹149.88 | K43: ₹1,737.01
A44: Dabble Reusable Colouring Pages + Glue Combo Kit | D44: 323.733 | E44: 323.733 | G44: Little Makerâ€™s Set | Dabble Sensory Play Dough + Painting Apron | H44: ₹1,112.86 | I44: ₹387.18 | J44: ₹168.68 | K44: ₹1,668.72
A45: Dabble Reusable Colouring Pages + Mini Finger Paints Combo Kit | B45: 610.036 | C45: 1179.068 | D45: 450.594 | E45: 2239.698 | G45: Dabble Starter Finger Painting Fun Pack + Apron ComboKit | H45: ₹672.30 | I45: ₹620.39 | J45: ₹270.48 | K45: ₹1,563.18
A46: Dabble Reusable Colouring Pages Kit | B46: 1944.814 | C46: 1589.915 | D46: 1095.654 | E46: 4630.383 | G46: Dabble Chubby Brushes | H46: ₹354.18 | I46: ₹641.80 | J46: ₹550.98 | K46: ₹1,546.96
A47: Dabble Sensory Painting Kit | B47: 177 | D47: 428.482 | E47: 605.482 | G47: Creative Wonder Set | Dabble Play Art Chunkies + Sensory Play Dough | H47: ₹245.64 | I47: ₹924.62 | J47: ₹340.22 | K47: ₹1,510.47
A48: dabble Sensory Playdough | B48: 8544.833 | C48: 6897.984 | D48: 20577.612 | E48: 36020.429 | G48: Dabble Reusable Colouring Pages + Crayons Combo Kit | H48: ₹670.53 | I48: ₹70.51 | J48: ₹672.76 | K48: ₹1,413.80
A49: Dabble Sensory Rice | C49: 129.493 | D49: 0 | E49: 129.493 | G49: Toddler's First Painting Set | Finger Paints + Jumbo Brushes | H49: ₹662.82 | I49: ₹289.92 | J49: ₹400.79 | K49: ₹1,353.53
A50: Dabble Sensory Rice Play Kit | B50: 1810.604 | C50: 622.797 | D50: 2070.001 | E50: 4503.402 | G50: Toddlers First Colouring Set | Playart Crayons + Art Roll | H50: ₹448.02 | I50: ₹597.33 | J50: ₹307.08 | K50: ₹1,352.43
A51: Dabble Starter Finger Painting Fun Pack + Apron ComboKit | B51: 301.514 | C51: 570.247 | D51: 0 | E51: 871.761 | G51: Dabble Magic Dough Lab â€” Colour Mixing STEAM Kit | H51: ₹205.77 | I51: ₹680.79 | J51: ₹443.96 | K51: ₹1,330.52
A52: Dabble Starter Pack | Chunkies + Finger Paints + Art Roll | B52: 1847.434 | C52: 1267.096 | D52: 1477.265 | E52: 4591.795 | G52: Dabble Playtime Prep Kit | H52: ₹127.57 | I52: ₹753.38 | J52: ₹307.08 | K52: ₹1,188.03
A53: Dabble Starter Painting + Chubby Brush Combo Kit | B53: 2369.562 | C53: 3349.818 | D53: 4648.748 | E53: 10368.128 | G53: Dabble Starter Pack | Chunkies + Finger Paints + Art Roll | H53: ₹292.37 | I53: ₹757.49 | J53: ₹90.09 | K53: ₹1,139.96
A54: Dabble UNICORN STENCIL ART & CRAFT Kit - Pack of 1 | B54: 363.794 | C54: 386.887 | D54: 0 | E54: 750.681 | G54: My First Dabble Swinginâ€™ Jungle Adventure + Mini Starter Fun Pack Combo | H54: ₹423.38 | I54: ₹377.59 | J54: ₹327.07 | K54: ₹1,128.05
A55: Endless Creations Pack | Dabble Reusable Colouring Pages + Sensory Play Dough | B55: 1681.654 | C55: 567.084 | D55: 175.631 | E55: 2424.369 | G55: My First Dabble Puzzle Colouring Set - Emotions, Shapes & Colours | H55: ₹253.32 | I55: ₹226.57 | J55: ₹418.33 | K55: ₹898.22
A56: Flip Flap Crayon Play Pack Dinosaur Themed | Activity Book with Crayons | | C56: 254.88 | D56: 505.5 | E56: 760.38 | G56: Dabble UNICORN STENCIL ART & CRAFT Kit - Pack of 1 | H56: ₹59.02 | I56: ₹664.00 | J56: ₹173.52 | K56: ₹896.54
A57: Flip Flap Play Pack | Activity Book | | D57: 297.083 | E57: 297.083 | G57: Multi Sensory Painting Set | H57: ₹0.00 | I57: ₹559.52 | J57: ₹307.08 | K57: ₹866.60
A58: Imagination Spark Kit | Dabble Sensory Play Dough + Magic Paint Dust | B58: 224.015 | C58: 1610.783 | D58: 1342.643 | E58: 3177.441 | G58: Dabble Reusable Colouring Pages + Mini Finger Paints Combo Kit | H58: ₹188.80 | I58: ₹422.49 | J58: ₹231.48 | K58: ₹842.77
A59: Jumbo BrusH | B59: 100.961 | D59: 0 | E59: 100.961 | G59: Dabble Finger Paints + Canvas Art Board | H59: ₹0.00 | I59: ₹253.53 | J59: ₹479.11 | K59: ₹732.64
A60: Little Artist Combo Kit | B60: 2677.39 | C60: 4151.871 | D60: 3378.972 | E60: 10208.233 | G60: Dabble Painting set | Finger Paints + Chubby Brushes | H60: ₹0.00 | I60: ₹585.02 | J60: ₹139.47 | K60: ₹724.49
A61: Little Makers Set | Dabble Sensory Play Dough + Painting Apron | B61: 488.52 | C61: 175.631 | D61: 1778.501 | E61: 2442.652 | G61: My first dabble Touch & Feel Colouring pages for toddlers + Baby's First Finger Paints | H61: ₹270.28 | I61: ₹264.42 | J61: ₹179.13 | K61: ₹713.83
A62: Magic Paint Dust Babys First Painting Kit | B62: 11587.717 | C62: 38948.391 | D62: 18772.786 | E62: 69308.894 | G62: Endless Creations Pack | Dabble Reusable Colouring Pages + Sensory Play Dough | H62: ₹237.12 | I62: ₹390.76 | J62: ₹0.00 | K62: ₹627.87
A63: Magic Paint Dust + Jumbo Brush Combo Kit Babys First Painting Kit | B63: 1508.489 | C63: 3624.632 | D63: 2795.409 | E63: 7928.53 | G63: Dabble Gift Pack | Chunkies + Finger Paints | H63: ₹0.00 | I63: ₹541.27 | J63: ₹82.43 | K63: ₹623.69
A64: Magic Paint Dust + Jumbo Brush Combo Kit + PlayArt Roll Babys First Painting Kit | B64: 399.593 | D64: 1409.12 | E64: 1808.713 | G64: Dabble Gift Set | Crayons + Finger Paints | H64: ₹0.00 | I64: ₹162.41 | J64: ₹358.92 | K64: ₹521.33
A65: Magic Paint Dust + PlayArt Roll Babys First Painting Kit | B65: 1523.758 | C65: 4342.836 | D65: 3212.101 | E65: 9078.695 | G65: Dabble Sensory Painting Kit | H65: ₹0.00 | I65: ₹370.19 | J65: ₹135.14 | K65: ₹505.33
A66: Magic Paint Dust Green | C66: 40.309 | D66: 0 | E66: 40.309 | G66: Magic Paint Dust + Jumbo Brush Combo Kit + PlayArt Roll Babys First Painting Kit | H66: ₹254.88 | I66: ₹0.00 | J66: ₹216.66 | K66: ₹471.54
A67: Masterpiece Set | B67: 1897.034 | C67: 3099.806 | D67: 5426.638 | E67: 10423.478 | G67: Dabble 3 In 1 Easy-Clean Fun Pack | H67: ₹100.24 | I67: ₹0.00 | J67: ₹307.08 | K67: ₹407.32
A68: Mini Starter Finger Painting Fun Pack | B68: 6748.587 | C68: 16520.436 | D68: 14441.784 | E68: 37710.807 | G68: My dabble India Map Art | India maps for kids learning | H68: ₹0.00 | I68: ₹92.80 | J68: ₹277.62 | K68: ₹370.43
A69: Multi Sensory Painting Set | B69: 1342.621 | C69: 708.236 | D69: 466.855 | E69: 2517.712 | G69: Dabble DINOSAUR STENCIL ART & CRAFT Kit - Pack of 10 | H69: ₹0.00 | I69: ₹255.21 | J69: ₹95.14 | K69: ₹350.35
A70: My Dabble ABC Trace & Colour Kit | Multi-Sensory Alphabet Learning for Kids - Crayons | B70: 1897.252 | C70: 1250.256 | D70: 3435.615 | E70: 6583.123 | G70: Pet Paw Print Keep Sake Kit | H70: ₹0.00 | I70: ₹162.41 | J70: ₹136.11 | K70: ₹298.52
A71: My Dabble ABC Trace & Colour Kit | Multi-Sensory Alphabet Learning for Kids - Paints | B71: 215.751 | C71: 105.091 | D71: 673.402 | E71: 994.244 | G71: Dabble Finger Painting Super Pack | H71: ₹0.00 | I71: ₹116.07 | J71: ₹153.95 | K71: ₹270.01
A72: My Dabble ABC Trace &amp; Colour Kit | Multi-Sensory Alphabet Learning for Kids - Crayons | D72: 178.475 | E72: 178.475 | G72: Flip Flap Play Pack | Activity Book | | H72: ₹89.03 | I72: ₹173.96 | J72: ₹0.00 | K72: ₹262.98
A73: My Dabble ABC Trace &amp; Colour Kit | Multi-Sensory Alphabet Learning for Kids - Paints | C73: 129.493 | D73: 40.309 | E73: 169.802 | G73: My Dabble ABC Trace &amp; Colour Kit | Multi-Sensory Alphabet Learning for Kids - Crayons | H73: ₹248.75 | I73: ₹0.00 | J73: ₹0.00 | K73: ₹248.75
A74: My dabble India Map Art | India maps for kids learning | C74: 322.47 | D74: 0 | E74: 322.47 | G74: Dabble Reusable Colouring Pages + Glue Combo Kit | H74: ₹62.69 | I74: ₹97.92 | J74: ₹59.92 | K74: ₹220.52
A75: My First Dabble Art Set For Toddlers | B75: 189.744 | D75: 0 | E75: 189.744 | G75: My First Dabble Art Set For Toddlers | H75: ₹0.00 | I75: ₹0.00 | J75: ₹191.92 | K75: ₹191.92
A76: My First Dabble Puzzle Colouring Set - Emotions, Shapes & Colours | B76: 175.631 | C76: 233.215 | D76: 1149.084 | E76: 1557.93 | G76: Dabble Essentials Pack | H76: ₹0.00 | I76: ₹174.01 | J76: ₹0.00 | K76: ₹174.01
A77: My First Dabble Swingin Jungle Adventure | Reusable Story Card Set | B77: 1729.364 | C77: 527.539 | D77: 1009.915 | E77: 3266.818 | G77: sensory playdough | H77: ₹0.00 | I77: ₹0.00 | J77: ₹168.68 | K77: ₹168.68
A78: My First Dabble Swingin Jungle Adventure + Crayons Combo | B78: 3436.398 | C78: 2653.937 | D78: 3526.384 | E78: 9616.719 | G78: Dabble DINOSAUR STENCIL ART & CRAFT Kit - Pack of 5 | H78: ₹0.00 | I78: ₹158.68 | J78: ₹0.00 | K78: ₹158.68
A79: My First Dabble Swingin Jungle Adventure + Mini Starter Fun Pack + Chubby Brushes Combo | B79: 1204.484 | C79: 798.514 | D79: 1154.571 | E79: 3157.569 | G79: All In One Paint Kit + Playart Crayons Combo | H79: ₹63.25 | I79: ₹0.00 | J79: ₹85.12 | K79: ₹148.36
A80: My First Dabble Swingin Jungle Adventure + Mini Starter Fun Pack Combo | B80: 156.916 | C80: 233.18 | D80: 133.977 | E80: 524.073 | G80: Dabble pages | H80: ₹0.00 | I80: ₹0.00 | J80: ₹147.73 | K80: ₹147.73
A81: My First Shape Explorer Stamp Kit | C81: 1099.866 | D81: 2098.101 | E81: 3197.967 | G81: Dabble DINOSAUR STENCIL ART &amp; CRAFT Kit - Pack of 1 | H81: ₹142.83 | I81: ₹0.00 | J81: ₹0.00 | K81: ₹142.83
A82: Palette &amp; Brush | D82: 285.654 | E82: 285.654 | G82: Baby’s Starter Painting + Jumbo Brush Combo Kit | H82: ₹135.27 | I82: ₹0.00 | J82: ₹0.00 | K82: ₹135.27
A83: Playart Crayons Art Roll | C83: 233.215 | D83: 0 | E83: 233.215 | G83: Dabble Flip Flap Make Your Own Dinosaur | Travel-Friendly No Mess DIY Activity Set - Unicorn & Princesses | H83: ₹0.00 | I83: ₹124.00 | J83: ₹0.00 | K83: ₹124.00
A84: Preschool Art and Craft Kit | B84: 1846.582 | C84: 1913.32 | D84: 2598.903 | E84: 6358.805 | G84: chunkie | H84: ₹120.05 | I84: ₹0.00 | J84: ₹0.00 | K84: ₹120.05
A85: Sensory Discovery Kit | Dabble Sensory Rice + Sensory Play Dough | B85: 378.615 | C85: 1365.496 | D85: 1565.545 | E85: 3309.656 | G85: My Dabble ABC Trace &amp; Colour Kit | Multi-Sensory Alphabet Learning for Kids - Paints | H85: ₹40.31 | I85: ₹65.00 | J85: ₹0.00 | K85: ₹105.31
A86: STICKER + Color paper | C86: 53.265 | D86: 0 | E86: 53.265 | G86: Dabble UNICORN STENCIL ART & CRAFT Kit - Pack of 10 | H86: ₹0.00 | I86: ₹0.00 | J86: ₹95.14 | K86: ₹95.14
A87: Toddlers First Colouring Set | Playart Crayons + Art Roll | B87: 1086.662 | C87: 1351.029 | D87: 988.686 | E87: 3426.377 | G87: Brush brown flat | H87: ₹0.00 | I87: ₹0.00 | J87: ₹94.40 | K87: ₹94.40
A88: Toddler's First Painting Set | Finger Paints + Jumbo Brushes | B88: 175.631 | C88: 1295.803 | D88: 745.429 | E88: 2216.863 | G88: My First Dabble Swingin’ Jungle Adventure + Mini Starter Fun Pack Combo | H88: ₹89.03 | I88: ₹0.00 | J88: ₹0.00 | K88: ₹89.03
G89: My First Dabble Swingin’ Jungle Adventure + Crayons Combo | H89: ₹89.03 | I89: ₹0.00 | J89: ₹0.00 | K89: ₹89.03
G90: Magic Paint Dust – Baby’s First Painting Kit | H90: ₹89.03 | I90: ₹0.00 | J90: ₹0.00 | K90: ₹89.03
G91: Sensory Playdough green color | H91: ₹87.05 | I91: ₹0.00 | J91: ₹0.00 | K91: ₹87.05
G92: Sensory palydough green color | H92: ₹87.05 | I92: ₹0.00 | J92: ₹0.00 | K92: ₹87.05
G93: green color paint dust | H93: ₹0.00 | I93: ₹0.00 | J93: ₹81.88 | K93: ₹81.88
G94: Palette & Brush | H94: ₹0.00 | I94: ₹0.00 | J94: ₹74.04 | K94: ₹74.04
G95: Red Playdough | H95: ₹0.00 | I95: ₹0.00 | J95: ₹69.60 | K95: ₹69.60
G96: yellow playdough | H96: ₹0.00 | I96: ₹0.00 | J96: ₹65.94 | K96: ₹65.94
G97: My First Dabble Swingin’ Jungle Adventure + Mini Starter Fun Pack + Chubby Brushes Combo | H97: ₹65.59 | I97: ₹0.00 | J97: ₹0.00 | K97: ₹65.59
G98: A-Z Alphabet Printable Activity Pack | H98: ₹0.00 | I98: ₹63.45 | J98: ₹0.00 | K98: ₹63.45
G99: Red colour 5ml | H99: ₹0.00 | I99: ₹0.00 | J99: ₹63.42 | K99: ₹63.42
G100: Flip Flap Crayon Play Pack Unicorn & Princesses Themed | Activity Book with Crayons | | H100: ₹0.00 | I100: ₹0.00 | J100: ₹62.79 | K100: ₹62.79
...

Sheet Google analytics
A1: Item name | B1: Items viewed | C1: Items added to cart | D1: Items purchased | E1: Item revenue | F1: Sessions | G1: Conv %
A2: Magic Paint Dust – Baby’s First Painting Kit | B2: 7870 | C2: 781 | D2: 221 | E2: 192044 | F2: 7147 | G2: =IFERROR(F2/D2,"NA") -> 32.339367
A3: dabble Sensory Playdough | B3: 7039 | C3: 761 | D3: 214 | E3: 190336 | F3: 6541 | G3: =IFERROR(F3/D3,"NA") -> 30.565421
A4: Dabble Finger Painting Fun Pack | B4: 2509 | C4: 408 | D4: 122 | E4: 157681 | F4: 2341 | G4: =IFERROR(F4/D4,"NA") -> 19.188525
A5: Babyâ€™s first handprint and footprint kit | B5: 5707 | C5: 623 | D5: 160 | E5: 113540 | F5: 5252 | G5: =IFERROR(F5/D5,"NA") -> 32.825
A6: Mini Starter Finger Painting Fun Pack | B6: 2356 | C6: 636 | D6: 171 | E6: 101319 | F6: 2316 | G6: =IFERROR(F6/D6,"NA") -> 13.54386
A7: Dabble Starter Painting + Chubby Brush Combo Kit | B7: 1383 | C7: 279 | D7: 90 | E7: 90842 | F7: 1333 | G7: =IFERROR(F7/D7,"NA") -> 14.811111
A8: Little Artist Combo Kit | B8: 1235 | C8: 158 | D8: 47 | E8: 81477 | F8: 1113 | G8: =IFERROR(F8/D8,"NA") -> 23.680851
A9: Masterpiece Set | B9: 1018 | C9: 156 | D9: 41 | E9: 80419 | F9: 935 | G9: =IFERROR(F9/D9,"NA") -> 22.804878
A10: Babyâ€™s Starter Painting + Jumbo Brush Combo Kit | B10: 1094 | C10: 221 | D10: 75 | E10: 79281 | F10: 1055 | G10: =IFERROR(F10/D10,"NA") -> 14.066667
A11: Dabble Playart Chunkies | B11: 3746 | C11: 458 | D11: 129 | E11: 70820.999 | F11: 3472 | G11: =IFERROR(F11/D11,"NA") -> 26.914729
A12: Dabble Finger Paints For Toddlers | B12: 1426 | C12: 350 | D12: 101 | E12: 63589 | F12: 1422 | G12: =IFERROR(F12/D12,"NA") -> 14.079208
A13: My Dabble ABC Trace & Colour Kit | Multi-Sensory Alphabet Learning for Kids | B13: 2650 | C13: 330 | D13: 98 | E13: 58561.999 | F13: 2473 | G13: =IFERROR(F13/D13,"NA") -> 25.234694
... A100: Toddler&#39;s First Painting Set | Finger Paints + Jumbo Brushes | B100: 0 | C100: 0 | D100: 0 | E100: 0 | F100: 5 | G100: =IFERROR(F100/D100,"NA") -> NA

Sheet Data Analytics rawData
A1: Item name | B1: Items viewed | C1: Items added to cart | D1: Items purchased | E1: Item revenue | F1: Sessions
A2: Magic Paint Dust – Baby’s First Painting Kit | B2: 7870 | C2: 781 | D2: 221 | E2: 192044 | F2: 7147
A3: dabble Sensory Playdough | B3: 7039 | C3: 761 | D3: 214 | E3: 190336 | F3: 6541
A4: Dabble Finger Painting Fun Pack | B4: 2509 | C4: 408 | D4: 122 | E4: 157681 | F4: 2341
A5: Babyâ€™s first handprint and footprint kit | B5: 5707 | C5: 623 | D5: 160 | E5: 113540 | F5: 5252
A6: Mini Starter Finger Painting Fun Pack | B6: 2356 | C6: 636 | D6: 171 | E6: 101319 | F6: 2316
A7: Dabble Starter Painting + Chubby Brush Combo Kit | B7: 1383 | C7: 279 | D7: 90 | E7: 90842 | F7: 1333
A8: Little Artist Combo Kit | B8: 1235 | C8: 158 | D8: 47 | E8: 81477 | F8: 1113
A9: Masterpiece Set | B9: 1018 | C9: 156 | D9: 41 | E9: 80419 | F9: 935
A10: Babyâ€™s Starter Painting + Jumbo Brush Combo Kit | B10: 1094 | C10: 221 | D10: 75 | E10: 79281 | F10: 1055
A11: Dabble Playart Chunkies | B11: 3746 | C11: 458 | D11: 129 | E11: 70820.999 | F11: 3472
A12: Dabble Finger Paints For Toddlers | B12: 1426 | C12: 350 | D12: 101 | E12: 63589 | F12: 1422
A13: My Dabble ABC Trace & Colour Kit | Multi-Sensory Alphabet Learning for Kids | B13: 2650 | C13: 330 | D13: 98 | E13: 58561.999 | F13: 2473
... A100: Toddler&#39;s First Painting Set | Finger Paints + Jumbo Brushes | B100: 0 | C100: 0 | D100: 0 | E100: 0 | F100: 5

Sheet Easy view data
A1: Other cost | B1: Cost of primary package % | C1: Cost of material % | D1: Total production cost % | E1: Gross margin % | F1: SKU CODE | G1: PRODUCT NAME | H1: MRP with GST | I1: MRP without GST(RS) | J1: Total cost with tax/unit | K1: Total cost without tax | L1: Cost of material | M1: Cost of primary packageing | N1: Other miscellaneous | O1: Over headcost | P1: Cost of secondary packing | Q1: Transportation
A2: =SUM(N2:O2)/I2*100/100 -> 0.11893625 | B2: =M2/I2*100/100 -> 0.061202186 | C2: =L2/I2*100/100 -> 0.068954463 | D2: =SUM(A2:C2) -> 0.2490929 | E2: =100%-D2 -> 0.7509071 | F2: DPJCPOTH1010 | G2: B3 | H2: 549 | I2: =H2/1.12 -> 490.17857 | J2: =K2+K2*0.12 -> 136.752 | K2: =SUM(L2:O2) -> 122.1 | L2: 33.8 | M2: =29+1 -> 30 | N2: 3.4 | O2: =H2*0.1 -> 54.9 | P2: 5 | Q2: =H2*0.15 -> 82.35
A3: =SUM(N3:O3)/I3*100/100 -> 0.11933862 | B3: =M3/I3*100/100 -> 0.074832962 | C3: =L3/I3*100/100 -> 0.073386192 | D3: =SUM(A3:C3) -> 0.26755777 | E3: =100%-D3 -> 0.73244223 | F3: DPMCPOEI1011 | G3: B8 | H3: 449 | I3: =H3/1.12 -> 400.89286 | J3: =K3+K3*0.12 -> 120.13344 | K3: =SUM(L3:O3) -> 107.262 | L3: 29.42 | M3: 30 | N3: =L3*0.1 -> 2.942 | O3: =H3*0.1 -> 44.9 | P3: 5 | Q3: =H3*0.15 -> 67.35
A4: =SUM(N4:O4)/I4*100/100 -> 0.12254545 | B4: =M4/I4*100/100 -> 0.07 | C4: =L4/I4*100/100 -> 0.049272727 | D4: =SUM(A4:C4) -> 0.24181818 | E4: =100%-D4 -> 0.75818182 | F4: DPFPPOTH1004 | G4: FP3 | H4: 649 | I4: =H4/1.18 -> 550 | J4: =K4+K4*0.18 -> 156.94 | K4: =SUM(L4:O4) -> 133 | L4: 27.1 | M4: 38.5 | N4: 2.5 | O4: =H4*0.1 -> 64.9 | P4: 6.5 | Q4: =H4*0.15 -> 97.35
A5: =SUM(N5:O5)/I5*100/100 -> 0.12416908 | B5: =M5/I5*100/100 -> 0.038064516 | C5: =L5/I5*100/100 -> 0.072361958 | D5: =SUM(A5:C5) -> 0.23459555 | E5: =100%-D5 -> 0.76540445 | F5: DPFPPOEI1007 | G5: FP8 | H5: 899 | I5: =H5/1.18 -> 761.86441 | J5: =K5+K5*0.18 -> 210.9014 | K5: =SUM(L5:O5) -> 178.73 | L5: 55.13 | M5: =29 -> 29 | N5: 4.7 | O5: =H5*0.1 -> 89.9 | P5: 9.5 | Q5: =H5*0.15 -> 134.85
A6: =SUM(N6:O6)/I6*100/100 -> 0.12272788 | B6: =M6/I6*100/100 -> 0.053188648 | C6: =L6/I6*100/100 -> 0.11721202 | D6: =SUM(A6:C6) -> 0.29312855 | E6: =100%-D6 -> 0.70687145 | F6: DPFPMSFP1029 | G6: SFP | H6: 599 | I6: =H6/1.18 -> 507.62712 | J6: =K6+K6*0.18 -> 175.584 | K6: =SUM(L6:O6) -> 148.8 | L6: =24+29+1+2.5+3 -> 59.5 | M6: =27 -> 27 | N6: 2.4 | O6: =H6*0.1 -> 59.9 | P6: 6.5 | Q6: =H6*0.15 -> 89.85
A7: =SUM(N7:O7)/I7*100/100 -> 0.12621826 | B7: =M7/I7*100/100 -> 0.042405345 | C7: =L7/I7*100/100 -> 0.14816926 | D7: =SUM(A7:C7) -> 0.31679287 | E7: =100%-D7 -> 0.68320713 | F7: DPCBPOFR1009 | G7: CB | H7: 449 | I7: =H7/1.12 -> 400.89286 | J7: =K7+K7*0.18 -> 149.86 | K7: =SUM(L7:O7) -> 127 | L7: =57+2.4 -> 59.4 | M7: 17 | N7: 5.7 | O7: =H7*0.1 -> 44.9 | P7: 5 | Q7: =H7*0.15 -> 67.35
A8: =SUM(N8:O8)/I8*100/100 -> 0.12456914 | B8: =M8/I8*100/100 -> 0.038156313 | C8: =L8/I8*100/100 -> 0.13018036 | D8: =SUM(A8:C8) -> 0.29290581 | E8: =100%-D8 -> 0.70709419 | F8: DPJBPOTW1008 | G8: JB | H8: 499 | I8: =H8/1.12 -> 445.53571 | J8: =K8+K8*0.18 -> 153.99 | K8: =SUM(L8:O8) -> 130.5 | L8: =56+2 -> 58 | M8: 17 | N8: 5.6 | O8: =H8*0.1 -> 49.9 | P8: 5 | Q8: =H8*0.15 -> 74.85
A9: =SUM(N9:O9)/I9*100/100 -> 0.015969925 | B9: =M9/I9*100/100 -> 0 | C9: =L9/I9*100/100 -> 0.15969925 | D9: =SUM(A9:C9) -> 0.17566917 | E9: =100%-D9 -> 0.82433083 | F9: DPCP20CP1034 | G9: DP | H9: 399 | I9: =H9/1.18 -> 338.13559 | J9: =K9+K9 -> 118.8 | K9: =SUM(L9:O9) -> 59.4 | L9: 54 | M9: 0 | N9: =L9*0.1 -> 5.4 | O9: 0 | P9: 8.5 | Q9: =H9*0.15 -> 59.85
A10: =SUM(N10:O10)/I10*100/100 -> 0.11823647 | B10: =M10/I10*100/100 -> 0 | C10: =L10/I10*100/100 -> 0.10641283 | D10: =SUM(A10:C10) -> 0.2246493 | E10: =100%-D10 -> 0.7753507 | F10: DPSCMSJ1038 | G10: SJ | H10: 499 | I10: =H10/1.18 -> 422.88136 | J10: =K10+K10*0.18 -> 112.1 | K10: =SUM(L10:O10) -> 95 | L10: 45 | M10: 0 | N10: 0 | O10: 50 | P10: 8.5 | Q10: =H10*0.15 -> 74.85
A11: =SUM(N11:O11)/I11*100/100 -> 0.14552152 | B11: =M11/I11*100/100 -> 0.034254254 | C11: =L11/I11*100/100 -> 0.27911311 | D11: =SUM(A11:C11) -> 0.45888889 | E11: =100%-D11 -> 0.54111111 | F11: DPAKSTKI1003 | G11: STAMPKIT | H11: 999 | I11: =H11/1.18 -> 846.61017 | J11: =K11+K11*0.18 -> 458.43 | K11: =SUM(L11:O11) -> 388.5 | L11: =233.3+3 -> 236.3 | M11: 29 | N11: 23.3 | O11: =H11*0.1 -> 99.9 | P11: 12.5 | Q11: =H11*0.15 -> 149.85
A12: =SUM(N12:O12)/I12*100/100 -> 0.14045743 | B12: =M12/I12*100/100 -> 0.059098497 | C12: =L12/I12*100/100 -> 0.22949917 | D12: =SUM(A12:C12) -> 0.42905509 | E12: =100%-D12 -> 0.57094491 | F12: DPAKPSAK321310001002 | G12: PRESCHOOL KIT | H12: 599 | I12: =H12/1.18 -> 507.62712 | J12: =K12+K12*0.18 -> 257.004 | K12: =SUM(L12:O12) -> 217.8 | L12: =114.5+2 -> 116.5 | M12: 30 | N12: 11.4 | O12: =H12*0.1 -> 59.9 | P12: 12.5 | Q12: =H12*0.15 -> 89.85
A13: =SUM(N13:O13)/I13*100/100 -> 0.135499 | B13: =M13/I13*100/100 -> 0.075671343 | C13: =L13/I13*100/100 -> 0.17262525 | D13: =SUM(A13:C13) -> 0.38379559 | E13: =100%-D13 -> 0.61620441 | F13: A1KIT | G13: A1 | H13: 499 | I13: =H13/1.18 -> 422.88136 | J13: =K13+K13*0.18 -> 191.514 | K13: =SUM(L13:O13) -> 162.3 | L13: 73 | M13: 32 | N13: =L13*0.1 -> 7.3 | O13: 50 | P13: 12.5 | Q13: =H13*0.15 -> 74.85
A14: =SUM(N14:O14)/I14*100/100 -> 0.1416 | B14: =M14/I14*100/100 -> 0 | C14: =L14/I14*100/100 -> 0.23972632 | D14: =SUM(A14:C14) -> 0.38132632 | E14: =100%-D14 -> 0.61867368 | F14: DPFRCAB1014 | G14: CANVAS FRAME | H14: 190 | I14: =H14/1.18 -> 161.01695 | J14: =K14+K14*0.18 -> 72.452 | K14: =SUM(L14:O14) -> 61.4 | L14: 38.6 | M14: 0 | N14: 3.8 | O14: =H14*0.1 -> 19 | P14: 8.5 | Q14: =H14*0.15 -> 28.5
A15: =SUM(N15:O15)/I15*100/100 -> 0.13927039 | B15: =M15/I15*100/100 -> 0 | C15: =L15/I15*100/100 -> 0.22114449 | D15: =SUM(A15:C15) -> 0.36041488 | E15: =100%-D15 -> 0.63958512 | F15: DPAR20MTR1013 | G15: ARTROLL | H15: 699 | I15: =H15/1.18 -> 592.37288 | J15: =K15+K15*0.18 -> 251.93 | K15: =SUM(L15:O15) -> 213.5 | L15: =126+5 -> 131 | M15: 0 | N15: 12.6 | O15: =H15*0.1 -> 69.9 | P15: 8.5 | Q15: =H15*0.15 -> 104.85
A16: =SUM(N16:O16)/I16*100/100 -> 0.14220776 | B16: =M16/I16*100/100 -> 0 | C16: =L16/I16*100/100 -> 0.3020776 | D16: =SUM(A16:C16) -> 0.44428536 | E16: =100%-D16 -> 0.55571464 | F16: DPAKAP1030 | G16: APRON | H16: 799 | I16: =H16/1.12 -> 713.39286 | J16: =K16+K16*0.18 -> 374.001 | K16: =SUM(L16:O16) -> 316.95 | L16: 215.5 | M16: 0 | N16: =L16*0.1 -> 21.55 | O16: =H16*0.1 -> 79.9 | P16: 5 | Q16: =H16*0.15 -> 119.85
A17: =SUM(N17:O17)/I17*100/100 -> 0.13101253 | B17: =M17/I17*100/100 -> 0.029573935 | C17: =L17/I17*100/100 -> 0.13071679 | D17: =SUM(A17:C17) -> 0.29130326 | E17: =100%-D17 -> 0.70869674 | F17: DPGLPOTW1012 | G17: GLUE | H17: 399 | I17: =H17/1.18 -> 338.13559 | J17: =K17+K17*0.18 -> 116.23 | K17: =SUM(L17:O17) -> 98.5 | L17: 44.2 | M17: 10 | N17: 4.4 | O17: =H17*0.1 -> 39.9 | P17: 5 | Q17: =H17*0.15 -> 59.85
A18: =SUM(N18:O18)/I18*100/100 -> 0.14332189 | B18: =M18/I18*100/100 -> 0.054020029 | C18: =L18/I18*100/100 -> 0.17286409 | D18: =SUM(A18:C18) -> 0.37020601 | E18: =100%-D18 -> 0.62979399 | G18: DIWALI KIT | H18: 699 | I18: =H18/1.18 -> 592.37288 | J18: =K18+K18*0.18 -> 258.774 | K18: =SUM(L18:O18) -> 219.3 | L18: 102.4 | M18: 32 | N18: 15 | O18: =H18*0.1 -> 69.9 | P18: 12.5 | Q18: =H18*0.15 -> 104.85
A19: =SUM(N19:O19)/I19*100/100 -> 0.1428048 | B19: =M19/I19*100/100 -> 0 | C19: =L19/I19*100/100 -> 0.24804805 | D19: =SUM(A19:C19) -> 0.39085285 | E19: =100%-D19 -> 0.60914715 | F19: DPPGE1049 | G19: PUZZLE KIT | H19: 999 | I19: =H19/1.18 -> 846.61017 | J19: =K19+K19*0.18 -> 390.462 | K19: =SUM(L19:O19) -> 330.9 | L19: 210 | M19: 0 | N19: =L19*0.1 -> 21 | O19: =H19*0.1 -> 99.9 | P19: 12.5 | Q19: =H19*0.15 -> 149.85
A20: =SUM(N20:O20)/I20*100/100 -> 0.15045537 | B20: =M20/I20*100/100 -> 0.062331512 | C20: =L20/I20*100/100 -> 0.11821494 | D20: =SUM(A20:C20) -> 0.33100182 | E20: =100%-D20 -> 0.66899818 | G20: CC8 | H20: 549 | I20: =H20/1.18 -> 465.25424 | J20: =K20+K20*0.12 -> 172.48 | K20: =SUM(L20:O20) -> 154 | L20: =48+5+1+1 -> 55 | M20: 29 | N20: 15.1 | O20: =H20*0.1 -> 54.9 | P20: 5 | Q20: =H20*0.15 -> 82.35
A21: =SUM(N21:O21)/I21*100/100 -> 0.13074545 | B21: =M21/I21*100/100 -> 0.052727273 | C21: =L21/I21*100/100 -> 0.12745455 | D21: =SUM(A21:C21) -> 0.31092727 | E21: =100%-D21 -> 0.68907273 | F21: DPAKHFPK1006 | G21: Canvas kit | H21: 649 | I21: =H21/1.18 -> 550 | J21: =K21+K21*0.18 -> 201.7918 | K21: =SUM(L21:O21) -> 171.01 | L21: 70.1 | M21: 29 | N21: =L21*0.1 -> 7.01 | O21: =H21*0.1 -> 64.9 | P21: 12.5 | Q21: =H21*0.15 -> 97.35
A22: =SUM(N22:O22)/I22*100/100 -> 0.1350634 | B22: =M22/I22*100/100 -> 0.036751947 | C22: =L22/I22*100/100 -> 0.17719689 | D22: =SUM(A22:C22) -> 0.34901224 | E22: =100%-D22 -> 0.65098776 | F22: DPCPTF1050 | G22: Touch & Feel | H22: 899 | I22: =H22/1.18 -> 761.86441 | J22: =K22+K22*0.18 -> 313.762 | K22: =SUM(L22:O22) -> 265.9 | L22: 135 | M22: 28 | N22: 13 | O22: =H22*0.1 -> 89.9 | P22: 12.5 | Q22: =H22*0.15 -> 134.85
A23: =SUM(N23:O23)/I23*100/100 -> 0.13324659 | B23: =M23/I23*100/100 -> 0.030063694 | C23: =L23/I23*100/100 -> 0.15246588 | D23: =SUM(A23:C23) -> 0.31577616 | E23: =100%-D23 -> 0.68422384 | F23: DPIMAK1044 | G23: India Map | H23: 1099 | I23: =H23/1.18 -> 931.35593 | J23: =K23+K23*0.18 -> 347.038 | K23: =SUM(L23:O23) -> 294.1 | L23: 142 | M23: 28 | N23: =L23*0.1 -> 14.2 | O23: 109.9 | P23: 12.5 | Q23: =H23*0.15 -> 164.85
A24: =SUM(N24:O24)/I24*100/100 -> 0.14078324 | B24: =M24/I24*100/100 -> 0 | C24: =L24/I24*100/100 -> 0.22783242 | D24: =SUM(A24:C24) -> 0.36861566 | E24: =100%-D24 -> 0.63138434 | F24: DPFBPB81049 | G24: Flip book - Princess | H24: 549 | I24: =H24/1.18 -> 465.25424 | J24: =K24+K24*0.18 -> 202.37 | K24: =SUM(L24:O24) -> 171.5 | L24: 106 | M24: 0 | N24: =L24*0.1 -> 10.6 | O24: =H24*0.1 -> 54.9 | P24: 5.5 | Q24: =H24*0.15 -> 82.35
A25: 0.141 | B25: 0 | C25: 0.228 | D25: 0.369 | E25: 0.631 | F25: DPFBDB81048 | G25: Flip book - Dino | H25: 549 | I25: 465 | J25: 202.4 | K25: 171.5 | L25: 106 | M25: 0 | N25: 10.6 | O25: 54.9 | P25: 5.5 | Q25: 82.35
A26: =SUM(N26:O26)/I26*100/100 -> 0.13219154 | B26: =M26/I26*100/100 -> 0.021024499 | C26: =L26/I26*100/100 -> 0.14191537 | D26: =SUM(A26:C26) -> 0.2951314 | E26: =100%-D26 -> 0.7048686 | F26: DPBUBLE1047 | G26: Bubble | H26: 449 | I26: =H26/1.18 -> 380.50847 | J26: =K26+K26*0.18 -> 132.514 | K26: =SUM(L26:O26) -> 112.3 | L26: 54 | M26: 8 | N26: =L26*0.1 -> 5.4 | O26: =H26*0.1 -> 44.9 | P26: 5.5 | Q26: =H26*0.15 -> 67.35
A27: =SUM(N27:O27)/I27*100/100 -> 0.118 | B27: =M27/I27*100/100 -> 0 | C27: =L27/I27*100/100 -> 0 | D27: =SUM(A27:C27) -> 0.118 | E27: =100%-D27 -> 0.882 | F27: DMDN1074 | G27: Dino kit | H27: 399 | I27: =H27/1.18 -> 338.13559 | J27: =K27+K27*0.18 -> 47.082 | K27: =SUM(L27:O27) -> 39.9 | N27: =L27*0.1 -> 0 | O27: =H27*0.1 -> 39.9 | Q27: =H27*0.15 -> 59.85
A28: =SUM(N28:O28)/I28*100/100 -> 0.118 | B28: =M28/I28*100/100 -> 0 | C28: =L28/I28*100/100 -> 0 | D28: =SUM(A28:C28) -> 0.118 | E28: =100%-D28 -> 0.882 | F28: DMUN1073 | G28: Unicorn kit | H28: 399 | I28: =H28/1.18 -> 338.13559 | J28: =K28+K28*0.18 -> 47.082 | K28: =SUM(L28:O28) -> 39.9 | N28: =L28*0.1 -> 0 | O28: =H28*0.1 -> 39.9 | Q28: =H28*0.15 -> 59.85
A29: =SUM(N29:O29)/I29*100/100 -> 0.12968881 | B29: =M29/I29*100/100 -> 0.0083392226 | C29: =L29/I29*100/100 -> 0.1168881 | D29: =SUM(A29:C29) -> 0.25491614 | E29: =100%-D29 -> 0.74508386 | F29: DPDP1072 | G29: PlayArt Diwali Paint-Your-Own Rocket Kit | H29: 849 | I29: =H29/1.18 -> 719.49153 | J29: =K29+K29*0.18 -> 216.4238 | K29: =SUM(L29:O29) -> 183.41 | L29: 84.1 | M29: 6 | N29: =L29*0.1 -> 8.41 | O29: =H29*0.1 -> 84.9 | Q29: =H29*0.15 -> 127.35
A30: =SUM(N30:O30)/I30*100/100 -> 0.118 | B30: =M30/I30*100/100 -> 0 | C30: =L30/I30*100/100 -> 0 | D30: =SUM(A30:C30) -> 0.118 | E30: =100%-D30 -> 0.882 | G30: Pet Paw Print Keep Sake Kit | H30: 749 | I30: =H30/1.18 -> 634.74576 | J30: =K30+K30*0.18 -> 88.382 | K30: =SUM(L30:O30) -> 74.9 | N30: =L30*0.1 -> 0 | O30: =H30*0.1 -> 74.9 | Q30: =H30*0.15 -> 112.35
A31: =SUM(N31:O31)/I31*100/100 -> 0.118 | B31: =M31/I31*100/100 -> 0 | C31: =L31/I31*100/100 -> 0 | D31: =SUM(A31:C31) -> 0.118 | E31: =100%-D31 -> 0.882 | F31: DMDN1078 | G31: Dabble DINOSAUR STENCIL ART & CRAFT Kit - Pack of 10 | H31: 3999 | I31: =H31/1.18 -> 3388.9831 | J31: =K31+K31*0.18 -> 471.882 | K31: =SUM(L31:O31) -> 399.9 | N31: =L31*0.1 -> 0 | O31: =H31*0.1 -> 399.9 | Q31: =H31*0.15 -> 599.85
A32: =SUM(N32:O32)/I32*100/100 -> 0.118 | B32: =M32/I32*100/100 -> 0 | C32: =L32/I32*100/100 -> 0 | D32: =SUM(A32:C32) -> 0.118 | E32: =100%-D32 -> 0.882 | F32: DMDN1077 | G32: Dabble DINOSAUR STENCIL ART & CRAFT Kit - Pack of 5 | H32: 1995 | I32: =H32/1.18 -> 1690.678 | J32: =K32+K32*0.18 -> 235.41 | K32: =SUM(L32:O32) -> 199.5 | N32: =L32*0.1 -> 0 | O32: =H32*0.1 -> 199.5 | Q32: =H32*0.15 -> 299.25
A33: =SUM(N33:O33)/I33*100/100 -> 0.13310952 | B33: =M33/I33*100/100 -> 0.038315526 | C33: =L33/I33*100/100 -> 0.15109516 | D33: =SUM(A33:C33) -> 0.3225202 | E33: =100%-D33 -> 0.6774798 | F33: DMDP1079 | G33: Dabble mini's Dessert Party | H33: 599 | I33: =H33/1.18 -> 507.62712 | J33: =K33+K33*0.18 -> 193.1896 | K33: =SUM(L33:O33) -> 163.72 | L33: 76.7 | M33: 19.45 | N33: =L33*0.1 -> 7.67 | O33: =H33*0.1 -> 59.9 | P33: 7.5 | Q33: =H33*0.15 -> 89.85
A34: =SUM(N34:O34)/I34*100/100 -> 0.12558431 | B34: =M34/I34*100/100 -> 0.038315526 | C34: =L34/I34*100/100 -> 0.075843072 | D34: =SUM(A34:C34) -> 0.2397429 | E34: =100%-D34 -> 0.7602571 | F34: DMMDL1080 | G34: Dabble mini's Magic Dough Lab | H34: 599 | I34: =H34/1.18 -> 507.62712 | J34: =K34+K34*0.18 -> 143.606 | K34: =SUM(L34:O34) -> 121.7 | L34: 38.5 | M34: 19.45 | N34: =L34*0.1 -> 3.85 | O34: =H34*0.1 -> 59.9 | P34: 7.5 | Q34: =H34*0.15 -> 89.85
A35: =SUM(N35:O35)/I35*100/100 -> 0.12897262 | B35: =M35/I35*100/100 -> 0.038315526 | C35: =L35/I35*100/100 -> 0.10972621 | D35: =SUM(A35:C35) -> 0.27701436 | E35: =100%-D35 -> 0.72298564 | F35: DMSPD1081 | G35: Dabble Minis Sensory Play Dough Kit | H35: 599 | I35: =H35/1.18 -> 507.62712 | J35: =K35+K35*0.18 -> 165.9316 | K35: =SUM(L35:O35) -> 140.62 | L35: 55.7 | M35: 19.45 | N35: =L35*0.1 -> 5.57 | O35: =H35*0.1 -> 59.9 | P35: 7.5 | Q35: =H35*0.15 -> 89.85
A36: =SUM(N36:O36)/I36*100/100 -> 0.118 | B36: =M36/I36*100/100 -> 0 | C36: =L36/I36*100/100 -> 0 | D36: =SUM(A36:C36) -> 0.118 | E36: =100%-D36 -> 0.882 | F36: DCS1088 | G36: Canvas and Stand | H36: 134 | I36: =H36/1.18 -> 113.55932 | J36: =K36+K36*0.18 -> 15.812 | K36: =SUM(L36:O36) -> 13.4 | N36: =L36*0.1 -> 0 | O36: =H36*0.1 -> 13.4 | Q36: =H36*0.15 -> 20.1

Sheet Discount calculation
A1: Row Labels | B1: Lineitem quantity | C1: Discount Amount | D1: Discount/unit
A2: All In One Paint Kit | B2: 93 | C2: 538.23 | D2: =C2/B2 -> 5.7874194
A3: All In One Paint Kit + Playart Crayons Combo | B3: 7 | C3: 145.05 | D3: =C3/B3 -> 20.721429
A4: A-Z Alphabet Printable Activity Pack | B4: 171 | C4: 146.97 | D4: =C4/B4 -> 0.85947368
A5: Babyâ€™s first handprint and footprint kit | B5: 487 | C5: 3980.68 | D5: =C5/B5 -> 8.1738809
A6: Babyâ€™s Starter Painting + Jumbo Brush Combo Kit | B6: 351 | C6: 4294.99 | D6: =C6/B6 -> 12.236439
A7: Baby's First Art Set | B7: 71 | C7: 1260.76 | D7: =C7/B7 -> 17.757183
A8: Canvas and Stand | B8: 527 | C8: 814.62 | D8: =C8/B8 -> 1.5457685
A9: Creative Wonder Set | Dabble Play Art Chunkies + Sensory Play Dough | B9: 47 | C9: 1217.4 | D9: =C9/B9 -> 25.902128
A10: Dabble 3 In 1 Easy-Clean Fun Pack | B10: 12 | C10: 165.82 | D10: =C10/B10 -> 13.818333
A11: Dabble Art Roll | B11: 486 | C11: 4682.51 | D11: =C11/B11 -> 9.6347942
A12: Dabble Baby's First Big Colouring Pages | B12: 156 | C12: 2105.52 | D12: =C12/B12 -> 13.496923
A13: Dabble Canvas Art Board | B13: 180 | C13: 380.35 | D13: =C13/B13 -> 2.1130556
... A81: Toddler's First Painting Set | Finger Paints + Jumbo Brushes | B81: 53 | C81: 848.29 | D81: =C81/B81 -> 16.005472
